Workbook

Sheet Resumo
B2: ENERGISA RO 3ª Tranche - LPT AmL - Lote 1 - Erro 5,00%
B3: Lote | C3: Lote | D3: ODI | E3: Municípios | F3: SIGFI 80 | G3: SIGFI 160 | H3: UC | I3: Dias | J3: Equipe | K3: Custo Estimado (R$)
B4: Extrato | C4: 3 | D4: {=ROWS(_xlfn.UNIQUE(_xlfn._xlws.FILTER('Amostra 1_3_extrato_erro_5%'!$A:$A,'Amostra 1_3_extrato_erro_5%'!$V:$V="Selecionado")))} -> 45 | E4: {=ROWS(_xlfn.UNIQUE(_xlfn._xlws.FILTER('Amostra 1_3_extrato_erro_5%'!$C:$C,'Amostra 1_3_extrato_erro_5%'!$V:$V="Selecionado")))} -> 13 | F4: 44 | G4: 1 | H4: =SUM(F4:G4) -> 45 | I4: 14 | J4: 4 | K4: 296640
C5: 4 | D5: {=ROWS(_xlfn.UNIQUE(_xlfn._xlws.FILTER('Amostra 1_4_extrato_erro_5%'!$A:$A,'Amostra 1_4_extrato_erro_5%'!$V:$V="Selecionado")))} -> 22 | E5: {=ROWS(_xlfn.UNIQUE(_xlfn._xlws.FILTER('Amostra 1_4_extrato_erro_5%'!$C:$C,'Amostra 1_4_extrato_erro_5%'!$V:$V="Selecionado")))} -> 9 | F5: 22 | G5: =SUMIFS('Amostra 1_4_extrato_erro_5%'!$O$2:$O$108,'Amostra 1_4_extrato_erro_5%'!$V$2:$V$108,"Selecionado") -> 0 | H5: =SUM(F5:G5) -> 22 | I5: 7 | J5: 2 | K5: 85440
C6: 5 | D6: {=ROWS(_xlfn.UNIQUE(_xlfn._xlws.FILTER('Amostra 1_5_extrato_erro_5%'!$A:$A,'Amostra 1_5_extrato_erro_5%'!$V:$V="Selecionado")))} -> 15 | E6: {=ROWS(_xlfn.UNIQUE(_xlfn._xlws.FILTER('Amostra 1_5_extrato_erro_5%'!$C:$C,'Amostra 1_5_extrato_erro_5%'!$V:$V="Selecionado")))} -> 9 | F6: 15 | G6: =SUMIFS('Amostra 1_5_extrato_erro_5%'!$O$2:$O$108,'Amostra 1_5_extrato_erro_5%'!$V$2:$V$108,"Selecionado") -> 0 | H6: =SUM(F6:G6) -> 15 | I6: 5 | J6: 2 | K6: 66240
C7: 6 | D7: {=ROWS(_xlfn.UNIQUE(_xlfn._xlws.FILTER('Amostra 1_6_extrato_erro_5%'!$A:$A,'Amostra 1_6_extrato_erro_5%'!$V:$V="Selecionado")))} -> 12 | E7: {=ROWS(_xlfn.UNIQUE(_xlfn._xlws.FILTER('Amostra 1_6_extrato_erro_5%'!$C:$C,'Amostra 1_6_extrato_erro_5%'!$V:$V="Selecionado")))} -> 8 | F7: 12 | G7: 0 | H7: =SUM(F7:G7) -> 12 | I7: 4 | J7: 2 | K7: 56640
L57: =12/40 -> 0.3

Sheet Dimensionamento_Inspecao
B2: RELATÓRIO TÉCNICO CONSOLIDADO — VALIDAÇÃO DA AMOSTRA, ANÁLISE LOGÍSTICA E DIMENSIONAMENTO DE EQUIPES
B3: Inspeção física de unidades consumidoras (UCs) — Estado de Rondônia | Amostras: 1_3, 1_4, 1_5 e 1_6 (extrato, erro 5%) | Referência histórica: Contrato ECM-015/2024, 2ª tranche
B5: 1. RESUMO EXECUTIVO
B6: Indicador-chave | D6: Valor | E6: Unidade / observação
B7: AMOSTRA SELECIONADA PARA A INSPEÇÃO | D7: {=INDEX($B$123:$B$126,$D$140)} -> Amostra 1_3_extrato_erro_5% | E7: eleita entre as 4 alternativas
B8: UCs a inspecionar | D8: =C127 -> 45 | E8: UCs
B9: Municípios abrangidos | D9: =D127 -> 13 | E9: municípios
B10: Clusters logísticos ativos | D10: =E127 -> 4 | E10: agrupamentos geográficos
B11: Município mais distante da capital | D11: {=INDEX($J$103:$J$106,$D$140)} -> 747 | E11: km rodoviários estimados
B12: Produtividade média bruta histórica (Rondônia) | D12: =D39 -> 1.125 | E12: UC / equipe / dia
B13: Produtividade líquida de inspeção (base de cálculo) | D13: =D42 -> 1.5 | E13: UC / equipe / dia
B14: Produtividade ajustada da amostra selecionada | D14: =P127 -> 1 | E14: UC / equipe / dia
B15: EQUIPES RECOMENDADAS | D15: =C147 -> 4 | E15: equipes
B16: PRAZO RECOMENDADO — dias de campo | D16: =G147 -> 13 | E16: dias de execução
B17: PRAZO TOTAL RECOMENDADO | D17: =I147 -> 14 | E17: dias corridos (campo + mobilização)
B18: Score da amostra selecionada na matriz de decisão | D18: =MAX(I138:L138) -> 0.65 | E18: de 0 a 1
B20: {="SÍNTESE: as abas 1_3, 1_4, 1_5 e 1_6 são quatro desenhos amostrais alternativos para o mesmo universo, e não parcelas de um mesmo escopo. Dimensionadas isoladamente, exigem "&I123&", "&I124&", "&I125&" e "&I126&" equipe-dias e prazos ótimos de "&O123&", "&O124&", "&O125&" e "&O126&" dias, respectivamente. Como todas percorrem os mesmos "&D60&" clusters logísticos, o custo de deslocamento é quase fixo e as amostras menores tornam-se as menos eficientes: o esforço por UC vai de "&TEXT(Q123,"0,00")&" na 1_3 a "&TEXT(Q126,"0,00")&" equipe-dias na 1_6. Pela matriz de decisão ponderada, recomenda-se a "&INDEX($B$123:$B$126,$D$140)&" ("&C127&" UCs em "&D127&" municípios), executada por "&C147&" equipes em "&I147&" dias corridos."} -> SÍNTESE: as abas 1_3, 1_4, 1_5 e 1_6 são quatro desenhos amostrais alternativos para o mesmo universo, e não parcelas de um mesmo escopo. Dimensionadas isoladamente, exigem 45, 28, 23 e 23 equipe-dias e prazos ótimos de 14, 9, 8 e 8 dias, respectivamente. Como todas percorrem os mesmos 4 clusters logísticos, o custo de deslocamento é quase fixo e as amostras menores tornam-se as menos eficientes: o esforço por UC vai de 1,00 na 1_3 a 1,92 equipe-dias na 1_6. Pela matriz de decisão ponderada, recomenda-se a Amostra 1_3_extrato_erro_5% (45 UCs em 13 municípios), executada por 4 equipes em 14 dias corridos.
B22: 2. METODOLOGIA UTILIZADA
B23: Etapa 1 — Extração da amostra: leitura das abas "Amostra 1_3", "1_4", "1_5" e "1_6" (extrato, erro 5%), filtrando exclusivamente os registros cuja coluna V (STATUS) contém o valor "Selecionado".
B24: Etapa 2 — Validação: verificação de duplicidade de código de UC, ausência de município, ausência de identificador de UC, ausência de coordenadas geográficas e divergência de grafia de municípios.
B25: Etapa 3 — Georreferenciamento: cálculo do centroide (média das coordenadas das UCs selecionadas) de cada município a partir das colunas X (Latitude_UC) e Y (Longitude_UC).
B26: Etapa 4 — Distâncias: distância geodésica capital–município pela fórmula de Haversine (raio 6.371 km) e conversão para distância rodoviária por fator de sinuosidade calibrado para a malha de Rondônia.
B27: Etapa 5 — Clusterização logística: agrupamento dos municípios por eixo rodoviário e proximidade, permitindo roteirização encadeada e diluição do deslocamento entre várias UCs.
B28: Etapa 6 — Produtividade: extração dos indicadores históricos de Rondônia (produtividade por equipe e produtividade diária) e segregação entre produtividade bruta e produtividade líquida de inspeção (expurgados os dias de deslocamento).
B29: Etapa 7 — Dimensionamento independente: para cada uma das quatro amostras, cálculo do esforço em equipe-dias (inspeção + deslocamento), do caminho crítico por cluster e do prazo com 2, 3, 4 e com o número ótimo de equipes.
B30: Etapa 8 — Seleção da amostra: matriz de decisão multicritério ponderada (robustez amostral, eficiência logística, prazo, esforço total e concentração geográfica) para eleger, entre as quatro alternativas, a mais adequada à execução da inspeção.
B32: 3. HISTÓRICO DE REFERÊNCIA — RONDÔNIA, CONTRATO ECM-015/2024 (2ª TRANCHE)
B33: Parâmetro histórico | D33: Valor | E33: Unidade
B34: UCs inspecionadas na 2ª tranche | D34: 18 | E34: UCs
B35: Equipes mobilizadas | D35: 2 | E35: equipes
B36: Dias de execução | D36: 8 | E36: dias
B37: Municípios abrangidos | D37: 3 | E37: municípios
B38: Produtividade média por equipe = 18 ÷ 2 | D38: =D34/D35 -> 9 | E38: UC / equipe
B39: Produtividade média por dia (bruta) = 18 ÷ (2 × 8) | D39: =D34/(D35*D36) -> 1.125 | E39: UC / equipe / dia
B40: Dias de deslocamento embutidos no histórico (ida e volta à capital) | D40: =D56 -> 2 | E40: dias / equipe
B41: Dias efetivos de inspeção por equipe = 8 − 2 | D41: =D36-D40 -> 6 | E41: dias / equipe
B42: Produtividade líquida de inspeção = 18 ÷ (2 × 6) | D42: =D34/(D35*D41) -> 1.5 | E42: UC / equipe / dia
B43: Dispersão geográfica histórica = 3 municípios ÷ 18 UCs | D43: =D37/D34 -> 0.16666667 | E43: municípios / UC
B44: UCs por município no histórico = 18 ÷ 3 | D44: =D34/D37 -> 6 | E44: UCs / município
B45: Esforço total histórico = 2 equipes × 8 dias | D45: =D35*D36 -> 16 | E45: equipe-dias
B47: 4. PREMISSAS E PARÂMETROS DE PLANEJAMENTO
B48: Parâmetro | D48: Valor | E48: Unidade / justificativa
B49: Capital do estado — base de partida e retorno das equipes | D49: Porto Velho / RO | E49: sede logística única
B50: Latitude da capital | D50: -8.7612 | E50: graus decimais
B51: Longitude da capital | D51: -63.9004 | E51: graus decimais
B52: Jornada diária de campo | D52: 8 | E52: horas / dia
B53: Velocidade média de deslocamento rodoviário | D53: 60 | E53: km/h — mescla de BR-364 pavimentada e vicinais não pavimentadas
B54: Alcance por dia dedicado a deslocamento = jornada × velocidade | D54: =D52*D53 -> 480 | E54: km / dia
B55: Fator de sinuosidade rodoviária (rodoviária ÷ geodésica) | D55: 1.35 | E55: calibrado para a malha viária de Rondônia
B56: Dias fixos de deslocamento por equipe (ida e volta à capital) | D56: 2 | E56: dias — expurgo aplicado ao histórico de RO
B57: Acréscimo de rota para deslocamentos intra-cluster | D57: 0.3 | E57: trechos entre municípios e acessos rurais às UCs
B58: Dias de mobilização / desmobilização | D58: 1 | E58: dias — logística, briefing e fechamento
B59: Produtividade líquida de inspeção adotada (do histórico de RO) | D59: =D42 -> 1.5 | E59: UC / equipe / dia
B60: Clusters logísticos identificados | D60: =COUNTA(B112:B115) -> 4 | E60: agrupamentos
B62: 5. VALIDAÇÃO DOS DADOS — AS QUATRO ABAS
B63: Verificação | D63: Am. 1_3 | E63: Am. 1_4 | F63: Am. 1_5 | G63: Am. 1_6 | H63: União das 4 abas (referência) | I63: Unidade | J63: Diagnóstico
B64: Registros totais na aba (base de sorteio) | D64: =COUNTA('Amostra 1_3_extrato_erro_5%'!$A$2:$A$863) -> 862 | E64: =COUNTA('Amostra 1_4_extrato_erro_5%'!$A$2:$A$863) -> 862 | F64: =COUNTA('Amostra 1_5_extrato_erro_5%'!$A$2:$A$863) -> 862 | G64: =COUNTA('Amostra 1_6_extrato_erro_5%'!$A$2:$A$863) -> 862 | H64: =SUM(D64:G64) -> 3448 | I64: registros | J64: Referência
B65: Registros com STATUS = "Selecionado" (universo de inspeção) | D65: =COUNTIF('Amostra 1_3_extrato_erro_5%'!$V$2:$V$863,"Selecionado") -> 45 | E65: =COUNTIF('Amostra 1_4_extrato_erro_5%'!$V$2:$V$863,"Selecionado") -> 22 | F65: =COUNTIF('Amostra 1_5_extrato_erro_5%'!$V$2:$V$863,"Selecionado") -> 15 | G65: =COUNTIF('Amostra 1_6_extrato_erro_5%'!$V$2:$V$863,"Selecionado") -> 12 | H65: =SUM(D65:G65) -> 94 | I65: UCs | J65: Universo de inspeção
B66: Códigos de UC distintos entre os selecionados | D66: {=ROWS(_xlfn.UNIQUE(_xlfn._xlws.FILTER('Amostra 1_3_extrato_erro_5%'!$A$2:$A$863,'Amostra 1_3_extrato_erro_5%'!$V$2:$V$863="Selecionado")))} -> 45 | E66: {=ROWS(_xlfn.UNIQUE(_xlfn._xlws.FILTER('Amostra 1_4_extrato_erro_5%'!$A$2:$A$863,'Amostra 1_4_extrato_erro_5%'!$V$2:$V$863="Selecionado")))} -> 22 | F66: {=ROWS(_xlfn.UNIQUE(_xlfn._xlws.FILTER('Amostra 1_5_extrato_erro_5%'!$A$2:$A$863,'Amostra 1_5_extrato_erro_5%'!$V$2:$V$863="Selecionado")))} -> 15 | G66: {=ROWS(_xlfn.UNIQUE(_xlfn._xlws.FILTER('Amostra 1_6_extrato_erro_5%'!$A$2:$A$863,'Amostra 1_6_extrato_erro_5%'!$V$2:$V$863="Selecionado")))} -> 12 | H66: =SUM(D66:G66) -> 94 | I66: UCs | J66: =IF(H66=H65,"OK — integridade confirmada","ATENÇÃO") -> OK — integridade confirmada
B67: Registros duplicados (mesma UC selecionada mais de uma vez) | D67: =D65-D66 -> 0 | E67: =E65-E66 -> 0 | F67: =F65-F66 -> 0 | G67: =G65-G66 -> 0 | H67: =SUM(D67:G67) -> 0 | I67: ocorrências | J67: =IF(H67=0,"OK — sem duplicidade","ATENÇÃO") -> OK — sem duplicidade
B68: Selecionados sem município identificado | D68: =COUNTIFS('Amostra 1_3_extrato_erro_5%'!$V$2:$V$863,"Selecionado",'Amostra 1_3_extrato_erro_5%'!$C$2:$C$863,"") -> 0 | E68: =COUNTIFS('Amostra 1_4_extrato_erro_5%'!$V$2:$V$863,"Selecionado",'Amostra 1_4_extrato_erro_5%'!$C$2:$C$863,"") -> 0 | F68: =COUNTIFS('Amostra 1_5_extrato_erro_5%'!$V$2:$V$863,"Selecionado",'Amostra 1_5_extrato_erro_5%'!$C$2:$C$863,"") -> 0 | G68: =COUNTIFS('Amostra 1_6_extrato_erro_5%'!$V$2:$V$863,"Selecionado",'Amostra 1_6_extrato_erro_5%'!$C$2:$C$863,"") -> 0 | H68: =SUM(D68:G68) -> 0 | I68: registros | J68: =IF(H68=0,"OK — sem lacuna","ATENÇÃO") -> OK — sem lacuna
B69: Selecionados sem identificação de UC | D69: =COUNTIFS('Amostra 1_3_extrato_erro_5%'!$V$2:$V$863,"Selecionado",'Amostra 1_3_extrato_erro_5%'!$A$2:$A$863,"") -> 0 | E69: =COUNTIFS('Amostra 1_4_extrato_erro_5%'!$V$2:$V$863,"Selecionado",'Amostra 1_4_extrato_erro_5%'!$A$2:$A$863,"") -> 0 | F69: =COUNTIFS('Amostra 1_5_extrato_erro_5%'!$V$2:$V$863,"Selecionado",'Amostra 1_5_extrato_erro_5%'!$A$2:$A$863,"") -> 0 | G69: =COUNTIFS('Amostra 1_6_extrato_erro_5%'!$V$2:$V$863,"Selecionado",'Amostra 1_6_extrato_erro_5%'!$A$2:$A$863,"") -> 0 | H69: =SUM(D69:G69) -> 0 | I69: registros | J69: =IF(H69=0,"OK — sem lacuna","ATENÇÃO") -> OK — sem lacuna
B70: Selecionados sem latitude | D70: =COUNTIFS('Amostra 1_3_extrato_erro_5%'!$V$2:$V$863,"Selecionado",'Amostra 1_3_extrato_erro_5%'!$X$2:$X$863,"") -> 0 | E70: =COUNTIFS('Amostra 1_4_extrato_erro_5%'!$V$2:$V$863,"Selecionado",'Amostra 1_4_extrato_erro_5%'!$X$2:$X$863,"") -> 0 | F70: =COUNTIFS('Amostra 1_5_extrato_erro_5%'!$V$2:$V$863,"Selecionado",'Amostra 1_5_extrato_erro_5%'!$X$2:$X$863,"") -> 0 | G70: =COUNTIFS('Amostra 1_6_extrato_erro_5%'!$V$2:$V$863,"Selecionado",'Amostra 1_6_extrato_erro_5%'!$X$2:$X$863,"") -> 0 | H70: =SUM(D70:G70) -> 0 | I70: registros | J70: =IF(H70=0,"OK — 100% georreferenciado","ATENÇÃO") -> OK — 100% georreferenciado
B71: Selecionados sem longitude | D71: =COUNTIFS('Amostra 1_3_extrato_erro_5%'!$V$2:$V$863,"Selecionado",'Amostra 1_3_extrato_erro_5%'!$Y$2:$Y$863,"") -> 0 | E71: =COUNTIFS('Amostra 1_4_extrato_erro_5%'!$V$2:$V$863,"Selecionado",'Amostra 1_4_extrato_erro_5%'!$Y$2:$Y$863,"") -> 0 | F71: =COUNTIFS('Amostra 1_5_extrato_erro_5%'!$V$2:$V$863,"Selecionado",'Amostra 1_5_extrato_erro_5%'!$Y$2:$Y$863,"") -> 0 | G71: =COUNTIFS('Amostra 1_6_extrato_erro_5%'!$V$2:$V$863,"Selecionado",'Amostra 1_6_extrato_erro_5%'!$Y$2:$Y$863,"") -> 0 | H71: =SUM(D71:G71) -> 0 | I71: registros | J71: =IF(H71=0,"OK — 100% georreferenciado","ATENÇÃO") -> OK — 100% georreferenciado
B72: Municípios distintos na amostra selecionada | D72: {=ROWS(_xlfn.UNIQUE(_xlfn._xlws.FILTER('Amostra 1_3_extrato_erro_5%'!$C$2:$C$863,'Amostra 1_3_extrato_erro_5%'!$V$2:$V$863="Selecionado")))} -> 13 | E72: {=ROWS(_xlfn.UNIQUE(_xlfn._xlws.FILTER('Amostra 1_4_extrato_erro_5%'!$C$2:$C$863,'Amostra 1_4_extrato_erro_5%'!$V$2:$V$863="Selecionado")))} -> 9 | F72: {=ROWS(_xlfn.UNIQUE(_xlfn._xlws.FILTER('Amostra 1_5_extrato_erro_5%'!$C$2:$C$863,'Amostra 1_5_extrato_erro_5%'!$V$2:$V$863="Selecionado")))} -> 9 | G72: {=ROWS(_xlfn.UNIQUE(_xlfn._xlws.FILTER('Amostra 1_6_extrato_erro_5%'!$C$2:$C$863,'Amostra 1_6_extrato_erro_5%'!$V$2:$V$863="Selecionado")))} -> 8 | H72: =COUNTA($B$82:$B$96) -> 15 | I72: municípios | J72: União dos municípios das 4 abas
B73: Valores distintos preenchidos na coluna V (STATUS) | D73: {=ROWS(_xlfn.UNIQUE(_xlfn._xlws.FILTER('Amostra 1_3_extrato_erro_5%'!$V$2:$V$863,'Amostra 1_3_extrato_erro_5%'!$V$2:$V$863<>"")))} -> 1 | E73: {=ROWS(_xlfn.UNIQUE(_xlfn._xlws.FILTER('Amostra 1_4_extrato_erro_5%'!$V$2:$V$863,'Amostra 1_4_extrato_erro_5%'!$V$2:$V$863<>"")))} -> 1 | F73: {=ROWS(_xlfn.UNIQUE(_xlfn._xlws.FILTER('Amostra 1_5_extrato_erro_5%'!$V$2:$V$863,'Amostra 1_5_extrato_erro_5%'!$V$2:$V$863<>"")))} -> 1 | G73: {=ROWS(_xlfn.UNIQUE(_xlfn._xlws.FILTER('Amostra 1_6_extrato_erro_5%'!$V$2:$V$863,'Amostra 1_6_extrato_erro_5%'!$V$2:$V$863<>"")))} -> 1 | H73: =1 -> 1 | I73: valores | J73: =IF(H73=1,"OK — domínio único","ATENÇÃO") -> OK — domínio único
B74: Fração amostral (selecionados ÷ base) | D74: =D65/D64 -> 0.052204176 | E74: =E65/E64 -> 0.025522042 | F74: =F65/F64 -> 0.017401392 | G74: =G65/G64 -> 0.013921114 | H74: =H65/H64 -> 0.027262181 | I74: % | J74: Compatível com erro de 5%
B76: Grafia de municípios — verificação qualitativa: não foram encontradas duas grafias distintas para o mesmo município dentro de uma mesma aba nem entre abas; a consolidação por nome é, portanto, segura.
B77: Ressalva de padronização: "Machadinho D'oeste" e "Espigão D'Oeste" divergem da grafia oficial do IBGE ("Machadinho d'Oeste" e "Espigão d'Oeste"). Como o uso é internamente consistente, não há impacto nas contagens — recomenda-se apenas normalizar antes de cruzamentos com bases externas.
B78: Observação: a coluna V contém um único valor preenchido ("Selecionado"); os demais registros da base estão vazios, confirmando que o filtro aplicado captura integralmente a amostra sorteada.
B80: 6. DISTRIBUIÇÃO POR MUNICÍPIO — CADA AMOSTRA SEPARADAMENTE, COM DISTÂNCIAS A PARTIR DE PORTO VELHO
B81: Município | C81: Cluster logístico | D81: Lat. centroide | E81: Long. centroide | F81: Dist. geodésica (km) | G81: Dist. rodoviária estimada (km) | H81: UCs Am. 1_3 | I81: % Am. 1_3 | J81: UCs Am. 1_4 | K81: % Am. 1_4 | L81: UCs Am. 1_5 | M81: % Am. 1_5 | N81: UCs Am. 1_6 | O81: % Am. 1_6 | P81: UCs — união das 4 abas (referência) | Q81: % da união | R81: Nº de amostras em que aparece
B82: Porto Velho | C82: A — Norte / Capital | D82: =(SUMIFS('Amostra 1_3_extrato_erro_5%'!$X$2:$X$863,'Amostra 1_3_extrato_erro_5%'!$C$2:$C$863,$B82,'Amostra 1_3_extrato_erro_5%'!$V$2:$V$863,"Selecionado")+SUMIFS('Amostra 1_4_extrato_erro_5%'!$X$2:$X$863,'Amostra 1_4_extrato_erro_5%'!$C$2:$C$863,$B82,'Amostra 1_4_extrato_erro_5%'!$V$2:$V$863,"Selecionado")+SUMIFS('Amostra 1_5_extrato_erro_5%'!$X$2:$X$863,'Amostra 1_5_extrato_erro_5%'!$C$2:$C$863,$B82,'Amostra 1_5_extrato_erro_5%'!$V$2:$V$863,"Selecionado")+SUMIFS('Amostra 1_6_extrato_erro_5%'!$X$2:$X$863,'Amostra 1_6_extrato_erro_5%'!$C$2:$C$863,$B82,'Amostra 1_6_extrato_erro_5%'!$V$2:$V$863,"Selecionado"))/$P82 -> -8.7019517 | E82: =(SUMIFS('Amostra 1_3_extrato_erro_5%'!$Y$2:$Y$863,'Amostra 1_3_extrato_erro_5%'!$C$2:$C$863,$B82,'Amostra 1_3_extrato_erro_5%'!$V$2:$V$863,"Selecionado")+SUMIFS('Amostra 1_4_extrato_erro_5%'!$Y$2:$Y$863,'Amostra 1_4_extrato_erro_5%'!$C$2:$C$863,$B82,'Amostra 1_4_extrato_erro_5%'!$V$2:$V$863,"Selecionado")+SUMIFS('Amostra 1_5_extrato_erro_5%'!$Y$2:$Y$863,'Amostra 1_5_extrato_erro_5%'!$C$2:$C$863,$B82,'Amostra 1_5_extrato_erro_5%'!$V$2:$V$863,"Selecionado")+SUMIFS('Amostra 1_6_extrato_erro_5%'!$Y$2:$Y$863,'Amostra 1_6_extrato_erro_5%'!$C$2:$C$863,$B82,'Amostra 1_6_extrato_erro_5%'!$V$2:$V$863,"Selecionado"))/$P82 -> -63.435844 | F82: =ROUND(6371*ACOS(MIN(1,COS(RADIANS(90-$D$50))*COS(RADIANS(90-D82))+SIN(RADIANS(90-$D$50))*SIN(RADIANS(90-D82))*COS(RADIANS($D$51-E82)))),0) -> 51 | G82: =ROUND(F82*$D$55,0) -> 69 | H82: =COUNTIFS('Amostra 1_3_extrato_erro_5%'!$C$2:$C$863,$B82,'Amostra 1_3_extrato_erro_5%'!$V$2:$V$863,"Selecionado") -> 3 | I82: =IFERROR(H82/H$97,0) -> 0.066666667 | J82: =COUNTIFS('Amostra 1_4_extrato_erro_5%'!$C$2:$C$863,$B82,'Amostra 1_4_extrato_erro_5%'!$V$2:$V$863,"Selecionado") -> 7 | K82: =IFERROR(J82/J$97,0) -> 0.31818182 | L82: =COUNTIFS('Amostra 1_5_extrato_erro_5%'!$C$2:$C$863,$B82,'Amostra 1_5_extrato_erro_5%'!$V$2:$V$863,"Selecionado") -> 3 | M82: =IFERROR(L82/L$97,0) -> 0.2 | N82: =COUNTIFS('Amostra 1_6_extrato_erro_5%'!$C$2:$C$863,$B82,'Amostra 1_6_extrato_erro_5%'!$V$2:$V$863,"Selecionado") -> 1 | O82: =IFERROR(N82/N$97,0) -> 0.083333333 | P82: =H82+J82+L82+N82 -> 14 | Q82: =P82/$P$97 -> 0.14893617 | R82: =(H82>0)+(J82>0)+(L82>0)+(N82>0) -> 4
B83: Cujubim | C83: A — Norte / Capital | D83: =(SUMIFS('Amostra 1_3_extrato_erro_5%'!$X$2:$X$863,'Amostra 1_3_extrato_erro_5%'!$C$2:$C$863,$B83,'Amostra 1_3_extrato_erro_5%'!$V$2:$V$863,"Selecionado")+SUMIFS('Amostra 1_4_extrato_erro_5%'!$X$2:$X$863,'Amostra 1_4_extrato_erro_5%'!$C$2:$C$863,$B83,'Amostra 1_4_extrato_erro_5%'!$V$2:$V$863,"Selecionado")+SUMIFS('Amostra 1_5_extrato_erro_5%'!$X$2:$X$863,'Amostra 1_5_extrato_erro_5%'!$C$2:$C$863,$B83,'Amostra 1_5_extrato_erro_5%'!$V$2:$V$863,"Selecionado")+SUMIFS('Amostra 1_6_extrato_erro_5%'!$X$2:$X$863,'Amostra 1_6_extrato_erro_5%'!$C$2:$C$863,$B83,'Amostra 1_6_extrato_erro_5%'!$V$2:$V$863,"Selecionado"))/$P83 -> -8.881215 | E83: =(SUMIFS('Amostra 1_3_extrato_erro_5%'!$Y$2:$Y$863,'Amostra 1_3_extrato_erro_5%'!$C$2:$C$863,$B83,'Amostra 1_3_extrato_erro_5%'!$V$2:$V$863,"Selecionado")+SUMIFS('Amostra 1_4_extrato_erro_5%'!$Y$2:$Y$863,'Amostra 1_4_extrato_erro_5%'!$C$2:$C$863,$B83,'Amostra 1_4_extrato_erro_5%'!$V$2:$V$863,"Selecionado")+SUMIFS('Amostra 1_5_extrato_erro_5%'!$Y$2:$Y$863,'Amostra 1_5_extrato_erro_5%'!$C$2:$C$863,$B83,'Amostra 1_5_extrato_erro_5%'!$V$2:$V$863,"Selecionado")+SUMIFS('Amostra 1_6_extrato_erro_5%'!$Y$2:$Y$863,'Amostra 1_6_extrato_erro_5%'!$C$2:$C$863,$B83,'Amostra 1_6_extrato_erro_5%'!$V$2:$V$863,"Selecionado"))/$P83 -> -62.360793 | F83: =ROUND(6371*ACOS(MIN(1,COS(RADIANS(90-$D$50))*COS(RADIANS(90-D83))+SIN(RADIANS(90-$D$50))*SIN(RADIANS(90-D83))*COS(RADIANS($D$51-E83)))),0) -> 170 | G83: =ROUND(F83*$D$55,0) -> 230 | H83: =COUNTIFS('Amostra 1_3_extrato_erro_5%'!$C$2:$C$863,$B83,'Amostra 1_3_extrato_erro_5%'!$V$2:$V$863,"Selecionado") -> 5 | I83: =IFERROR(H83/H$97,0) -> 0.11111111 | J83: =COUNTIFS('Amostra 1_4_extrato_erro_5%'!$C$2:$C$863,$B83,'Amostra 1_4_extrato_erro_5%'!$V$2:$V$863,"Selecionado") -> 1 | K83: =IFERROR(J83/J$97,0) -> 0.045454545 | L83: =COUNTIFS('Amostra 1_5_extrato_erro_5%'!$C$2:$C$863,$B83,'Amostra 1_5_extrato_erro_5%'!$V$2:$V$863,"Selecionado") -> 0 | M83: =IFERROR(L83/L$97,0) -> 0 | N83: =COUNTIFS('Amostra 1_6_extrato_erro_5%'!$C$2:$C$863,$B83,'Amostra 1_6_extrato_erro_5%'!$V$2:$V$863,"Selecionado") -> 0 | O83: =IFERROR(N83/N$97,0) -> 0 | P83: =H83+J83+L83+N83 -> 6 | Q83: =P83/$P$97 -> 0.063829787 | R83: =(H83>0)+(J83>0)+(L83>0)+(N83>0) -> 2
B84: Candeias do Jamari | C84: A — Norte / Capital | D84: =(SUMIFS('Amostra 1_3_extrato_erro_5%'!$X$2:$X$863,'Amostra 1_3_extrato_erro_5%'!$C$2:$C$863,$B84,'Amostra 1_3_extrato_erro_5%'!$V$2:$V$863,"Selecionado")+SUMIFS('Amostra 1_4_extrato_erro_5%'!$X$2:$X$863,'Amostra 1_4_extrato_erro_5%'!$C$2:$C$863,$B84,'Amostra 1_4_extrato_erro_5%'!$V$2:$V$863,"Selecionado")+SUMIFS('Amostra 1_5_extrato_erro_5%'!$X$2:$X$863,'Amostra 1_5_extrato_erro_5%'!$C$2:$C$863,$B84,'Amostra 1_5_extrato_erro_5%'!$V$2:$V$863,"Selecionado")+SUMIFS('Amostra 1_6_extrato_erro_5%'!$X$2:$X$863,'Amostra 1_6_extrato_erro_5%'!$C$2:$C$863,$B84,'Amostra 1_6_extrato_erro_5%'!$V$2:$V$863,"Selecionado"))/$P84 -> -8.5268515 | E84: =(SUMIFS('Amostra 1_3_extrato_erro_5%'!$Y$2:$Y$863,'Amostra 1_3_extrato_erro_5%'!$C$2:$C$863,$B84,'Amostra 1_3_extrato_erro_5%'!$V$2:$V$863,"Selecionado")+SUMIFS('Amostra 1_4_extrato_erro_5%'!$Y$2:$Y$863,'Amostra 1_4_extrato_erro_5%'!$C$2:$C$863,$B84,'Amostra 1_4_extrato_erro_5%'!$V$2:$V$863,"Selecionado")+SUMIFS('Amostra 1_5_extrato_erro_5%'!$Y$2:$Y$863,'Amostra 1_5_extrato_erro_5%'!$C$2:$C$863,$B84,'Amostra 1_5_extrato_erro_5%'!$V$2:$V$863,"Selecionado")+SUMIFS('Amostra 1_6_extrato_erro_5%'!$Y$2:$Y$863,'Amostra 1_6_extrato_erro_5%'!$C$2:$C$863,$B84,'Amostra 1_6_extrato_erro_5%'!$V$2:$V$863,"Selecionado"))/$P84 -> -63.444928 | F84: =ROUND(6371*ACOS(MIN(1,COS(RADIANS(90-$D$50))*COS(RADIANS(90-D84))+SIN(RADIANS(90-$D$50))*SIN(RADIANS(90-D84))*COS(RADIANS($D$51-E84)))),0) -> 56 | G84: =ROUND(F84*$D$55,0) -> 76 | H84: =COUNTIFS('Amostra 1_3_extrato_erro_5%'!$C$2:$C$863,$B84,'Amostra 1_3_extrato_erro_5%'!$V$2:$V$863,"Selecionado") -> 1 | I84: =IFERROR(H84/H$97,0) -> 0.022222222 | J84: =COUNTIFS('Amostra 1_4_extrato_erro_5%'!$C$2:$C$863,$B84,'Amostra 1_4_extrato_erro_5%'!$V$2:$V$863,"Selecionado") -> 0 | K84: =IFERROR(J84/J$97,0) -> 0 | L84: =COUNTIFS('Amostra 1_5_extrato_erro_5%'!$C$2:$C$863,$B84,'Amostra 1_5_extrato_erro_5%'!$V$2:$V$863,"Selecionado") -> 1 | M84: =IFERROR(L84/L$97,0) -> 0.066666667 | N84: =COUNTIFS('Amostra 1_6_extrato_erro_5%'!$C$2:$C$863,$B84,'Amostra 1_6_extrato_erro_5%'!$V$2:$V$863,"Selecionado") -> 0 | O84: =IFERROR(N84/N$97,0) -> 0 | P84: =H84+J84+L84+N84 -> 2 | Q84: =P84/$P$97 -> 0.021276596 | R84: =(H84>0)+(J84>0)+(L84>0)+(N84>0) -> 2
B85: Vale do Anari | C85: A — Norte / Capital | D85: =(SUMIFS('Amostra 1_3_extrato_erro_5%'!$X$2:$X$863,'Amostra 1_3_extrato_erro_5%'!$C$2:$C$863,$B85,'Amostra 1_3_extrato_erro_5%'!$V$2:$V$863,"Selecionado")+SUMIFS('Amostra 1_4_extrato_erro_5%'!$X$2:$X$863,'Amostra 1_4_extrato_erro_5%'!$C$2:$C$863,$B85,'Amostra 1_4_extrato_erro_5%'!$V$2:$V$863,"Selecionado")+SUMIFS('Amostra 1_5_extrato_erro_5%'!$X$2:$X$863,'Amostra 1_5_extrato_erro_5%'!$C$2:$C$863,$B85,'Amostra 1_5_extrato_erro_5%'!$V$2:$V$863,"Selecionado")+SUMIFS('Amostra 1_6_extrato_erro_5%'!$X$2:$X$863,'Amostra 1_6_extrato_erro_5%'!$C$2:$C$863,$B85,'Amostra 1_6_extrato_erro_5%'!$V$2:$V$863,"Selecionado"))/$P85 -> -9.727253 | E85: =(SUMIFS('Amostra 1_3_extrato_erro_5%'!$Y$2:$Y$863,'Amostra 1_3_extrato_erro_5%'!$C$2:$C$863,$B85,'Amostra 1_3_extrato_erro_5%'!$V$2:$V$863,"Selecionado")+SUMIFS('Amostra 1_4_extrato_erro_5%'!$Y$2:$Y$863,'Amostra 1_4_extrato_erro_5%'!$C$2:$C$863,$B85,'Amostra 1_4_extrato_erro_5%'!$V$2:$V$863,"Selecionado")+SUMIFS('Amostra 1_5_extrato_erro_5%'!$Y$2:$Y$863,'Amostra 1_5_extrato_erro_5%'!$C$2:$C$863,$B85,'Amostra 1_5_extrato_erro_5%'!$V$2:$V$863,"Selecionado")+SUMIFS('Amostra 1_6_extrato_erro_5%'!$Y$2:$Y$863,'Amostra 1_6_extrato_erro_5%'!$C$2:$C$863,$B85,'Amostra 1_6_extrato_erro_5%'!$V$2:$V$863,"Selecionado"))/$P85 -> -62.044457 | F85: =ROUND(6371*ACOS(MIN(1,COS(RADIANS(90-$D$50))*COS(RADIANS(90-D85))+SIN(RADIANS(90-$D$50))*SIN(RADIANS(90-D85))*COS(RADIANS($D$51-E85)))),0) -> 230 | G85: =ROUND(F85*$D$55,0) -> 311 | H85: =COUNTIFS('Amostra 1_3_extrato_erro_5%'!$C$2:$C$863,$B85,'Amostra 1_3_extrato_erro_5%'!$V$2:$V$863,"Selecionado") -> 0 | I85: =IFERROR(H85/H$97,0) -> 0 | J85: =COUNTIFS('Amostra 1_4_extrato_erro_5%'!$C$2:$C$863,$B85,'Amostra 1_4_extrato_erro_5%'!$V$2:$V$863,"Selecionado") -> 1 | K85: =IFERROR(J85/J$97,0) -> 0.045454545 | L85: =COUNTIFS('Amostra 1_5_extrato_erro_5%'!$C$2:$C$863,$B85,'Amostra 1_5_extrato_erro_5%'!$V$2:$V$863,"Selecionado") -> 0 | M85: =IFERROR(L85/L$97,0) -> 0 | N85: =COUNTIFS('Amostra 1_6_extrato_erro_5%'!$C$2:$C$863,$B85,'Amostra 1_6_extrato_erro_5%'!$V$2:$V$863,"Selecionado") -> 0 | O85: =IFERROR(N85/N$97,0) -> 0 | P85: =H85+J85+L85+N85 -> 1 | Q85: =P85/$P$97 -> 0.010638298 | R85: =(H85>0)+(J85>0)+(L85>0)+(N85>0) -> 1
B86: Machadinho D'oeste | C86: A — Norte / Capital | D86: =(SUMIFS('Amostra 1_3_extrato_erro_5%'!$X$2:$X$863,'Amostra 1_3_extrato_erro_5%'!$C$2:$C$863,$B86,'Amostra 1_3_extrato_erro_5%'!$V$2:$V$863,"Selecionado")+SUMIFS('Amostra 1_4_extrato_erro_5%'!$X$2:$X$863,'Amostra 1_4_extrato_erro_5%'!$C$2:$C$863,$B86,'Amostra 1_4_extrato_erro_5%'!$V$2:$V$863,"Selecionado")+SUMIFS('Amostra 1_5_extrato_erro_5%'!$X$2:$X$863,'Amostra 1_5_extrato_erro_5%'!$C$2:$C$863,$B86,'Amostra 1_5_extrato_erro_5%'!$V$2:$V$863,"Selecionado")+SUMIFS('Amostra 1_6_extrato_erro_5%'!$X$2:$X$863,'Amostra 1_6_extrato_erro_5%'!$C$2:$C$863,$B86,'Amostra 1_6_extrato_erro_5%'!$V$2:$V$863,"Selecionado"))/$P86 -> -9.55046 | E86: =(SUMIFS('Amostra 1_3_extrato_erro_5%'!$Y$2:$Y$863,'Amostra 1_3_extrato_erro_5%'!$C$2:$C$863,$B86,'Amostra 1_3_extrato_erro_5%'!$V$2:$V$863,"Selecionado")+SUMIFS('Amostra 1_4_extrato_erro_5%'!$Y$2:$Y$863,'Amostra 1_4_extrato_erro_5%'!$C$2:$C$863,$B86,'Amostra 1_4_extrato_erro_5%'!$V$2:$V$863,"Selecionado")+SUMIFS('Amostra 1_5_extrato_erro_5%'!$Y$2:$Y$863,'Amostra 1_5_extrato_erro_5%'!$C$2:$C$863,$B86,'Amostra 1_5_extrato_erro_5%'!$V$2:$V$863,"Selecionado")+SUMIFS('Amostra 1_6_extrato_erro_5%'!$Y$2:$Y$863,'Amostra 1_6_extrato_erro_5%'!$C$2:$C$863,$B86,'Amostra 1_6_extrato_erro_5%'!$V$2:$V$863,"Selecionado"))/$P86 -> -62.016022 | F86: =ROUND(6371*ACOS(MIN(1,COS(RADIANS(90-$D$50))*COS(RADIANS(90-D86))+SIN(RADIANS(90-$D$50))*SIN(RADIANS(90-D86))*COS(RADIANS($D$51-E86)))),0) -> 225 | G86: =ROUND(F86*$D$55,0) -> 304 | H86: =COUNTIFS('Amostra 1_3_extrato_erro_5%'!$C$2:$C$863,$B86,'Amostra 1_3_extrato_erro_5%'!$V$2:$V$863,"Selecionado") -> 1 | I86: =IFERROR(H86/H$97,0) -> 0.022222222 | J86: =COUNTIFS('Amostra 1_4_extrato_erro_5%'!$C$2:$C$863,$B86,'Amostra 1_4_extrato_erro_5%'!$V$2:$V$863,"Selecionado") -> 0 | K86: =IFERROR(J86/J$97,0) -> 0 | L86: =COUNTIFS('Amostra 1_5_extrato_erro_5%'!$C$2:$C$863,$B86,'Amostra 1_5_extrato_erro_5%'!$V$2:$V$863,"Selecionado") -> 0 | M86: =IFERROR(L86/L$97,0) -> 0 | N86: =COUNTIFS('Amostra 1_6_extrato_erro_5%'!$C$2:$C$863,$B86,'Amostra 1_6_extrato_erro_5%'!$V$2:$V$863,"Selecionado") -> 0 | O86: =IFERROR(N86/N$97,0) -> 0 | P86: =H86+J86+L86+N86 -> 1 | Q86: =P86/$P$97 -> 0.010638298 | R86: =(H86>0)+(J86>0)+(L86>0)+(N86>0) -> 1
B87: Guajará-Mirim | C87: B — Oeste / Mamoré | D87: =(SUMIFS('Amostra 1_3_extrato_erro_5%'!$X$2:$X$863,'Amostra 1_3_extrato_erro_5%'!$C$2:$C$863,$B87,'Amostra 1_3_extrato_erro_5%'!$V$2:$V$863,"Selecionado")+SUMIFS('Amostra 1_4_extrato_erro_5%'!$X$2:$X$863,'Amostra 1_4_extrato_erro_5%'!$C$2:$C$863,$B87,'Amostra 1_4_extrato_erro_5%'!$V$2:$V$863,"Selecionado")+SUMIFS('Amostra 1_5_extrato_erro_5%'!$X$2:$X$863,'Amostra 1_5_extrato_erro_5%'!$C$2:$C$863,$B87,'Amostra 1_5_extrato_erro_5%'!$V$2:$V$863,"Selecionado")+SUMIFS('Amostra 1_6_extrato_erro_5%'!$X$2:$X$863,'Amostra 1_6_extrato_erro_5%'!$C$2:$C$863,$B87,'Amostra 1_6_extrato_erro_5%'!$V$2:$V$863,"Selecionado"))/$P87 -> -11.287779 | E87: =(SUMIFS('Amostra 1_3_extrato_erro_5%'!$Y$2:$Y$863,'Amostra 1_3_extrato_erro_5%'!$C$2:$C$863,$B87,'Amostra 1_3_extrato_erro_5%'!$V$2:$V$863,"Selecionado")+SUMIFS('Amostra 1_4_extrato_erro_5%'!$Y$2:$Y$863,'Amostra 1_4_extrato_erro_5%'!$C$2:$C$863,$B87,'Amostra 1_4_extrato_erro_5%'!$V$2:$V$863,"Selecionado")+SUMIFS('Amostra 1_5_extrato_erro_5%'!$Y$2:$Y$863,'Amostra 1_5_extrato_erro_5%'!$C$2:$C$863,$B87,'Amostra 1_5_extrato_erro_5%'!$V$2:$V$863,"Selecionado")+SUMIFS('Amostra 1_6_extrato_erro_5%'!$Y$2:$Y$863,'Amostra 1_6_extrato_erro_5%'!$C$2:$C$863,$B87,'Amostra 1_6_extrato_erro_5%'!$V$2:$V$863,"Selecionado"))/$P87 -> -64.831455 | F87: =ROUND(6371*ACOS(MIN(1,COS(RADIANS(90-$D$50))*COS(RADIANS(90-D87))+SIN(RADIANS(90-$D$50))*SIN(RADIANS(90-D87))*COS(RADIANS($D$51-E87)))),0) -> 299 | G87: =ROUND(F87*$D$55,0) -> 404 | H87: =COUNTIFS('Amostra 1_3_extrato_erro_5%'!$C$2:$C$863,$B87,'Amostra 1_3_extrato_erro_5%'!$V$2:$V$863,"Selecionado") -> 13 | I87: =IFERROR(H87/H$97,0) -> 0.28888889 | J87: =COUNTIFS('Amostra 1_4_extrato_erro_5%'!$C$2:$C$863,$B87,'Amostra 1_4_extrato_erro_5%'!$V$2:$V$863,"Selecionado") -> 6 | K87: =IFERROR(J87/J$97,0) -> 0.27272727 | L87: =COUNTIFS('Amostra 1_5_extrato_erro_5%'!$C$2:$C$863,$B87,'Amostra 1_5_extrato_erro_5%'!$V$2:$V$863,"Selecionado") -> 3 | M87: =IFERROR(L87/L$97,0) -> 0.2 | N87: =COUNTIFS('Amostra 1_6_extrato_erro_5%'!$C$2:$C$863,$B87,'Amostra 1_6_extrato_erro_5%'!$V$2:$V$863,"Selecionado") -> 4 | O87: =IFERROR(N87/N$97,0) -> 0.33333333 | P87: =H87+J87+L87+N87 -> 26 | Q87: =P87/$P$97 -> 0.27659574 | R87: =(H87>0)+(J87>0)+(L87>0)+(N87>0) -> 4
B88: Nova Mamoré | C88: B — Oeste / Mamoré | D88: =(SUMIFS('Amostra 1_3_extrato_erro_5%'!$X$2:$X$863,'Amostra 1_3_extrato_erro_5%'!$C$2:$C$863,$B88,'Amostra 1_3_extrato_erro_5%'!$V$2:$V$863,"Selecionado")+SUMIFS('Amostra 1_4_extrato_erro_5%'!$X$2:$X$863,'Amostra 1_4_extrato_erro_5%'!$C$2:$C$863,$B88,'Amostra 1_4_extrato_erro_5%'!$V$2:$V$863,"Selecionado")+SUMIFS('Amostra 1_5_extrato_erro_5%'!$X$2:$X$863,'Amostra 1_5_extrato_erro_5%'!$C$2:$C$863,$B88,'Amostra 1_5_extrato_erro_5%'!$V$2:$V$863,"Selecionado")+SUMIFS('Amostra 1_6_extrato_erro_5%'!$X$2:$X$863,'Amostra 1_6_extrato_erro_5%'!$C$2:$C$863,$B88,'Amostra 1_6_extrato_erro_5%'!$V$2:$V$863,"Selecionado"))/$P88 -> -10.341826 | E88: =(SUMIFS('Amostra 1_3_extrato_erro_5%'!$Y$2:$Y$863,'Amostra 1_3_extrato_erro_5%'!$C$2:$C$863,$B88,'Amostra 1_3_extrato_erro_5%'!$V$2:$V$863,"Selecionado")+SUMIFS('Amostra 1_4_extrato_erro_5%'!$Y$2:$Y$863,'Amostra 1_4_extrato_erro_5%'!$C$2:$C$863,$B88,'Amostra 1_4_extrato_erro_5%'!$V$2:$V$863,"Selecionado")+SUMIFS('Amostra 1_5_extrato_erro_5%'!$Y$2:$Y$863,'Amostra 1_5_extrato_erro_5%'!$C$2:$C$863,$B88,'Amostra 1_5_extrato_erro_5%'!$V$2:$V$863,"Selecionado")+SUMIFS('Amostra 1_6_extrato_erro_5%'!$Y$2:$Y$863,'Amostra 1_6_extrato_erro_5%'!$C$2:$C$863,$B88,'Amostra 1_6_extrato_erro_5%'!$V$2:$V$863,"Selecionado"))/$P88 -> -65.052209 | F88: =ROUND(6371*ACOS(MIN(1,COS(RADIANS(90-$D$50))*COS(RADIANS(90-D88))+SIN(RADIANS(90-$D$50))*SIN(RADIANS(90-D88))*COS(RADIANS($D$51-E88)))),0) -> 216 | G88: =ROUND(F88*$D$55,0) -> 292 | H88: =COUNTIFS('Amostra 1_3_extrato_erro_5%'!$C$2:$C$863,$B88,'Amostra 1_3_extrato_erro_5%'!$V$2:$V$863,"Selecionado") -> 2 | I88: =IFERROR(H88/H$97,0) -> 0.044444444 | J88: =COUNTIFS('Amostra 1_4_extrato_erro_5%'!$C$2:$C$863,$B88,'Amostra 1_4_extrato_erro_5%'!$V$2:$V$863,"Selecionado") -> 0 | K88: =IFERROR(J88/J$97,0) -> 0 | L88: =COUNTIFS('Amostra 1_5_extrato_erro_5%'!$C$2:$C$863,$B88,'Amostra 1_5_extrato_erro_5%'!$V$2:$V$863,"Selecionado") -> 0 | M88: =IFERROR(L88/L$97,0) -> 0 | N88: =COUNTIFS('Amostra 1_6_extrato_erro_5%'!$C$2:$C$863,$B88,'Amostra 1_6_extrato_erro_5%'!$V$2:$V$863,"Selecionado") -> 1 | O88: =IFERROR(N88/N$97,0) -> 0.083333333 | P88: =H88+J88+L88+N88 -> 3 | Q88: =P88/$P$97 -> 0.031914894 | R88: =(H88>0)+(J88>0)+(L88>0)+(N88>0) -> 2
B89: Vilhena | C89: C — Centro-Leste / BR-364 | D89: =(SUMIFS('Amostra 1_3_extrato_erro_5%'!$X$2:$X$863,'Amostra 1_3_extrato_erro_5%'!$C$2:$C$863,$B89,'Amostra 1_3_extrato_erro_5%'!$V$2:$V$863,"Selecionado")+SUMIFS('Amostra 1_4_extrato_erro_5%'!$X$2:$X$863,'Amostra 1_4_extrato_erro_5%'!$C$2:$C$863,$B89,'Amostra 1_4_extrato_erro_5%'!$V$2:$V$863,"Selecionado")+SUMIFS('Amostra 1_5_extrato_erro_5%'!$X$2:$X$863,'Amostra 1_5_extrato_erro_5%'!$C$2:$C$863,$B89,'Amostra 1_5_extrato_erro_5%'!$V$2:$V$863,"Selecionado")+SUMIFS('Amostra 1_6_extrato_erro_5%'!$X$2:$X$863,'Amostra 1_6_extrato_erro_5%'!$C$2:$C$863,$B89,'Amostra 1_6_extrato_erro_5%'!$V$2:$V$863,"Selecionado"))/$P89 -> -12.277523 | E89: =(SUMIFS('Amostra 1_3_extrato_erro_5%'!$Y$2:$Y$863,'Amostra 1_3_extrato_erro_5%'!$C$2:$C$863,$B89,'Amostra 1_3_extrato_erro_5%'!$V$2:$V$863,"Selecionado")+SUMIFS('Amostra 1_4_extrato_erro_5%'!$Y$2:$Y$863,'Amostra 1_4_extrato_erro_5%'!$C$2:$C$863,$B89,'Amostra 1_4_extrato_erro_5%'!$V$2:$V$863,"Selecionado")+SUMIFS('Amostra 1_5_extrato_erro_5%'!$Y$2:$Y$863,'Amostra 1_5_extrato_erro_5%'!$C$2:$C$863,$B89,'Amostra 1_5_extrato_erro_5%'!$V$2:$V$863,"Selecionado")+SUMIFS('Amostra 1_6_extrato_erro_5%'!$Y$2:$Y$863,'Amostra 1_6_extrato_erro_5%'!$C$2:$C$863,$B89,'Amostra 1_6_extrato_erro_5%'!$V$2:$V$863,"Selecionado"))/$P89 -> -60.316484 | F89: =ROUND(6371*ACOS(MIN(1,COS(RADIANS(90-$D$50))*COS(RADIANS(90-D89))+SIN(RADIANS(90-$D$50))*SIN(RADIANS(90-D89))*COS(RADIANS($D$51-E89)))),0) -> 553 | G89: =ROUND(F89*$D$55,0) -> 747 | H89: =COUNTIFS('Amostra 1_3_extrato_erro_5%'!$C$2:$C$863,$B89,'Amostra 1_3_extrato_erro_5%'!$V$2:$V$863,"Selecionado") -> 4 | I89: =IFERROR(H89/H$97,0) -> 0.088888889 | J89: =COUNTIFS('Amostra 1_4_extrato_erro_5%'!$C$2:$C$863,$B89,'Amostra 1_4_extrato_erro_5%'!$V$2:$V$863,"Selecionado") -> 2 | K89: =IFERROR(J89/J$97,0) -> 0.090909091 | L89: =COUNTIFS('Amostra 1_5_extrato_erro_5%'!$C$2:$C$863,$B89,'Amostra 1_5_extrato_erro_5%'!$V$2:$V$863,"Selecionado") -> 2 | M89: =IFERROR(L89/L$97,0) -> 0.13333333 | N89: =COUNTIFS('Amostra 1_6_extrato_erro_5%'!$C$2:$C$863,$B89,'Amostra 1_6_extrato_erro_5%'!$V$2:$V$863,"Selecionado") -> 1 | O89: =IFERROR(N89/N$97,0) -> 0.083333333 | P89: =H89+J89+L89+N89 -> 9 | Q89: =P89/$P$97 -> 0.095744681 | R89: =(H89>0)+(J89>0)+(L89>0)+(N89>0) -> 4
B90: Ji-Paraná | C90: C — Centro-Leste / BR-364 | D90: =(SUMIFS('Amostra 1_3_extrato_erro_5%'!$X$2:$X$863,'Amostra 1_3_extrato_erro_5%'!$C$2:$C$863,$B90,'Amostra 1_3_extrato_erro_5%'!$V$2:$V$863,"Selecionado")+SUMIFS('Amostra 1_4_extrato_erro_5%'!$X$2:$X$863,'Amostra 1_4_extrato_erro_5%'!$C$2:$C$863,$B90,'Amostra 1_4_extrato_erro_5%'!$V$2:$V$863,"Selecionado")+SUMIFS('Amostra 1_5_extrato_erro_5%'!$X$2:$X$863,'Amostra 1_5_extrato_erro_5%'!$C$2:$C$863,$B90,'Amostra 1_5_extrato_erro_5%'!$V$2:$V$863,"Selecionado")+SUMIFS('Amostra 1_6_extrato_erro_5%'!$X$2:$X$863,'Amostra 1_6_extrato_erro_5%'!$C$2:$C$863,$B90,'Amostra 1_6_extrato_erro_5%'!$V$2:$V$863,"Selecionado"))/$P90 -> -10.577831 | E90: =(SUMIFS('Amostra 1_3_extrato_erro_5%'!$Y$2:$Y$863,'Amostra 1_3_extrato_erro_5%'!$C$2:$C$863,$B90,'Amostra 1_3_extrato_erro_5%'!$V$2:$V$863,"Selecionado")+SUMIFS('Amostra 1_4_extrato_erro_5%'!$Y$2:$Y$863,'Amostra 1_4_extrato_erro_5%'!$C$2:$C$863,$B90,'Amostra 1_4_extrato_erro_5%'!$V$2:$V$863,"Selecionado")+SUMIFS('Amostra 1_5_extrato_erro_5%'!$Y$2:$Y$863,'Amostra 1_5_extrato_erro_5%'!$C$2:$C$863,$B90,'Amostra 1_5_extrato_erro_5%'!$V$2:$V$863,"Selecionado")+SUMIFS('Amostra 1_6_extrato_erro_5%'!$Y$2:$Y$863,'Amostra 1_6_extrato_erro_5%'!$C$2:$C$863,$B90,'Amostra 1_6_extrato_erro_5%'!$V$2:$V$863,"Selecionado"))/$P90 -> -61.66076 | F90: =ROUND(6371*ACOS(MIN(1,COS(RADIANS(90-$D$50))*COS(RADIANS(90-D90))+SIN(RADIANS(90-$D$50))*SIN(RADIANS(90-D90))*COS(RADIANS($D$51-E90)))),0) -> 318 | G90: =ROUND(F90*$D$55,0) -> 429 | H90: =COUNTIFS('Amostra 1_3_extrato_erro_5%'!$C$2:$C$863,$B90,'Amostra 1_3_extrato_erro_5%'!$V$2:$V$863,"Selecionado") -> 5 | I90: =IFERROR(H90/H$97,0) -> 0.11111111 | J90: =COUNTIFS('Amostra 1_4_extrato_erro_5%'!$C$2:$C$863,$B90,'Amostra 1_4_extrato_erro_5%'!$V$2:$V$863,"Selecionado") -> 2 | K90: =IFERROR(J90/J$97,0) -> 0.090909091 | L90: =COUNTIFS('Amostra 1_5_extrato_erro_5%'!$C$2:$C$863,$B90,'Amostra 1_5_extrato_erro_5%'!$V$2:$V$863,"Selecionado") -> 1 | M90: =IFERROR(L90/L$97,0) -> 0.066666667 | N90: =COUNTIFS('Amostra 1_6_extrato_erro_5%'!$C$2:$C$863,$B90,'Amostra 1_6_extrato_erro_5%'!$V$2:$V$863,"Selecionado") -> 1 | O90: =IFERROR(N90/N$97,0) -> 0.083333333 | P90: =H90+J90+L90+N90 -> 9 | Q90: =P90/$P$97 -> 0.095744681 | R90: =(H90>0)+(J90>0)+(L90>0)+(N90>0) -> 4
B91: Pimenta Bueno | C91: C — Centro-Leste / BR-364 | D91: =(SUMIFS('Amostra 1_3_extrato_erro_5%'!$X$2:$X$863,'Amostra 1_3_extrato_erro_5%'!$C$2:$C$863,$B91,'Amostra 1_3_extrato_erro_5%'!$V$2:$V$863,"Selecionado")+SUMIFS('Amostra 1_4_extrato_erro_5%'!$X$2:$X$863,'Amostra 1_4_extrato_erro_5%'!$C$2:$C$863,$B91,'Amostra 1_4_extrato_erro_5%'!$V$2:$V$863,"Selecionado")+SUMIFS('Amostra 1_5_extrato_erro_5%'!$X$2:$X$863,'Amostra 1_5_extrato_erro_5%'!$C$2:$C$863,$B91,'Amostra 1_5_extrato_erro_5%'!$V$2:$V$863,"Selecionado")+SUMIFS('Amostra 1_6_extrato_erro_5%'!$X$2:$X$863,'Amostra 1_6_extrato_erro_5%'!$C$2:$C$863,$B91,'Amostra 1_6_extrato_erro_5%'!$V$2:$V$863,"Selecionado"))/$P91 -> -12.07661 | E91: =(SUMIFS('Amostra 1_3_extrato_erro_5%'!$Y$2:$Y$863,'Amostra 1_3_extrato_erro_5%'!$C$2:$C$863,$B91,'Amostra 1_3_extrato_erro_5%'!$V$2:$V$863,"Selecionado")+SUMIFS('Amostra 1_4_extrato_erro_5%'!$Y$2:$Y$863,'Amostra 1_4_extrato_erro_5%'!$C$2:$C$863,$B91,'Amostra 1_4_extrato_erro_5%'!$V$2:$V$863,"Selecionado")+SUMIFS('Amostra 1_5_extrato_erro_5%'!$Y$2:$Y$863,'Amostra 1_5_extrato_erro_5%'!$C$2:$C$863,$B91,'Amostra 1_5_extrato_erro_5%'!$V$2:$V$863,"Selecionado")+SUMIFS('Amostra 1_6_extrato_erro_5%'!$Y$2:$Y$863,'Amostra 1_6_extrato_erro_5%'!$C$2:$C$863,$B91,'Amostra 1_6_extrato_erro_5%'!$V$2:$V$863,"Selecionado"))/$P91 -> -60.404733 | F91: =ROUND(6371*ACOS(MIN(1,COS(RADIANS(90-$D$50))*COS(RADIANS(90-D91))+SIN(RADIANS(90-$D$50))*SIN(RADIANS(90-D91))*COS(RADIANS($D$51-E91)))),0) -> 531 | G91: =ROUND(F91*$D$55,0) -> 717 | H91: =COUNTIFS('Amostra 1_3_extrato_erro_5%'!$C$2:$C$863,$B91,'Amostra 1_3_extrato_erro_5%'!$V$2:$V$863,"Selecionado") -> 2 | I91: =IFERROR(H91/H$97,0) -> 0.044444444 | J91: =COUNTIFS('Amostra 1_4_extrato_erro_5%'!$C$2:$C$863,$B91,'Amostra 1_4_extrato_erro_5%'!$V$2:$V$863,"Selecionado") -> 1 | K91: =IFERROR(J91/J$97,0) -> 0.045454545 | L91: =COUNTIFS('Amostra 1_5_extrato_erro_5%'!$C$2:$C$863,$B91,'Amostra 1_5_extrato_erro_5%'!$V$2:$V$863,"Selecionado") -> 2 | M91: =IFERROR(L91/L$97,0) -> 0.13333333 | N91: =COUNTIFS('Amostra 1_6_extrato_erro_5%'!$C$2:$C$863,$B91,'Amostra 1_6_extrato_erro_5%'!$V$2:$V$863,"Selecionado") -> 1 | O91: =IFERROR(N91/N$97,0) -> 0.083333333 | P91: =H91+J91+L91+N91 -> 6 | Q91: =P91/$P$97 -> 0.063829787 | R91: =(H91>0)+(J91>0)+(L91>0)+(N91>0) -> 4
B92: Espigão D'Oeste | C92: C — Centro-Leste / BR-364 | D92: =(SUMIFS('Amostra 1_3_extrato_erro_5%'!$X$2:$X$863,'Amostra 1_3_extrato_erro_5%'!$C$2:$C$863,$B92,'Amostra 1_3_extrato_erro_5%'!$V$2:$V$863,"Selecionado")+SUMIFS('Amostra 1_4_extrato_erro_5%'!$X$2:$X$863,'Amostra 1_4_extrato_erro_5%'!$C$2:$C$863,$B92,'Amostra 1_4_extrato_erro_5%'!$V$2:$V$863,"Selecionado")+SUMIFS('Amostra 1_5_extrato_erro_5%'!$X$2:$X$863,'Amostra 1_5_extrato_erro_5%'!$C$2:$C$863,$B92,'Amostra 1_5_extrato_erro_5%'!$V$2:$V$863,"Selecionado")+SUMIFS('Amostra 1_6_extrato_erro_5%'!$X$2:$X$863,'Amostra 1_6_extrato_erro_5%'!$C$2:$C$863,$B92,'Amostra 1_6_extrato_erro_5%'!$V$2:$V$863,"Selecionado"))/$P92 -> -11.172653 | E92: =(SUMIFS('Amostra 1_3_extrato_erro_5%'!$Y$2:$Y$863,'Amostra 1_3_extrato_erro_5%'!$C$2:$C$863,$B92,'Amostra 1_3_extrato_erro_5%'!$V$2:$V$863,"Selecionado")+SUMIFS('Amostra 1_4_extrato_erro_5%'!$Y$2:$Y$863,'Amostra 1_4_extrato_erro_5%'!$C$2:$C$863,$B92,'Amostra 1_4_extrato_erro_5%'!$V$2:$V$863,"Selecionado")+SUMIFS('Amostra 1_5_extrato_erro_5%'!$Y$2:$Y$863,'Amostra 1_5_extrato_erro_5%'!$C$2:$C$863,$B92,'Amostra 1_5_extrato_erro_5%'!$V$2:$V$863,"Selecionado")+SUMIFS('Amostra 1_6_extrato_erro_5%'!$Y$2:$Y$863,'Amostra 1_6_extrato_erro_5%'!$C$2:$C$863,$B92,'Amostra 1_6_extrato_erro_5%'!$V$2:$V$863,"Selecionado"))/$P92 -> -60.672094 | F92: =ROUND(6371*ACOS(MIN(1,COS(RADIANS(90-$D$50))*COS(RADIANS(90-D92))+SIN(RADIANS(90-$D$50))*SIN(RADIANS(90-D92))*COS(RADIANS($D$51-E92)))),0) -> 444 | G92: =ROUND(F92*$D$55,0) -> 599 | H92: =COUNTIFS('Amostra 1_3_extrato_erro_5%'!$C$2:$C$863,$B92,'Amostra 1_3_extrato_erro_5%'!$V$2:$V$863,"Selecionado") -> 0 | I92: =IFERROR(H92/H$97,0) -> 0 | J92: =COUNTIFS('Amostra 1_4_extrato_erro_5%'!$C$2:$C$863,$B92,'Amostra 1_4_extrato_erro_5%'!$V$2:$V$863,"Selecionado") -> 1 | K92: =IFERROR(J92/J$97,0) -> 0.045454545 | L92: =COUNTIFS('Amostra 1_5_extrato_erro_5%'!$C$2:$C$863,$B92,'Amostra 1_5_extrato_erro_5%'!$V$2:$V$863,"Selecionado") -> 1 | M92: =IFERROR(L92/L$97,0) -> 0.066666667 | N92: =COUNTIFS('Amostra 1_6_extrato_erro_5%'!$C$2:$C$863,$B92,'Amostra 1_6_extrato_erro_5%'!$V$2:$V$863,"Selecionado") -> 1 | O92: =IFERROR(N92/N$97,0) -> 0.083333333 | P92: =H92+J92+L92+N92 -> 3 | Q92: =P92/$P$97 -> 0.031914894 | R92: =(H92>0)+(J92>0)+(L92>0)+(N92>0) -> 3
B93: Cacoal | C93: C — Centro-Leste / BR-364 | D93: =(SUMIFS('Amostra 1_3_extrato_erro_5%'!$X$2:$X$863,'Amostra 1_3_extrato_erro_5%'!$C$2:$C$863,$B93,'Amostra 1_3_extrato_erro_5%'!$V$2:$V$863,"Selecionado")+SUMIFS('Amostra 1_4_extrato_erro_5%'!$X$2:$X$863,'Amostra 1_4_extrato_erro_5%'!$C$2:$C$863,$B93,'Amostra 1_4_extrato_erro_5%'!$V$2:$V$863,"Selecionado")+SUMIFS('Amostra 1_5_extrato_erro_5%'!$X$2:$X$863,'Amostra 1_5_extrato_erro_5%'!$C$2:$C$863,$B93,'Amostra 1_5_extrato_erro_5%'!$V$2:$V$863,"Selecionado")+SUMIFS('Amostra 1_6_extrato_erro_5%'!$X$2:$X$863,'Amostra 1_6_extrato_erro_5%'!$C$2:$C$863,$B93,'Amostra 1_6_extrato_erro_5%'!$V$2:$V$863,"Selecionado"))/$P93 -> -11.104323 | E93: =(SUMIFS('Amostra 1_3_extrato_erro_5%'!$Y$2:$Y$863,'Amostra 1_3_extrato_erro_5%'!$C$2:$C$863,$B93,'Amostra 1_3_extrato_erro_5%'!$V$2:$V$863,"Selecionado")+SUMIFS('Amostra 1_4_extrato_erro_5%'!$Y$2:$Y$863,'Amostra 1_4_extrato_erro_5%'!$C$2:$C$863,$B93,'Amostra 1_4_extrato_erro_5%'!$V$2:$V$863,"Selecionado")+SUMIFS('Amostra 1_5_extrato_erro_5%'!$Y$2:$Y$863,'Amostra 1_5_extrato_erro_5%'!$C$2:$C$863,$B93,'Amostra 1_5_extrato_erro_5%'!$V$2:$V$863,"Selecionado")+SUMIFS('Amostra 1_6_extrato_erro_5%'!$Y$2:$Y$863,'Amostra 1_6_extrato_erro_5%'!$C$2:$C$863,$B93,'Amostra 1_6_extrato_erro_5%'!$V$2:$V$863,"Selecionado"))/$P93 -> -61.350523 | F93: =ROUND(6371*ACOS(MIN(1,COS(RADIANS(90-$D$50))*COS(RADIANS(90-D93))+SIN(RADIANS(90-$D$50))*SIN(RADIANS(90-D93))*COS(RADIANS($D$51-E93)))),0) -> 382 | G93: =ROUND(F93*$D$55,0) -> 516 | H93: =COUNTIFS('Amostra 1_3_extrato_erro_5%'!$C$2:$C$863,$B93,'Amostra 1_3_extrato_erro_5%'!$V$2:$V$863,"Selecionado") -> 1 | I93: =IFERROR(H93/H$97,0) -> 0.022222222 | J93: =COUNTIFS('Amostra 1_4_extrato_erro_5%'!$C$2:$C$863,$B93,'Amostra 1_4_extrato_erro_5%'!$V$2:$V$863,"Selecionado") -> 0 | K93: =IFERROR(J93/J$97,0) -> 0 | L93: =COUNTIFS('Amostra 1_5_extrato_erro_5%'!$C$2:$C$863,$B93,'Amostra 1_5_extrato_erro_5%'!$V$2:$V$863,"Selecionado") -> 1 | M93: =IFERROR(L93/L$97,0) -> 0.066666667 | N93: =COUNTIFS('Amostra 1_6_extrato_erro_5%'!$C$2:$C$863,$B93,'Amostra 1_6_extrato_erro_5%'!$V$2:$V$863,"Selecionado") -> 0 | O93: =IFERROR(N93/N$97,0) -> 0 | P93: =H93+J93+L93+N93 -> 2 | Q93: =P93/$P$97 -> 0.021276596 | R93: =(H93>0)+(J93>0)+(L93>0)+(N93>0) -> 2
... B96: Alta Floresta d'Oeste | C96: D — Vale do Guaporé | D96: =(SUMIFS('Amostra 1_3_extrato_erro_5%'!$X$2:$X$863,'Amostra 1_3_extrato_erro_5%'!$C$2:$C$863,$B96,'Amostra 1_3_extrato_erro_5%'!$V$2:$V$863,"Selecionado")+SUMIFS('Amostra 1_4_extrato_erro_5%'!$X$2:$X$863,'Amostra 1_4_extrato_erro_5%'!$C$2:$C$863,$B96,'Amostra 1_4_extrato_erro_5%'!$V$2:$V$863,"Selecionado")+SUMIFS('Amostra 1_5_extrato_erro_5%'!$X$2:$X$863,'Amostra 1_5_extrato_erro_5%'!$C$2:$C$863,$B96,'Amostra 1_5_extrato_erro_5%'!$V$2:$V$863,"Selecionado")+SUMIFS('Amostra 1_6_extrato_erro_5%'!$X$2:$X$863,'Amostra 1_6_extrato_erro_5%'!$C$2:$C$863,$B96,'Amostra 1_6_extrato_erro_5%'!$V$2:$V$863,"Selecionado"))/$P96 -> -12.9224 | E96: =(SUMIFS('Amostra 1_3_extrato_erro_5%'!$Y$2:$Y$863,'Amostra 1_3_extrato_erro_5%'!$C$2:$C$863,$B96,'Amostra 1_3_extrato_erro_5%'!$V$2:$V$863,"Selecionado")+SUMIFS('Amostra 1_4_extrato_erro_5%'!$Y$2:$Y$863,'Amostra 1_4_extrato_erro_5%'!$C$2:$C$863,$B96,'Amostra 1_4_extrato_erro_5%'!$V$2:$V$863,"Selecionado")+SUMIFS('Amostra 1_5_extrato_erro_5%'!$Y$2:$Y$863,'Amostra 1_5_extrato_erro_5%'!$C$2:$C$863,$B96,'Amostra 1_5_extrato_erro_5%'!$V$2:$V$863,"Selecionado")+SUMIFS('Amostra 1_6_extrato_erro_5%'!$Y$2:$Y$863,'Amostra 1_6_extrato_erro_5%'!$C$2:$C$863,$B96,'Amostra 1_6_extrato_erro_5%'!$V$2:$V$863,"Selecionado"))/$P96 -> -62.1839 | F96: =ROUND(6371*ACOS(MIN(1,COS(RADIANS(90-$D$50))*COS(RADIANS(90-D96))+SIN(RADIANS(90-$D$50))*SIN(RADIANS(90-D96))*COS(RADIANS($D$51-E96)))),0) -> 499 | G96: =ROUND(F96*$D$55,0) -> 674 | H96: =COUNTIFS('Amostra 1_3_extrato_erro_5%'!$C$2:$C$863,$B96,'Amostra 1_3_extrato_erro_5%'!$V$2:$V$863,"Selecionado") -> 1 | I96: =IFERROR(H96/H$97,0) -> 0.022222222 | J96: =COUNTIFS('Amostra 1_4_extrato_erro_5%'!$C$2:$C$863,$B96,'Amostra 1_4_extrato_erro_5%'!$V$2:$V$863,"Selecionado") -> 0 | K96: =IFERROR(J96/J$97,0) -> 0 | L96: =COUNTIFS('Amostra 1_5_extrato_erro_5%'!$C$2:$C$863,$B96,'Amostra 1_5_extrato_erro_5%'!$V$2:$V$863,"Selecionado") -> 0 | M96: =IFERROR(L96/L$97,0) -> 0 | N96: =COUNTIFS('Amostra 1_6_extrato_erro_5%'!$C$2:$C$863,$B96,'Amostra 1_6_extrato_erro_5%'!$V$2:$V$863,"Selecionado") -> 0 | O96: =IFERROR(N96/N$97,0) -> 0 | P96: =H96+J96+L96+N96 -> 1 | Q96: =P96/$P$97 -> 0.010638298 | R96: =(H96>0)+(J96>0)+(L96>0)+(N96>0) -> 1
B97: TOTAL / MÉDIA | C97: =COUNTA(B82:B96)&" municípios / "&D60&" clusters" -> 15 municípios / 4 clusters | F97: =ROUND(AVERAGE(F82:F96),0) -> 319 | G97: =ROUND(AVERAGE(G82:G96),0) -> 431 | H97: =SUM(H82:H96) -> 45 | I97: =SUM(I82:I96) -> 1 | J97: =SUM(J82:J96) -> 22 | K97: =SUM(K82:K96) -> 1 | L97: =SUM(L82:L96) -> 15 | M97: =SUM(M82:M96) -> 1 | N97: =SUM(N82:N96) -> 12 | O97: =SUM(O82:O96) -> 1 | ... Q97: =SUM(Q82:Q96) -> 1 | R97: =ROUND(AVERAGE(R82:R96),1) -> 2.6
B98: Cada bloco de colunas (UCs e %) refere-se a UMA amostra, tratada como alternativa independente. As colunas de união das quatro abas servem apenas para mapear o conjunto de municípios envolvidos e calcular centroides; NÃO representam um escopo de execução. Centroides = média das coordenadas das UCs selecionadas (colunas X e Y das abas de origem).
B99: Distância geodésica calculada por Haversine entre o centroide municipal e Porto Velho; distância rodoviária = geodésica × fator de sinuosidade (célula D55). São estimativas de planejamento e devem ser refinadas por roteirização real antes da mobilização.
B101: 7. COMPARATIVO ENTRE AS QUATRO AMOSTRAS
B102: Amostra | D102: UCs selecionadas | E102: % da união das 4 abas | F102: Municípios abrangidos | G102: UCs por município | H102: Dispersão (munic./UC) | I102: Dist. média ponderada (km) | J102: Dist. máxima (km) | K102: Clusters ativos | L102: Índice de dispersão vs. Rondônia
B103: Amostra 1_3_extrato_erro_5% | D103: =SUM($H$82:$H$96) -> 45 | E103: =D103/$D$107 -> 0.4787234 | F103: =COUNTIF($H$82:$H$96,">0") -> 13 | G103: =D103/F103 -> 3.4615385 | H103: =F103/D103 -> 0.28888889 | I103: =ROUND(SUMPRODUCT($G$82:$G$96,$H$82:$H$96)/SUM($H$82:$H$96),0) -> 427 | J103: =_xlfn.MAXIFS($G$82:$G$96,$H$82:$H$96,">0") -> 747 | K103: {=SUMPRODUCT(--(SUMIF($C$82:$C$96,$B$112:$B$115,$H$82:$H$96)>0))} -> 4 | L103: =H103/$D$43 -> 1.7333333
B104: Amostra 1_4_extrato_erro_5% | D104: =SUM($J$82:$J$96) -> 22 | E104: =D104/$D$107 -> 0.23404255 | F104: =COUNTIF($J$82:$J$96,">0") -> 9 | G104: =D104/F104 -> 2.4444444 | H104: =F104/D104 -> 0.40909091 | I104: =ROUND(SUMPRODUCT($G$82:$G$96,$J$82:$J$96)/SUM($J$82:$J$96),0) -> 347 | J104: =_xlfn.MAXIFS($G$82:$G$96,$J$82:$J$96,">0") -> 747 | K104: {=SUMPRODUCT(--(SUMIF($C$82:$C$96,$B$112:$B$115,$J$82:$J$96)>0))} -> 4 | L104: =H104/$D$43 -> 2.4545455
B105: Amostra 1_5_extrato_erro_5% | D105: =SUM($L$82:$L$96) -> 15 | E105: =D105/$D$107 -> 0.15957447 | F105: =COUNTIF($L$82:$L$96,">0") -> 9 | G105: =D105/F105 -> 1.6666667 | H105: =F105/D105 -> 0.6 | I105: =ROUND(SUMPRODUCT($G$82:$G$96,$L$82:$L$96)/SUM($L$82:$L$96),0) -> 433 | J105: =_xlfn.MAXIFS($G$82:$G$96,$L$82:$L$96,">0") -> 747 | K105: {=SUMPRODUCT(--(SUMIF($C$82:$C$96,$B$112:$B$115,$L$82:$L$96)>0))} -> 4 | L105: =H105/$D$43 -> 3.6
B106: Amostra 1_6_extrato_erro_5% | D106: =SUM($N$82:$N$96) -> 12 | E106: =D106/$D$107 -> 0.12765957 | F106: =COUNTIF($N$82:$N$96,">0") -> 8 | G106: =D106/F106 -> 1.5 | H106: =F106/D106 -> 0.66666667 | I106: =ROUND(SUMPRODUCT($G$82:$G$96,$N$82:$N$96)/SUM($N$82:$N$96),0) -> 466 | J106: =_xlfn.MAXIFS($G$82:$G$96,$N$82:$N$96,">0") -> 747 | K106: {=SUMPRODUCT(--(SUMIF($C$82:$C$96,$B$112:$B$115,$N$82:$N$96)>0))} -> 4 | L106: =H106/$D$43 -> 4
B107: UNIÃO DAS 4 ABAS (referência — não é cenário de execução) | D107: =SUM($P$82:$P$96) -> 94 | E107: =D107/$D$107 -> 1 | F107: =COUNTIF($P$82:$P$96,">0") -> 15 | G107: =D107/F107 -> 6.2666667 | H107: =F107/D107 -> 0.15957447 | I107: =ROUND(SUMPRODUCT($G$82:$G$96,$P$82:$P$96)/SUM($P$82:$P$96),0) -> 414 | J107: =_xlfn.MAXIFS($G$82:$G$96,$P$82:$P$96,">0") -> 747 | K107: {=SUMPRODUCT(--(SUMIF($C$82:$C$96,$B$112:$B$115,$P$82:$P$96)>0))} -> 4 | L107: =H107/$D$43 -> 0.95744681
B108: Índice de dispersão = (municípios ÷ UCs da amostra) ÷ (municípios ÷ UCs do histórico de Rondônia). Valores acima de 1,00x indicam amostra mais pulverizada que o histórico e, portanto, maior peso relativo do deslocamento. As quatro amostras são alternativas: a linha de união é referência estatística, não um escopo a executar.
B110: 8. ANÁLISE LOGÍSTICA CONSOLIDADA — CLUSTERS GEOGRÁFICOS E ROTEIRIZAÇÃO
B111: Cluster | C111: Municípios do cluster | D111: Município mais distante (km rod.) | E111: Rota da união das 4 abas (km, referência) | F111: Dias de deslocamento da união (referência) | G111: UCs Am. 1_3 | H111: UCs Am. 1_4 | I111: UCs Am. 1_5 | J111: UCs Am. 1_6 | K111: UCs — união (referência) | L111: Dias de inspeção da união (referência) | M111: Dias totais da união com 1 equipe (referência) | N111: Rota Am. 1_3 (km) | O111: Rota Am. 1_4 (km) | P111: Rota Am. 1_5 (km) | Q111: Rota Am. 1_6 (km)
B112: A — Norte / Capital | C112: {=_xlfn.TEXTJOIN(", ",TRUE,IF($C$82:$C$96=$B112,$B$82:$B$96,""))} -> Porto Velho, Cujubim, Candeias do Jamari, Vale do Anari, Machadinho D'oeste | D112: =_xlfn.MAXIFS($G$82:$G$96,$C$82:$C$96,$B112) -> 311 | E112: =ROUND(2*D112*(1+$D$57),0) -> 809 | F112: =ROUNDUP(E112/$D$54,0) -> 2 | G112: =SUMIF($C$82:$C$96,$B112,$H$82:$H$96) -> 10 | H112: =SUMIF($C$82:$C$96,$B112,$J$82:$J$96) -> 9 | I112: =SUMIF($C$82:$C$96,$B112,$L$82:$L$96) -> 4 | J112: =SUMIF($C$82:$C$96,$B112,$N$82:$N$96) -> 1 | K112: =SUMIF($C$82:$C$96,$B112,$P$82:$P$96) -> 24 | L112: =ROUNDUP(K112/$D$59,0) -> 16 | M112: =L112+F112 -> 18 | N112: =IF(SUMIF($C$82:$C$96,$B112,$H$82:$H$96)=0,0,ROUND(2*_xlfn.MAXIFS($G$82:$G$96,$C$82:$C$96,$B112,$H$82:$H$96,">0")*(1+$D$57),0)) -> 790 | O112: =IF(SUMIF($C$82:$C$96,$B112,$J$82:$J$96)=0,0,ROUND(2*_xlfn.MAXIFS($G$82:$G$96,$C$82:$C$96,$B112,$J$82:$J$96,">0")*(1+$D$57),0)) -> 809 | P112: =IF(SUMIF($C$82:$C$96,$B112,$L$82:$L$96)=0,0,ROUND(2*_xlfn.MAXIFS($G$82:$G$96,$C$82:$C$96,$B112,$L$82:$L$96,">0")*(1+$D$57),0)) -> 198 | Q112: =IF(SUMIF($C$82:$C$96,$B112,$N$82:$N$96)=0,0,ROUND(2*_xlfn.MAXIFS($G$82:$G$96,$C$82:$C$96,$B112,$N$82:$N$96,">0")*(1+$D$57),0)) -> 179
B113: B — Oeste / Mamoré | C113: {=_xlfn.TEXTJOIN(", ",TRUE,IF($C$82:$C$96=$B113,$B$82:$B$96,""))} -> Guajará-Mirim, Nova Mamoré | D113: =_xlfn.MAXIFS($G$82:$G$96,$C$82:$C$96,$B113) -> 404 | E113: =ROUND(2*D113*(1+$D$57),0) -> 1050 | F113: =ROUNDUP(E113/$D$54,0) -> 3 | G113: =SUMIF($C$82:$C$96,$B113,$H$82:$H$96) -> 15 | H113: =SUMIF($C$82:$C$96,$B113,$J$82:$J$96) -> 6 | I113: =SUMIF($C$82:$C$96,$B113,$L$82:$L$96) -> 3 | J113: =SUMIF($C$82:$C$96,$B113,$N$82:$N$96) -> 5 | K113: =SUMIF($C$82:$C$96,$B113,$P$82:$P$96) -> 29 | L113: =ROUNDUP(K113/$D$59,0) -> 20 | M113: =L113+F113 -> 23 | N113: =IF(SUMIF($C$82:$C$96,$B113,$H$82:$H$96)=0,0,ROUND(2*_xlfn.MAXIFS($G$82:$G$96,$C$82:$C$96,$B113,$H$82:$H$96,">0")*(1+$D$57),0)) -> 1050 | O113: =IF(SUMIF($C$82:$C$96,$B113,$J$82:$J$96)=0,0,ROUND(2*_xlfn.MAXIFS($G$82:$G$96,$C$82:$C$96,$B113,$J$82:$J$96,">0")*(1+$D$57),0)) -> 1050 | P113: =IF(SUMIF($C$82:$C$96,$B113,$L$82:$L$96)=0,0,ROUND(2*_xlfn.MAXIFS($G$82:$G$96,$C$82:$C$96,$B113,$L$82:$L$96,">0")*(1+$D$57),0)) -> 1050 | Q113: =IF(SUMIF($C$82:$C$96,$B113,$N$82:$N$96)=0,0,ROUND(2*_xlfn.MAXIFS($G$82:$G$96,$C$82:$C$96,$B113,$N$82:$N$96,">0")*(1+$D$57),0)) -> 1050
...

Sheet Estimativa_extra.6

Sheet Planilha4
A1: Município | C1: Município | E1: Município | G1: Município
A2: Alta Floresta d'Oeste | C2: Cujubim | E2: Cacoal | G2: Espigão D'Oeste
A3: Cacoal | C3: Espigão D'Oeste | E3: Candeias do Jamari | G3: Guajará-Mirim
A4: Candeias do Jamari | C4: Guajará-Mirim | E4: Espigão D'Oeste | G4: Ji-Paraná
A5: Cujubim | C5: Ji-Paraná | E5: Guajará-Mirim | G5: Nova Mamoré
A6: Guajará-Mirim | C6: Pimenta Bueno | E6: Ji-Paraná | G6: Pimenta Bueno
A7: Ji-Paraná | C7: Porto Velho | E7: Pimenta Bueno | G7: Porto Velho
A8: Machadinho D'oeste | C8: São Miguel do Guaporé | E8: Porto Velho | G8: São Francisco do Guaporé
A9: Nova Mamoré | C9: Vale do Anari | E9: São Miguel do Guaporé | G9: Vilhena
A10: Pimenta Bueno | C10: Vilhena | E10: Vilhena
A11: Porto Velho
A12: São Francisco do Guaporé
A13: São Miguel do Guaporé
A14: Vilhena

Sheet Estimativa_extra.5

Sheet Estimativa_extra.4

Sheet Estimativa_extra.3

Sheet Amostra 1_3_extrato_erro_5%
A1: UC | B1: Projeto | C1: Município | D1: Data Inicio | E1: Data Fim | F1: Custo(R$) | G1: Cons. | H1: Kit | I1: Regional | J1: Grupo | K1: Poste | L1: Rede AT km | M1: Rede BT km | N1: Medidor | O1: Trafo | P1: Equip. | Q1: VR | R1: Estrato | S1: regionale | T1: NGH | U1: NPH | V1: STATUS | W1: SIGFI | X1: Latitude_UC | Y1: Longitude_UC
A2: 2595147 | B2: POSTO DE SAUDE ALDEIA PALHAL | C2: Vilhena | D2: 45500 | E2: 45500 | F2: 34042.861 | G2: 1 | H2: 1 | J2: 0 | Q2: 144.5618 | R2: 3 | S2: 3 | T2: 187 | U2: 9 | W2: =_xlfn.XLOOKUP(A2,[1]CALCULO_VR!$D:$D,[1]CALCULO_VR!$J:$J) -> 80 | X2: =_xlfn.XLOOKUP(A2,[1]CALCULO_VR!$D:$D,[1]CALCULO_VR!$O:$O) -> -11.479878 | Y2: =_xlfn.XLOOKUP(A2,[1]CALCULO_VR!$D:$D,[1]CALCULO_VR!$P:$P) -> -60.460112
A3: 2595177 | B3: GERSON CINTA LARGA | C3: São Francisco do Guaporé | D3: 45504 | E3: 45504 | F3: 52970.941 | G3: 1 | H3: 1 | J3: 0 | Q3: 70.928033 | R3: 2 | S3: 2 | T3: 225 | U3: 9 | W3: =_xlfn.XLOOKUP(A3,[1]CALCULO_VR!$D:$D,[1]CALCULO_VR!$J:$J) -> 160 | X3: =_xlfn.XLOOKUP(A3,[1]CALCULO_VR!$D:$D,[1]CALCULO_VR!$O:$O) -> -12.408093 | Y3: =_xlfn.XLOOKUP(A3,[1]CALCULO_VR!$D:$D,[1]CALCULO_VR!$P:$P) -> -63.021408
A4: 2595236 | B4: POSTO DE SAUDE ALDEIA CAJUI | C4: São Francisco do Guaporé | D4: 45505 | E4: 45505 | F4: 34042.861 | G4: 1 | H4: 1 | J4: 0 | Q4: 70.937531 | R4: 2 | S4: 2 | T4: 225 | U4: 9 | W4: =_xlfn.XLOOKUP(A4,[1]CALCULO_VR!$D:$D,[1]CALCULO_VR!$J:$J) -> 80 | X4: =_xlfn.XLOOKUP(A4,[1]CALCULO_VR!$D:$D,[1]CALCULO_VR!$O:$O) -> -12.407253 | Y4: =_xlfn.XLOOKUP(A4,[1]CALCULO_VR!$D:$D,[1]CALCULO_VR!$P:$P) -> -63.020755
A5: 2595237 | B5: EIEEFM KON KOATT TUPARI | C5: São Francisco do Guaporé | D5: 45505 | E5: 45505 | F5: 34042.861 | G5: 1 | H5: 1 | J5: 0 | Q5: 70.910302 | R5: 2 | S5: 2 | T5: 225 | U5: 9 | W5: =_xlfn.XLOOKUP(A5,[1]CALCULO_VR!$D:$D,[1]CALCULO_VR!$J:$J) -> 80 | X5: =_xlfn.XLOOKUP(A5,[1]CALCULO_VR!$D:$D,[1]CALCULO_VR!$O:$O) -> -12.40728 | Y5: =_xlfn.XLOOKUP(A5,[1]CALCULO_VR!$D:$D,[1]CALCULO_VR!$P:$P) -> -63.02107
A6: 2595249 | B6: ROSEANE TENHARIN | C6: São Francisco do Guaporé | D6: 45500 | E6: 45500 | F6: 52970.941 | G6: 1 | H6: 1 | J6: 0 | Q6: 90.038796 | R6: 2 | S6: 2 | T6: 225 | U6: 9 | W6: =_xlfn.XLOOKUP(A6,[1]CALCULO_VR!$D:$D,[1]CALCULO_VR!$J:$J) -> 160 | X6: =_xlfn.XLOOKUP(A6,[1]CALCULO_VR!$D:$D,[1]CALCULO_VR!$O:$O) -> -12.34808 | Y6: =_xlfn.XLOOKUP(A6,[1]CALCULO_VR!$D:$D,[1]CALCULO_VR!$P:$P) -> -62.795132
A7: 2595250 | B7: OSMAR MAINTAKA TUPARI | C7: São Francisco do Guaporé | D7: 45500 | E7: 45500 | F7: 52970.941 | G7: 1 | H7: 1 | J7: 0 | Q7: 89.873976 | R7: 2 | S7: 2 | T7: 225 | U7: 9 | V7: Selecionado | W7: =_xlfn.XLOOKUP(A7,[1]CALCULO_VR!$D:$D,[1]CALCULO_VR!$J:$J) -> 160 | X7: =_xlfn.XLOOKUP(A7,[1]CALCULO_VR!$D:$D,[1]CALCULO_VR!$O:$O) -> -12.347225 | Y7: =_xlfn.XLOOKUP(A7,[1]CALCULO_VR!$D:$D,[1]CALCULO_VR!$P:$P) -> -62.796425
A8: 2595269 | B8: EIEEFM KON KOATT TUPARI | C8: São Francisco do Guaporé | D8: 45506 | E8: 45506 | F8: 34042.861 | G8: 1 | H8: 1 | J8: 0 | Q8: 70.974094 | R8: 2 | S8: 2 | T8: 225 | U8: 9 | W8: =_xlfn.XLOOKUP(A8,[1]CALCULO_VR!$D:$D,[1]CALCULO_VR!$J:$J) -> 80 | X8: =_xlfn.XLOOKUP(A8,[1]CALCULO_VR!$D:$D,[1]CALCULO_VR!$O:$O) -> -12.41203 | Y8: =_xlfn.XLOOKUP(A8,[1]CALCULO_VR!$D:$D,[1]CALCULO_VR!$P:$P) -> -63.023502
A9: 2595272 | B9: WALDIR FIRMINO VALE | C9: São Francisco do Guaporé | D9: 45502 | E9: 45502 | F9: 52970.941 | G9: 1 | H9: 1 | J9: 0 | Q9: 89.869751 | R9: 2 | S9: 2 | T9: 225 | U9: 9 | W9: =_xlfn.XLOOKUP(A9,[1]CALCULO_VR!$D:$D,[1]CALCULO_VR!$J:$J) -> 160 | X9: =_xlfn.XLOOKUP(A9,[1]CALCULO_VR!$D:$D,[1]CALCULO_VR!$O:$O) -> -12.347462 | Y9: =_xlfn.XLOOKUP(A9,[1]CALCULO_VR!$D:$D,[1]CALCULO_VR!$P:$P) -> -62.796557
A10: 2583661 | B10: DIVINO GOMES LIMA | C10: Guajará-Mirim | D10: 45459 | E10: 45459 | F10: 34042.861 | G10: 1 | H10: 1 | J10: 0 | Q10: 54.60863 | R10: 1 | S10: 1 | T10: 450 | U10: 27 | W10: =_xlfn.XLOOKUP(A10,[1]CALCULO_VR!$D:$D,[1]CALCULO_VR!$J:$J) -> 80 | X10: =_xlfn.XLOOKUP(A10,[1]CALCULO_VR!$D:$D,[1]CALCULO_VR!$O:$O) -> -10.681757 | Y10: =_xlfn.XLOOKUP(A10,[1]CALCULO_VR!$D:$D,[1]CALCULO_VR!$P:$P) -> -64.832982
A11: 2583662 | B11: JOSE PEREIRA ALVES | C11: Guajará-Mirim | D11: 45458 | E11: 45458 | F11: 34042.861 | G11: 1 | H11: 1 | J11: 0 | Q11: 56.302057 | R11: 1 | S11: 1 | T11: 450 | U11: 27 | W11: =_xlfn.XLOOKUP(A11,[1]CALCULO_VR!$D:$D,[1]CALCULO_VR!$J:$J) -> 80 | X11: =_xlfn.XLOOKUP(A11,[1]CALCULO_VR!$D:$D,[1]CALCULO_VR!$O:$O) -> -10.673628 | Y11: =_xlfn.XLOOKUP(A11,[1]CALCULO_VR!$D:$D,[1]CALCULO_VR!$P:$P) -> -64.818818
A12: 2583663 | B12: ELIETE BIRA MACIEL | C12: Guajará-Mirim | D12: 45459 | E12: 45459 | F12: 34042.861 | G12: 1 | H12: 1 | J12: 0 | Q12: 56.649232 | R12: 1 | S12: 1 | T12: 450 | U12: 27 | W12: =_xlfn.XLOOKUP(A12,[1]CALCULO_VR!$D:$D,[1]CALCULO_VR!$J:$J) -> 80 | X12: =_xlfn.XLOOKUP(A12,[1]CALCULO_VR!$D:$D,[1]CALCULO_VR!$O:$O) -> -10.669567 | Y12: =_xlfn.XLOOKUP(A12,[1]CALCULO_VR!$D:$D,[1]CALCULO_VR!$P:$P) -> -64.816427
A13: 2583664 | B13: JOSE ELEUTERIO FILHO | C13: Guajará-Mirim | D13: 45459 | E13: 45459 | F13: 34042.861 | G13: 1 | H13: 1 | J13: 0 | Q13: 57.074959 | R13: 1 | S13: 1 | T13: 450 | U13: 27 | W13: =_xlfn.XLOOKUP(A13,[1]CALCULO_VR!$D:$D,[1]CALCULO_VR!$J:$J) -> 80 | X13: =_xlfn.XLOOKUP(A13,[1]CALCULO_VR!$D:$D,[1]CALCULO_VR!$O:$O) -> -10.674992 | Y13: =_xlfn.XLOOKUP(A13,[1]CALCULO_VR!$D:$D,[1]CALCULO_VR!$P:$P) -> -64.811327
A14: 2583665 | B14: CARMOZINA FIGUEIREDO DIAS | C14: Guajará-Mirim | D14: 45457 | E14: 45457 | F14: 34042.861 | G14: 1 | H14: 1 | J14: 0 | Q14: 54.358934 | R14: 1 | S14: 1 | T14: 450 | U14: 27 | W14: =_xlfn.XLOOKUP(A14,[1]CALCULO_VR!$D:$D,[1]CALCULO_VR!$J:$J) -> 80 | X14: =_xlfn.XLOOKUP(A14,[1]CALCULO_VR!$D:$D,[1]CALCULO_VR!$O:$O) -> -10.682125 | Y14: =_xlfn.XLOOKUP(A14,[1]CALCULO_VR!$D:$D,[1]CALCULO_VR!$P:$P) -> -64.835237
A15: 2583667 | B15: MARIA IRES DA SILVA RAMOS FERREIRA | C15: Guajará-Mirim | D15: 45458 | E15: 45458 | F15: 34042.861 | G15: 1 | H15: 1 | J15: 0 | Q15: 55.814782 | R15: 1 | S15: 1 | T15: 450 | U15: 27 | W15: =_xlfn.XLOOKUP(A15,[1]CALCULO_VR!$D:$D,[1]CALCULO_VR!$J:$J) -> 80 | X15: =_xlfn.XLOOKUP(A15,[1]CALCULO_VR!$D:$D,[1]CALCULO_VR!$O:$O) -> -10.677553 | Y15: =_xlfn.XLOOKUP(A15,[1]CALCULO_VR!$D:$D,[1]CALCULO_VR!$P:$P) -> -64.822568
A16: 2585819 | B16: DELCILENE ORO MON | C16: Nova Mamoré | D16: 45462 | E16: 45462 | F16: 34042.861 | G16: 1 | H16: 1 | J16: 0 | Q16: 27.565715 | R16: 1 | S16: 1 | T16: 450 | U16: 27 | W16: =_xlfn.XLOOKUP(A16,[1]CALCULO_VR!$D:$D,[1]CALCULO_VR!$J:$J) -> 80 | X16: =_xlfn.XLOOKUP(A16,[1]CALCULO_VR!$D:$D,[1]CALCULO_VR!$O:$O) -> -10.36488 | Y16: =_xlfn.XLOOKUP(A16,[1]CALCULO_VR!$D:$D,[1]CALCULO_VR!$P:$P) -> -65.081663
A17: 2583668 | B17: JOSE CASIMIRO DOS SANTOS | C17: Guajará-Mirim | D17: 45461 | E17: 45461 | F17: 34042.861 | G17: 1 | H17: 1 | J17: 0 | Q17: 60.379099 | R17: 1 | S17: 1 | T17: 450 | U17: 27 | W17: =_xlfn.XLOOKUP(A17,[1]CALCULO_VR!$D:$D,[1]CALCULO_VR!$J:$J) -> 80 | X17: =_xlfn.XLOOKUP(A17,[1]CALCULO_VR!$D:$D,[1]CALCULO_VR!$O:$O) -> -10.640712 | Y17: =_xlfn.XLOOKUP(A17,[1]CALCULO_VR!$D:$D,[1]CALCULO_VR!$P:$P) -> -64.788205
A18: 2583702 | B18: IRACEMA DA SILVA GOMES | C18: Guajará-Mirim | D18: 45458 | E18: 45458 | F18: 34042.861 | G18: 1 | H18: 1 | J18: 0 | Q18: 54.615242 | R18: 1 | S18: 1 | T18: 450 | U18: 27 | W18: =_xlfn.XLOOKUP(A18,[1]CALCULO_VR!$D:$D,[1]CALCULO_VR!$J:$J) -> 80 | X18: =_xlfn.XLOOKUP(A18,[1]CALCULO_VR!$D:$D,[1]CALCULO_VR!$O:$O) -> -10.681718 | Y18: =_xlfn.XLOOKUP(A18,[1]CALCULO_VR!$D:$D,[1]CALCULO_VR!$P:$P) -> -64.832928
A19: 2583669 | B19: CICERO MACIEL DO NASCIMENTO | C19: Guajará-Mirim | D19: 45459 | E19: 45459 | F19: 34042.861 | G19: 1 | H19: 1 | J19: 0 | Q19: 57.711664 | R19: 1 | S19: 1 | T19: 450 | U19: 27 | W19: =_xlfn.XLOOKUP(A19,[1]CALCULO_VR!$D:$D,[1]CALCULO_VR!$J:$J) -> 80 | X19: =_xlfn.XLOOKUP(A19,[1]CALCULO_VR!$D:$D,[1]CALCULO_VR!$O:$O) -> -10.672623 | Y19: =_xlfn.XLOOKUP(A19,[1]CALCULO_VR!$D:$D,[1]CALCULO_VR!$P:$P) -> -64.805865
... A21: 2583410 | B21: FRANCISCO ASSIS DE ALMEIDA | C21: Guajará-Mirim | D21: 45459 | E21: 45459 | F21: 34042.861 | G21: 1 | H21: 1 | J21: 0 | Q21: 57.249923 | R21: 1 | S21: 1 | T21: 450 | U21: 27 | W21: =_xlfn.XLOOKUP(A21,[1]CALCULO_VR!$D:$D,[1]CALCULO_VR!$J:$J) -> 80 | X21: =_xlfn.XLOOKUP(A21,[1]CALCULO_VR!$D:$D,[1]CALCULO_VR!$O:$O) -> -10.673652 | Y21: =_xlfn.XLOOKUP(A21,[1]CALCULO_VR!$D:$D,[1]CALCULO_VR!$P:$P) -> -64.809965
A22: 2583920 | B22: ESCOLA ENSINO FUNDAMENTAL VALDEMAR CABIXI | C22: Guajará-Mirim | D22: 45455 | E22: 45455 | F22: 34042.861 | G22: 1 | H22: 1 | J22: 0 | Q22: 129.99808 | R22: 3 | S22: 3 | T22: 187 | U22: 9 | V22: Selecionado | W22: =_xlfn.XLOOKUP(A22,[1]CALCULO_VR!$D:$D,[1]CALCULO_VR!$J:$J) -> 80 | X22: =_xlfn.XLOOKUP(A22,[1]CALCULO_VR!$D:$D,[1]CALCULO_VR!$O:$O) -> -11.15186 | Y22: =_xlfn.XLOOKUP(A22,[1]CALCULO_VR!$D:$D,[1]CALCULO_VR!$P:$P) -> -64.19707
A23: 2583764 | B23: EVERLANI ORO WIN | C23: Guajará-Mirim | D23: 45456 | E23: 45456 | F23: 34042.861 | G23: 1 | H23: 1 | J23: 0 | Q23: 130.13093 | R23: 3 | S23: 3 | T23: 187 | U23: 9 | W23: =_xlfn.XLOOKUP(A23,[1]CALCULO_VR!$D:$D,[1]CALCULO_VR!$J:$J) -> 80 | X23: =_xlfn.XLOOKUP(A23,[1]CALCULO_VR!$D:$D,[1]CALCULO_VR!$O:$O) -> -11.150538 | Y23: =_xlfn.XLOOKUP(A23,[1]CALCULO_VR!$D:$D,[1]CALCULO_VR!$P:$P) -> -64.195328
A24: 2583766 | B24: WELINTON CABIXI MACURAP | C24: Guajará-Mirim | D24: 45456 | E24: 45456 | F24: 34042.861 | G24: 1 | H24: 1 | J24: 0 | Q24: 129.95073 | R24: 3 | S24: 3 | T24: 187 | U24: 9 | W24: =_xlfn.XLOOKUP(A24,[1]CALCULO_VR!$D:$D,[1]CALCULO_VR!$J:$J) -> 80 | X24: =_xlfn.XLOOKUP(A24,[1]CALCULO_VR!$D:$D,[1]CALCULO_VR!$O:$O) -> -11.152557 | Y24: =_xlfn.XLOOKUP(A24,[1]CALCULO_VR!$D:$D,[1]CALCULO_VR!$P:$P) -> -64.19777
A25: 2583767 | B25: FABRICIO ORO NAO CABIXI | C25: Guajará-Mirim | D25: 45457 | E25: 45457 | F25: 34042.861 | G25: 1 | H25: 1 | J25: 0 | Q25: 130.05216 | R25: 3 | S25: 3 | T25: 187 | U25: 9 | W25: =_xlfn.XLOOKUP(A25,[1]CALCULO_VR!$D:$D,[1]CALCULO_VR!$J:$J) -> 80 | X25: =_xlfn.XLOOKUP(A25,[1]CALCULO_VR!$D:$D,[1]CALCULO_VR!$O:$O) -> -11.15322 | Y25: =_xlfn.XLOOKUP(A25,[1]CALCULO_VR!$D:$D,[1]CALCULO_VR!$P:$P) -> -64.197018
A26: 2583768 | B26: TANIA ORO WIN CABIXI | C26: Guajará-Mirim | D26: 45457 | E26: 45457 | F26: 34042.861 | G26: 1 | H26: 1 | J26: 0 | Q26: 130.05496 | R26: 3 | S26: 3 | T26: 187 | U26: 9 | W26: =_xlfn.XLOOKUP(A26,[1]CALCULO_VR!$D:$D,[1]CALCULO_VR!$J:$J) -> 80 | X26: =_xlfn.XLOOKUP(A26,[1]CALCULO_VR!$D:$D,[1]CALCULO_VR!$O:$O) -> -11.154017 | Y26: =_xlfn.XLOOKUP(A26,[1]CALCULO_VR!$D:$D,[1]CALCULO_VR!$P:$P) -> -64.197268
A27: 2583769 | B27: ELIENETE ORO NAO CABIXI | C27: Guajará-Mirim | D27: 45457 | E27: 45457 | F27: 34042.861 | G27: 1 | H27: 1 | J27: 0 | Q27: 129.97582 | R27: 3 | S27: 3 | T27: 187 | U27: 9 | W27: =_xlfn.XLOOKUP(A27,[1]CALCULO_VR!$D:$D,[1]CALCULO_VR!$J:$J) -> 80 | X27: =_xlfn.XLOOKUP(A27,[1]CALCULO_VR!$D:$D,[1]CALCULO_VR!$O:$O) -> -11.148292 | Y27: =_xlfn.XLOOKUP(A27,[1]CALCULO_VR!$D:$D,[1]CALCULO_VR!$P:$P) -> -64.196057
A28: 2583770 | B28: ROMARIO ORO WIN | C28: Guajará-Mirim | D28: 45457 | E28: 45457 | F28: 34042.861 | G28: 1 | H28: 1 | J28: 0 | Q28: 130.04754 | R28: 3 | S28: 3 | T28: 187 | U28: 9 | W28: =_xlfn.XLOOKUP(A28,[1]CALCULO_VR!$D:$D,[1]CALCULO_VR!$J:$J) -> 80 | X28: =_xlfn.XLOOKUP(A28,[1]CALCULO_VR!$D:$D,[1]CALCULO_VR!$O:$O) -> -11.153937 | Y28: =_xlfn.XLOOKUP(A28,[1]CALCULO_VR!$D:$D,[1]CALCULO_VR!$P:$P) -> -64.197312
A29: 2585862 | B29: ROSILEIA ORO MON | C29: Nova Mamoré | D29: 45462 | E29: 45462 | F29: 34042.861 | G29: 1 | H29: 1 | J29: 0 | Q29: 27.487788 | R29: 1 | S29: 1 | T29: 450 | U29: 27 | W29: =_xlfn.XLOOKUP(A29,[1]CALCULO_VR!$D:$D,[1]CALCULO_VR!$J:$J) -> 80 | X29: =_xlfn.XLOOKUP(A29,[1]CALCULO_VR!$D:$D,[1]CALCULO_VR!$O:$O) -> -10.365348 | Y29: =_xlfn.XLOOKUP(A29,[1]CALCULO_VR!$D:$D,[1]CALCULO_VR!$P:$P) -> -65.082297
A30: 2583772 | B30: JOEL DA SILVA PANTOJA | C30: Guajará-Mirim | D30: 45457 | E30: 45457 | F30: 34042.861 | G30: 1 | H30: 1 | J30: 0 | Q30: 130.1332 | R30: 3 | S30: 3 | T30: 187 | U30: 9 | W30: =_xlfn.XLOOKUP(A30,[1]CALCULO_VR!$D:$D,[1]CALCULO_VR!$J:$J) -> 80 | X30: =_xlfn.XLOOKUP(A30,[1]CALCULO_VR!$D:$D,[1]CALCULO_VR!$O:$O) -> -11.150477 | Y30: =_xlfn.XLOOKUP(A30,[1]CALCULO_VR!$D:$D,[1]CALCULO_VR!$P:$P) -> -64.195285
A31: 2585863 | B31: REGIANE ORO MON | C31: Nova Mamoré | D31: 45462 | E31: 45462 | F31: 34042.861 | G31: 1 | H31: 1 | J31: 0 | Q31: 27.499203 | R31: 1 | S31: 1 | T31: 450 | U31: 27 | W31: =_xlfn.XLOOKUP(A31,[1]CALCULO_VR!$D:$D,[1]CALCULO_VR!$J:$J) -> 80 | X31: =_xlfn.XLOOKUP(A31,[1]CALCULO_VR!$D:$D,[1]CALCULO_VR!$O:$O) -> -10.364902 | Y31: =_xlfn.XLOOKUP(A31,[1]CALCULO_VR!$D:$D,[1]CALCULO_VR!$P:$P) -> -65.082278
A32: 2583659 | B32: RICARDO BORGES DE AMORIM | C32: Guajará-Mirim | D32: 45462 | E32: 45462 | F32: 34042.861 | G32: 1 | H32: 1 | J32: 0 | Q32: 114.8648 | R32: 3 | S32: 3 | T32: 187 | U32: 9 | W32: =_xlfn.XLOOKUP(A32,[1]CALCULO_VR!$D:$D,[1]CALCULO_VR!$J:$J) -> 80 | X32: =_xlfn.XLOOKUP(A32,[1]CALCULO_VR!$D:$D,[1]CALCULO_VR!$O:$O) -> -11.211737 | Y32: =_xlfn.XLOOKUP(A32,[1]CALCULO_VR!$D:$D,[1]CALCULO_VR!$P:$P) -> -64.370842
A33: 2583774 | B33: LUIZA ORO NAO | C33: Guajará-Mirim | D33: 45462 | E33: 45462 | F33: 34042.861 | G33: 1 | H33: 1 | J33: 0 | Q33: 129.40783 | R33: 3 | S33: 3 | T33: 187 | U33: 9 | W33: =_xlfn.XLOOKUP(A33,[1]CALCULO_VR!$D:$D,[1]CALCULO_VR!$J:$J) -> 80 | X33: =_xlfn.XLOOKUP(A33,[1]CALCULO_VR!$D:$D,[1]CALCULO_VR!$O:$O) -> -11.17219 | Y33: =_xlfn.XLOOKUP(A33,[1]CALCULO_VR!$D:$D,[1]CALCULO_VR!$P:$P) -> -64.210073
A34: 2585864 | B34: FRANCIMAR ORO WARAM XIJEIN | C34: Nova Mamoré | D34: 45463 | E34: 45463 | F34: 34042.861 | G34: 1 | H34: 1 | J34: 0 | Q34: 27.553453 | R34: 1 | S34: 1 | T34: 450 | U34: 27 | W34: =_xlfn.XLOOKUP(A34,[1]CALCULO_VR!$D:$D,[1]CALCULO_VR!$J:$J) -> 80 | X34: =_xlfn.XLOOKUP(A34,[1]CALCULO_VR!$D:$D,[1]CALCULO_VR!$O:$O) -> -10.366462 | Y34: =_xlfn.XLOOKUP(A34,[1]CALCULO_VR!$D:$D,[1]CALCULO_VR!$P:$P) -> -65.081472
... A59: 2583922 | B59: ESCOLA JOAO FARIAS DE BARROS | C59: Guajará-Mirim | D59: 45460 | E59: 45460 | F59: 34042.861 | G59: 1 | H59: 1 | J59: 0 | Q59: 140.12685 | R59: 3 | S59: 3 | T59: 187 | U59: 9 | W59: =_xlfn.XLOOKUP(A59,[1]CALCULO_VR!$D:$D,[1]CALCULO_VR!$J:$J) -> 80 | X59: =_xlfn.XLOOKUP(A59,[1]CALCULO_VR!$D:$D,[1]CALCULO_VR!$O:$O) -> -11.087058 | Y59: =_xlfn.XLOOKUP(A59,[1]CALCULO_VR!$D:$D,[1]CALCULO_VR!$P:$P) -> -64.080738
A60: 2583788 | B60: SILVANA KARITIANA | C60: Porto Velho | D60: 45468 | E60: 45468 | F60: 34042.861 | G60: 1 | H60: 1 | J60: 0 | Q60: 48.832983 | R60: 1 | S60: 1 | T60: 450 | U60: 27 | V60: Selecionado | W60: =_xlfn.XLOOKUP(A60,[1]CALCULO_VR!$D:$D,[1]CALCULO_VR!$J:$J) -> 80 | X60: =_xlfn.XLOOKUP(A60,[1]CALCULO_VR!$D:$D,[1]CALCULO_VR!$O:$O) -> -9.192673 | Y60: =_xlfn.XLOOKUP(A60,[1]CALCULO_VR!$D:$D,[1]CALCULO_VR!$P:$P) -> -63.948097
A61: 2583789 | B61: GEICILENE ORO JOWIN | C61: Guajará-Mirim | D61: 45460 | E61: 45460 | F61: 34042.861 | G61: 1 | H61: 1 | J61: 0 | Q61: 140.19906 | R61: 3 | S61: 3 | T61: 187 | U61: 9 | W61: =_xlfn.XLOOKUP(A61,[1]CALCULO_VR!$D:$D,[1]CALCULO_VR!$J:$J) -> 80 | X61: =_xlfn.XLOOKUP(A61,[1]CALCULO_VR!$D:$D,[1]CALCULO_VR!$O:$O) -> -11.087127 | Y61: =_xlfn.XLOOKUP(A61,[1]CALCULO_VR!$D:$D,[1]CALCULO_VR!$P:$P) -> -64.080073
A62: 2583790 | B62: ROSENDA FERREIRA INUMA | C62: Guajará-Mirim | D62: 45469 | E62: 45469 | F62: 34042.861 | G62: 1 | H62: 1 | J62: 0 | Q62: 94.114195 | R62: 2 | S62: 2 | T62: 225 | U62: 9 | W62: =_xlfn.XLOOKUP(A62,[1]CALCULO_VR!$D:$D,[1]CALCULO_VR!$J:$J) -> 80 | X62: =_xlfn.XLOOKUP(A62,[1]CALCULO_VR!$D:$D,[1]CALCULO_VR!$O:$O) -> -11.380303 | Y62: =_xlfn.XLOOKUP(A62,[1]CALCULO_VR!$D:$D,[1]CALCULO_VR!$P:$P) -> -64.72229
A63: 2583791 | B63: NEIDE MORAIS KARITIANA LOPES | C63: Porto Velho | D63: 45469 | E63: 45469 | F63: 34042.861 | G63: 1 | H63: 1 | J63: 0 | Q63: 66.468637 | R63: 1 | S63: 1 | T63: 450 | U63: 27 | W63: =_xlfn.XLOOKUP(A63,[1]CALCULO_VR!$D:$D,[1]CALCULO_VR!$J:$J) -> 80 | X63: =_xlfn.XLOOKUP(A63,[1]CALCULO_VR!$D:$D,[1]CALCULO_VR!$O:$O) -> -9.320778 | Y63: =_xlfn.XLOOKUP(A63,[1]CALCULO_VR!$D:$D,[1]CALCULO_VR!$P:$P) -> -64.064005
A64: 2583792 | B64: JOAO FERREIRA LOPES | C64: Guajará-Mirim | D64: 45468 | E64: 45468 | F64: 34042.861 | G64: 1 | H64: 1 | J64: 0 | Q64: 86.782843 | R64: 2 | S64: 2 | T64: 225 | U64: 9 | W64: =_xlfn.XLOOKUP(A64,[1]CALCULO_VR!$D:$D,[1]CALCULO_VR!$J:$J) -> 80 | X64: =_xlfn.XLOOKUP(A64,[1]CALCULO_VR!$D:$D,[1]CALCULO_VR!$O:$O) -> -11.353395 | Y64: =_xlfn.XLOOKUP(A64,[1]CALCULO_VR!$D:$D,[1]CALCULO_VR!$P:$P) -> -64.791288
A65: 2583923 | B65: ESCOLA INDIGENA NYJNYJI | C65: Porto Velho | D65: 45469 | E65: 45469 | F65: 34042.861 | G65: 1 | H65: 1 | J65: 0 | Q65: 66.366 | R65: 1 | S65: 1 | T65: 450 | U65: 27 | W65: =_xlfn.XLOOKUP(A65,[1]CALCULO_VR!$D:$D,[1]CALCULO_VR!$J:$J) -> 80 | X65: =_xlfn.XLOOKUP(A65,[1]CALCULO_VR!$D:$D,[1]CALCULO_VR!$O:$O) -> -9.32021 | Y65: =_xlfn.XLOOKUP(A65,[1]CALCULO_VR!$D:$D,[1]CALCULO_VR!$P:$P) -> -64.062953
A66: 2583681 | B66: MIZAEL ORO NAO | C66: Guajará-Mirim | D66: 45467 | E66: 45467 | F66: 34042.861 | G66: 1 | H66: 1 | J66: 0 | Q66: 63.415301 | R66: 1 | S66: 1 | T66: 450 | U66: 27 | W66: =_xlfn.XLOOKUP(A66,[1]CALCULO_VR!$D:$D,[1]CALCULO_VR!$J:$J) -> 80 | X66: =_xlfn.XLOOKUP(A66,[1]CALCULO_VR!$D:$D,[1]CALCULO_VR!$O:$O) -> -11.219857 | Y66: =_xlfn.XLOOKUP(A66,[1]CALCULO_VR!$D:$D,[1]CALCULO_VR!$P:$P) -> -64.961832
A67: 2583793 | B67: CELIANE DA SILVA KARITIANA | C67: Porto Velho | D67: 45467 | E67: 45467 | F67: 34042.861 | G67: 1 | H67: 1 | J67: 0 | Q67: 48.79447 | R67: 1 | S67: 1 | T67: 450 | U67: 27 | W67: =_xlfn.XLOOKUP(A67,[1]CALCULO_VR!$D:$D,[1]CALCULO_VR!$J:$J) -> 80 | X67: =_xlfn.XLOOKUP(A67,[1]CALCULO_VR!$D:$D,[1]CALCULO_VR!$O:$O) -> -9.192733 | Y67: =_xlfn.XLOOKUP(A67,[1]CALCULO_VR!$D:$D,[1]CALCULO_VR!$P:$P) -> -63.946527
A68: 2583795 | B68: CELESTINO ORO NAO CABIXI | C68: Guajará-Mirim | D68: 45457 | E68: 45457 | F68: 34042.861 | G68: 1 | H68: 1 | J68: 0 | Q68: 130.05636 | R68: 3 | S68: 3 | T68: 187 | U68: 9 | W68: =_xlfn.XLOOKUP(A68,[1]CALCULO_VR!$D:$D,[1]CALCULO_VR!$J:$J) -> 80 | X68: =_xlfn.XLOOKUP(A68,[1]CALCULO_VR!$D:$D,[1]CALCULO_VR!$O:$O) -> -11.149813 | Y68: =_xlfn.XLOOKUP(A68,[1]CALCULO_VR!$D:$D,[1]CALCULO_VR!$P:$P) -> -64.1958
A69: 2583797 | B69: SOLANGE ORO EO CABIXI | C69: Guajará-Mirim | D69: 45457 | E69: 45457 | F69: 34042.861 | G69: 1 | H69: 1 | J69: 0 | Q69: 130.01907 | R69: 3 | S69: 3 | T69: 187 | U69: 9 | W69: =_xlfn.XLOOKUP(A69,[1]CALCULO_VR!$D:$D,[1]CALCULO_VR!$J:$J) -> 80 | X69: =_xlfn.XLOOKUP(A69,[1]CALCULO_VR!$D:$D,[1]CALCULO_VR!$O:$O) -> -11.150392 | Y69: =_xlfn.XLOOKUP(A69,[1]CALCULO_VR!$D:$D,[1]CALCULO_VR!$P:$P) -> -64.19636
A70: 2583798 | B70: REINALDO GARCIA KARITIANA | C70: Porto Velho | D70: 45469 | E70: 45469 | F70: 34042.861 | G70: 1 | H70: 1 | J70: 0 | Q70: 66.286766 | R70: 1 | S70: 1 | T70: 450 | U70: 27 | W70: =_xlfn.XLOOKUP(A70,[1]CALCULO_VR!$D:$D,[1]CALCULO_VR!$J:$J) -> 80 | X70: =_xlfn.XLOOKUP(A70,[1]CALCULO_VR!$D:$D,[1]CALCULO_VR!$O:$O) -> -9.31918 | Y70: =_xlfn.XLOOKUP(A70,[1]CALCULO_VR!$D:$D,[1]CALCULO_VR!$P:$P) -> -64.063582
A71: 2583924 | B71: POSTO DE SAUDE ALDEIA BOM SAMARITANO | C71: Porto Velho | D71: 45469 | E71: 45469 | F71: 34042.861 | G71: 1 | H71: 1 | J71: 0 | Q71: 66.383 | R71: 1 | S71: 1 | T71: 450 | U71: 27 | W71: =_xlfn.XLOOKUP(A71,[1]CALCULO_VR!$D:$D,[1]CALCULO_VR!$J:$J) -> 80 | X71: =_xlfn.XLOOKUP(A71,[1]CALCULO_VR!$D:$D,[1]CALCULO_VR!$O:$O) -> -9.320353 | Y71: =_xlfn.XLOOKUP(A71,[1]CALCULO_VR!$D:$D,[1]CALCULO_VR!$P:$P) -> -64.063008
A72: 2583800 | B72: HOTO ORO WIN | C72: Guajará-Mirim | D72: 45459 | E72: 45459 | F72: 34042.861 | G72: 1 | H72: 1 | J72: 0 | Q72: 140.22869 | R72: 3 | S72: 3 | T72: 187 | U72: 9 | W72: =_xlfn.XLOOKUP(A72,[1]CALCULO_VR!$D:$D,[1]CALCULO_VR!$J:$J) -> 80 | X72: =_xlfn.XLOOKUP(A72,[1]CALCULO_VR!$D:$D,[1]CALCULO_VR!$O:$O) -> -11.086923 | Y72: =_xlfn.XLOOKUP(A72,[1]CALCULO_VR!$D:$D,[1]CALCULO_VR!$P:$P) -> -64.07974
... A97: 2585879 | B97: REBECA ORO WARAM XIJEIN | C97: Nova Mamoré | D97: 45465 | E97: 45465 | F97: 34042.861 | G97: 1 | H97: 1 | J97: 0 | Q97: 26.652162 | R97: 1 | S97: 1 | T97: 450 | U97: 27 | W97: =_xlfn.XLOOKUP(A97,[1]CALCULO_VR!$D:$D,[1]CALCULO_VR!$J:$J) -> 80 | X97: =_xlfn.XLOOKUP(A97,[1]CALCULO_VR!$D:$D,[1]CALCULO_VR!$O:$O) -> -10.328627 | Y97: =_xlfn.XLOOKUP(A97,[1]CALCULO_VR!$D:$D,[1]CALCULO_VR!$P:$P) -> -65.10061
A98: 2583928 | B98: ESCOLA INDIGINA ESTADUAL DE ENSINO | C98: Porto Velho | D98: 45467 | E98: 45467 | F98: 34042.861 | G98: 1 | H98: 1 | J98: 0 | Q98: 48.798952 | R98: 1 | S98: 1 | T98: 450 | U98: 27 | V98: Selecionado | W98: =_xlfn.XLOOKUP(A98,[1]CALCULO_VR!$D:$D,[1]CALCULO_VR!$J:$J) -> 80 | X98: =_xlfn.XLOOKUP(A98,[1]CALCULO_VR!$D:$D,[1]CALCULO_VR!$O:$O) -> -9.192465 | Y98: =_xlfn.XLOOKUP(A98,[1]CALCULO_VR!$D:$D,[1]CALCULO_VR!$P:$P) -> -63.94769
A99: 2583692 | B99: YURI ALEXANDRE DOS SANTOS | C99: Guajará-Mirim | D99: 45467 | E99: 45467 | F99: 34042.861 | G99: 1 | H99: 1 | J99: 0 | Q99: 45.685981 | R99: 1 | S99: 1 | T99: 450 | U99: 27 | W99: =_xlfn.XLOOKUP(A99,[1]CALCULO_VR!$D:$D,[1]CALCULO_VR!$J:$J) -> 80 | X99: =_xlfn.XLOOKUP(A99,[1]CALCULO_VR!$D:$D,[1]CALCULO_VR!$O:$O) -> -11.095315 | Y99: =_xlfn.XLOOKUP(A99,[1]CALCULO_VR!$D:$D,[1]CALCULO_VR!$P:$P) -> -65.063307
A100: 2583819 | B100: MBURIETE URU EU WAU WAU | C100: Porto Velho | D100: 45470 | E100: 45470 | F100: 34042.861 | G100: 1 | H100: 1 | J100: 0 | Q100: 121.96584 | R100: 3 | S100: 3 | T100: 187 | U100: 9 | W100: =_xlfn.XLOOKUP(A100,[1]CALCULO_VR!$D:$D,[1]CALCULO_VR!$J:$J) -> 80 | X100: =_xlfn.XLOOKUP(A100,[1]CALCULO_VR!$D:$D,[1]CALCULO_VR!$O:$O) -> -9.754548 | Y100: =_xlfn.XLOOKUP(A100,[1]CALCULO_VR!$D:$D,[1]CALCULO_VR!$P:$P) -> -64.319052
A101: 2583820 | B101: LENICE ORO EO | C101: Guajará-Mirim | D101: 45459 | E101: 45459 | F101: 34042.861 | G101: 1 | H101: 1 | J101: 0 | Q101: 140.24961 | R101: 3 | S101: 3 | T101: 187 | U101: 9 | W101: =_xlfn.XLOOKUP(A101,[1]CALCULO_VR!$D:$D,[1]CALCULO_VR!$J:$J) -> 80 | X101: =_xlfn.XLOOKUP(A101,[1]CALCULO_VR!$D:$D,[1]CALCULO_VR!$O:$O) -> -11.08526 | Y101: =_xlfn.XLOOKUP(A101,[1]CALCULO_VR!$D:$D,[1]CALCULO_VR!$P:$P) -> -64.079113
A102: 2583822 | B102: CEZAR MERCADO BAZAN | C102: Guajará-Mirim | D102: 45459 | E102: 45459 | F102: 34042.861 | G102: 1 | H102: 1 | J102: 0 | Q102: 140.2579 | R102: 3 | S102: 3 | T102: 187 | U102: 9 | W102: =_xlfn.XLOOKUP(A102,[1]CALCULO_VR!$D:$D,[1]CALCULO_VR!$J:$J) -> 80 | X102: =_xlfn.XLOOKUP(A102,[1]CALCULO_VR!$D:$D,[1]CALCULO_VR!$O:$O) -> -11.086715 | Y102: =_xlfn.XLOOKUP(A102,[1]CALCULO_VR!$D:$D,[1]CALCULO_VR!$P:$P) -> -64.07941
A103: 2583823 | B103: CARLOS ANDRE ORO WIM | C103: Guajará-Mirim | D103: 45459 | E103: 45459 | F103: 34042.861 | G103: 1 | H103: 1 | J103: 0 | Q103: 140.25163 | R103: 3 | S103: 3 | T103: 187 | U103: 9 | W103: =_xlfn.XLOOKUP(A103,[1]CALCULO_VR!$D:$D,[1]CALCULO_VR!$J:$J) -> 80 | X103: =_xlfn.XLOOKUP(A103,[1]CALCULO_VR!$D:$D,[1]CALCULO_VR!$O:$O) -> -11.085303 | Y103: =_xlfn.XLOOKUP(A103,[1]CALCULO_VR!$D:$D,[1]CALCULO_VR!$P:$P) -> -64.079105
A104: 2583824 | B104: NATALICIO ORO NAO | C104: Guajará-Mirim | D104: 45459 | E104: 45459 | F104: 34042.861 | G104: 1 | H104: 1 | J104: 0 | Q104: 140.22868 | R104: 3 | S104: 3 | T104: 187 | U104: 9 | W104: =_xlfn.XLOOKUP(A104,[1]CALCULO_VR!$D:$D,[1]CALCULO_VR!$J:$J) -> 80 | X104: =_xlfn.XLOOKUP(A104,[1]CALCULO_VR!$D:$D,[1]CALCULO_VR!$O:$O) -> -11.0858 | Y104: =_xlfn.XLOOKUP(A104,[1]CALCULO_VR!$D:$D,[1]CALCULO_VR!$P:$P) -> -64.07945
A105: 2583825 | B105: INHINHAM ORO WIN | C105: Guajará-Mirim | D105: 45459 | E105: 45459 | F105: 34042.861 | G105: 1 | H105: 1 | J105: 0 | Q105: 140.27851 | R105: 3 | S105: 3 | T105: 187 | U105: 9 | W105: =_xlfn.XLOOKUP(A105,[1]CALCULO_VR!$D:$D,[1]CALCULO_VR!$J:$J) -> 80 | X105: =_xlfn.XLOOKUP(A105,[1]CALCULO_VR!$D:$D,[1]CALCULO_VR!$O:$O) -> -11.085443 | Y105: =_xlfn.XLOOKUP(A105,[1]CALCULO_VR!$D:$D,[1]CALCULO_VR!$P:$P) -> -64.078887
A106: 2585875 | B106: MARIA LUCIA ORO MON | C106: Nova Mamoré | D106: 45463 | E106: 45463 | F106: 34042.861 | G106: 1 | H106: 1 | J106: 0 | Q106: 27.537724 | R106: 1 | S106: 1 | T106: 450 | U106: 27 | W106: =_xlfn.XLOOKUP(A106,[1]CALCULO_VR!$D:$D,[1]CALCULO_VR!$J:$J) -> 80 | X106: =_xlfn.XLOOKUP(A106,[1]CALCULO_VR!$D:$D,[1]CALCULO_VR!$O:$O) -> -10.362237 | Y106: =_xlfn.XLOOKUP(A106,[1]CALCULO_VR!$D:$D,[1]CALCULO_VR!$P:$P) -> -65.082458
A107: 2585876 | B107: DIANA ORO MON | C107: Nova Mamoré | D107: 45462 | E107: 45462 | F107: 34042.861 | G107: 1 | H107: 1 | J107: 0 | Q107: 27.456662 | R107: 1 | S107: 1 | T107: 450 | U107: 27 | W107: =_xlfn.XLOOKUP(A107,[1]CALCULO_VR!$D:$D,[1]CALCULO_VR!$J:$J) -> 80 | X107: =_xlfn.XLOOKUP(A107,[1]CALCULO_VR!$D:$D,[1]CALCULO_VR!$O:$O) -> -10.36371 | Y107: =_xlfn.XLOOKUP(A107,[1]CALCULO_VR!$D:$D,[1]CALCULO_VR!$P:$P) -> -65.082912
A108: 2583826 | B108: SALOMAO ORO WIN | C108: Guajará-Mirim | D108: 45459 | E108: 45459 | F108: 34042.861 | G108: 1 | H108: 1 | J108: 0 | Q108: 140.15336 | R108: 3 | S108: 3 | T108: 187 | U108: 9 | V108: Selecionado | W108: =_xlfn.XLOOKUP(A108,[1]CALCULO_VR!$D:$D,[1]CALCULO_VR!$J:$J) -> 80 | X108: =_xlfn.XLOOKUP(A108,[1]CALCULO_VR!$D:$D,[1]CALCULO_VR!$O:$O) -> -11.086663 | Y108: =_xlfn.XLOOKUP(A108,[1]CALCULO_VR!$D:$D,[1]CALCULO_VR!$P:$P) -> -64.080385
A109: 2583827 | B109: FREDERICO ORO WIN | C109: Guajará-Mirim | D109: 45460 | E109: 45460 | F109: 34042.861 | G109: 1 | H109: 1 | J109: 0 | Q109: 140.15432 | R109: 3 | S109: 3 | T109: 187 | U109: 9 | W109: =_xlfn.XLOOKUP(A109,[1]CALCULO_VR!$D:$D,[1]CALCULO_VR!$J:$J) -> 80 | X109: =_xlfn.XLOOKUP(A109,[1]CALCULO_VR!$D:$D,[1]CALCULO_VR!$O:$O) -> -11.086957 | Y109: =_xlfn.XLOOKUP(A109,[1]CALCULO_VR!$D:$D,[1]CALCULO_VR!$P:$P) -> -64.080452
A110: 2583929 | B110: CASA DE APOIO ALDEIA PEDREIRA | C110: Guajará-Mirim | D110: 45456 | E110: 45456 | F110: 34042.861 | G110: 1 | H110: 1 | J110: 0 | Q110: 129.99959 | R110: 3 | S110: 3 | T110: 187 | U110: 9 | W110: =_xlfn.XLOOKUP(A110,[1]CALCULO_VR!$D:$D,[1]CALCULO_VR!$J:$J) -> 80 | X110: =_xlfn.XLOOKUP(A110,[1]CALCULO_VR!$D:$D,[1]CALCULO_VR!$O:$O) -> -11.152488 | Y110: =_xlfn.XLOOKUP(A110,[1]CALCULO_VR!$D:$D,[1]CALCULO_VR!$P:$P) -> -64.197273
A111: 2583598 | B111: JOSIMAR DOS SANTOS BRITES | C111: Guajará-Mirim | D111: 45473 | E111: 45473 | F111: 34042.861 | G111: 1 | H111: 1 | J111: 0 | Q111: 122.27517 | R111: 3 | S111: 3 | T111: 187 | U111: 9 | W111: =_xlfn.XLOOKUP(A111,[1]CALCULO_VR!$D:$D,[1]CALCULO_VR!$J:$J) -> 80 | X111: =_xlfn.XLOOKUP(A111,[1]CALCULO_VR!$D:$D,[1]CALCULO_VR!$O:$O) -> -11.823138 | Y111: =_xlfn.XLOOKUP(A111,[1]CALCULO_VR!$D:$D,[1]CALCULO_VR!$P:$P) -> -64.98837
A112: 2583600 | B112: DAVID VARGAS ZABALA | C112: Guajará-Mirim | D112: 45473 | E112: 45473 | F112: 34042.861 | G112: 1 | H112: 1 | J112: 0 | Q112: 124.04786 | R112: 3 | S112: 3 | T112: 187 | U112: 9 | W112: =_xlfn.XLOOKUP(A112,[1]CALCULO_VR!$D:$D,[1]CALCULO_VR!$J:$J) -> 80 | X112: =_xlfn.XLOOKUP(A112,[1]CALCULO_VR!$D:$D,[1]CALCULO_VR!$O:$O) -> -11.798917 | Y112: =_xlfn.XLOOKUP(A112,[1]CALCULO_VR!$D:$D,[1]CALCULO_VR!$P:$P) -> -64.874983
A113: 2583828 | B113: WILLIAS DA SILVA ERVIS | C113: Guajará-Mirim | D113: 45470 | E113: 45470 | F113: 34042.861 | G113: 1 | H113: 1 | J113: 0 | Q113: 89.309673 | R113: 2 | S113: 2 | T113: 225 | U113: 9 | W113: =_xlfn.XLOOKUP(A113,[1]CALCULO_VR!$D:$D,[1]CALCULO_VR!$J:$J) -> 80 | X113: =_xlfn.XLOOKUP(A113,[1]CALCULO_VR!$D:$D,[1]CALCULO_VR!$O:$O) -> -11.234253 | Y113: =_xlfn.XLOOKUP(A113,[1]CALCULO_VR!$D:$D,[1]CALCULO_VR!$P:$P) -> -64.653473
A114: 2583601 | B114: GEDEON COSTA BARBOZA | C114: Guajará-Mirim | D114: 45473 | E114: 45473 | F114: 34042.861 | G114: 1 | H114: 1 | J114: 0 | Q114: 125.3257 | R114: 3 | S114: 3 | T114: 187 | U114: 9 | W114: =_xlfn.XLOOKUP(A114,[1]CALCULO_VR!$D:$D,[1]CALCULO_VR!$J:$J) -> 80 | X114: =_xlfn.XLOOKUP(A114,[1]CALCULO_VR!$D:$D,[1]CALCULO_VR!$O:$O) -> -11.804793 | Y114: =_xlfn.XLOOKUP(A114,[1]CALCULO_VR!$D:$D,[1]CALCULO_VR!$P:$P) -> -64.859393
A115: 2583829 | B115: JOSE CARLOS KARIPUNA TUPINAMBA | C115: Porto Velho | D115: 45471 | E115: 45471 | F115: 34042.861 | G115: 1 | H115: 1 | J115: 0 | Q115: 122.00627 | R115: 3 | S115: 3 | T115: 187 | U115: 9 | W115: =_xlfn.XLOOKUP(A115,[1]CALCULO_VR!$D:$D,[1]CALCULO_VR!$J:$J) -> 80 | X115: =_xlfn.XLOOKUP(A115,[1]CALCULO_VR!$D:$D,[1]CALCULO_VR!$O:$O) -> -9.754798 | Y115: =_xlfn.XLOOKUP(A115,[1]CALCULO_VR!$D:$D,[1]CALCULO_VR!$P:$P) -> -64.319373
A116: 2583830 | B116: ERIC ONE KARIPUNA DAVECAI | C116: Porto Velho | D116: 45472 | E116: 45472 | F116: 34042.861 | G116: 1 | H116: 1 | J116: 0 | Q116: 121.95847 | R116: 3 | S116: 3 | T116: 187 | U116: 9 | W116: =_xlfn.XLOOKUP(A116,[1]CALCULO_VR!$D:$D,[1]CALCULO_VR!$J:$J) -> 80 | X116: =_xlfn.XLOOKUP(A116,[1]CALCULO_VR!$D:$D,[1]CALCULO_VR!$O:$O) -> -9.755073 | Y116: =_xlfn.XLOOKUP(A116,[1]CALCULO_VR!$D:$D,[1]CALCULO_VR!$P:$P) -> -64.317808
A117: 2583833 | B117: BATITI KARIPUNA PAIAPEGA | C117: Porto Velho | D117: 45472 | E117: 45472 | F117: 34042.861 | G117: 1 | H117: 1 | J117: 0 | Q117: 121.97977 | R117: 3 | S117: 3 | T117: 187 | U117: 9 | W117: =_xlfn.XLOOKUP(A117,[1]CALCULO_VR!$D:$D,[1]CALCULO_VR!$J:$J) -> 80 | X117: =_xlfn.XLOOKUP(A117,[1]CALCULO_VR!$D:$D,[1]CALCULO_VR!$O:$O) -> -9.75444 | Y117: =_xlfn.XLOOKUP(A117,[1]CALCULO_VR!$D:$D,[1]CALCULO_VR!$P:$P) -> -64.319565
A118: 2583693 | B118: RITA SOUZA RUFINO | C118: Guajará-Mirim | D118: 45470 | E118: 45470 | F118: 34042.861 | G118: 1 | H118: 1 | J118: 0 | Q118: 65.677039 | R118: 1 | S118: 1 | T118: 450 | U118: 27 | W118: =_xlfn.XLOOKUP(A118,[1]CALCULO_VR!$D:$D,[1]CALCULO_VR!$J:$J) -> 80 | X118: =_xlfn.XLOOKUP(A118,[1]CALCULO_VR!$D:$D,[1]CALCULO_VR!$O:$O) -> -11.199123 | Y118: =_xlfn.XLOOKUP(A118,[1]CALCULO_VR!$D:$D,[1]CALCULO_VR!$P:$P) -> -64.906375
A119: 2583836 | B119: FRANCISCO DELGADO KARITIANA | C119: Porto Velho | D119: 45473 | E119: 45473 | F119: 34042.861 | G119: 1 | H119: 1 | J119: 0 | Q119: 84.805223 | R119: 2 | S119: 2 | T119: 225 | U119: 9 | W119: =_xlfn.XLOOKUP(A119,[1]CALCULO_VR!$D:$D,[1]CALCULO_VR!$J:$J) -> 80 | X119: =_xlfn.XLOOKUP(A119,[1]CALCULO_VR!$D:$D,[1]CALCULO_VR!$O:$O) -> -9.440398 | Y119: =_xlfn.XLOOKUP(A119,[1]CALCULO_VR!$D:$D,[1]CALCULO_VR!$P:$P) -> -64.197652
A120: 2583700 | B120: VANUSA URUATI RUFINO | C120: Guajará-Mirim | D120: 45470 | E120: 45470 | F120: 34042.861 | G120: 1 | H120: 1 | J120: 0 | Q120: 108.1276 | R120: 2 | S120: 2 | T120: 225 | U120: 9 | W120: =_xlfn.XLOOKUP(A120,[1]CALCULO_VR!$D:$D,[1]CALCULO_VR!$J:$J) -> 80 | X120: =_xlfn.XLOOKUP(A120,[1]CALCULO_VR!$D:$D,[1]CALCULO_VR!$O:$O) -> -11.255777 | Y120: =_xlfn.XLOOKUP(A120,[1]CALCULO_VR!$D:$D,[1]CALCULO_VR!$P:$P) -> -64.463485
... A135: 2583869 | B135: FRANCISCO FERREIRA DA SILVA | C135: Guajará-Mirim | D135: 45470 | E135: 45470 | F135: 34042.861 | G135: 1 | H135: 1 | J135: 0 | Q135: 84.371148 | R135: 2 | S135: 2 | T135: 225 | U135: 9 | W135: =_xlfn.XLOOKUP(A135,[1]CALCULO_VR!$D:$D,[1]CALCULO_VR!$J:$J) -> 80 | X135: =_xlfn.XLOOKUP(A135,[1]CALCULO_VR!$D:$D,[1]CALCULO_VR!$O:$O) -> -11.33905 | Y135: =_xlfn.XLOOKUP(A135,[1]CALCULO_VR!$D:$D,[1]CALCULO_VR!$P:$P) -> -64.808098
A136: 2585878 | B136: ANGELINA ORO MON | C136: Nova Mamoré | D136: 45463 | E136: 45463 | F136: 34042.861 | G136: 1 | H136: 1 | J136: 0 | Q136: 27.533476 | R136: 1 | S136: 1 | T136: 450 | U136: 27 | V136: Selecionado | W136: =_xlfn.XLOOKUP(A136,[1]CALCULO_VR!$D:$D,[1]CALCULO_VR!$J:$J) -> 80 | X136: =_xlfn.XLOOKUP(A136,[1]CALCULO_VR!$D:$D,[1]CALCULO_VR!$O:$O) -> -10.368292 | Y136: =_xlfn.XLOOKUP(A136,[1]CALCULO_VR!$D:$D,[1]CALCULO_VR!$P:$P) -> -65.081318
A137: 2583871 | B137: REGINA ORO WIN | C137: Guajará-Mirim | D137: 45459 | E137: 45459 | F137: 34042.861 | G137: 1 | H137: 1 | J137: 0 | Q137: 140.18986 | R137: 3 | S137: 3 | T137: 187 | U137: 9 | W137: =_xlfn.XLOOKUP(A137,[1]CALCULO_VR!$D:$D,[1]CALCULO_VR!$J:$J) -> 80 | X137: =_xlfn.XLOOKUP(A137,[1]CALCULO_VR!$D:$D,[1]CALCULO_VR!$O:$O) -> -11.085385 | Y137: =_xlfn.XLOOKUP(A137,[1]CALCULO_VR!$D:$D,[1]CALCULO_VR!$P:$P) -> -64.07971
A138: 2585874 | B138: REBECA ORO WARAM XIJEIN | C138: Nova Mamoré | D138: 45464 | E138: 45464 | F138: 34042.861 | G138: 1 | H138: 1 | J138: 0 | Q138: 26.513264 | R138: 1 | S138: 1 | T138: 450 | U138: 27 | W138: =_xlfn.XLOOKUP(A138,[1]CALCULO_VR!$D:$D,[1]CALCULO_VR!$J:$J) -> 80 | X138: =_xlfn.XLOOKUP(A138,[1]CALCULO_VR!$D:$D,[1]CALCULO_VR!$O:$O) -> -10.326222 | Y138: =_xlfn.XLOOKUP(A138,[1]CALCULO_VR!$D:$D,[1]CALCULO_VR!$P:$P) -> -65.10289
A139: 2583872 | B139: RIKELVI MACURAP CABIXI | C139: Guajará-Mirim | D139: 45457 | E139: 45457 | F139: 34042.861 | G139: 1 | H139: 1 | J139: 0 | Q139: 130.18577 | R139: 3 | S139: 3 | T139: 187 | U139: 9 | W139: =_xlfn.XLOOKUP(A139,[1]CALCULO_VR!$D:$D,[1]CALCULO_VR!$J:$J) -> 80 | X139: =_xlfn.XLOOKUP(A139,[1]CALCULO_VR!$D:$D,[1]CALCULO_VR!$O:$O) -> -11.150807 | Y139: =_xlfn.XLOOKUP(A139,[1]CALCULO_VR!$D:$D,[1]CALCULO_VR!$P:$P) -> -64.19489
A140: 2583672 | B140: ALCILENE CASIMIRO DOS SANTOS | C140: Guajará-Mirim | D140: 45460 | E140: 45460 | F140: 34042.861 | G140: 1 | H140: 1 | J140: 0 | Q140: 60.536913 | R140: 1 | S140: 1 | T140: 450 | U140: 27 | W140: =_xlfn.XLOOKUP(A140,[1]CALCULO_VR!$D:$D,[1]CALCULO_VR!$J:$J) -> 80 | X140: =_xlfn.XLOOKUP(A140,[1]CALCULO_VR!$D:$D,[1]CALCULO_VR!$O:$O) -> -10.634712 | Y140: =_xlfn.XLOOKUP(A140,[1]CALCULO_VR!$D:$D,[1]CALCULO_VR!$P:$P) -> -64.788298
A141: 2583643 | B141: UEVERSON COUTINHO DA SILVA | C141: Guajará-Mirim | D141: 45474 | E141: 45474 | F141: 34042.861 | G141: 1 | H141: 1 | J141: 0 | Q141: 123.01667 | R141: 3 | S141: 3 | T141: 187 | U141: 9 | W141: =_xlfn.XLOOKUP(A141,[1]CALCULO_VR!$D:$D,[1]CALCULO_VR!$J:$J) -> 80 | X141: =_xlfn.XLOOKUP(A141,[1]CALCULO_VR!$D:$D,[1]CALCULO_VR!$O:$O) -> -11.78909 | Y141: =_xlfn.XLOOKUP(A141,[1]CALCULO_VR!$D:$D,[1]CALCULO_VR!$P:$P) -> -64.875635
A142: 2583673 | B142: CARLOS FERREIRA NEVES | C142: Guajará-Mirim | D142: 45459 | E142: 45459 | F142: 34042.861 | G142: 1 | H142: 1 | J142: 0 | Q142: 56.748775 | R142: 1 | S142: 1 | T142: 450 | U142: 27 | W142: =_xlfn.XLOOKUP(A142,[1]CALCULO_VR!$D:$D,[1]CALCULO_VR!$J:$J) -> 80 | X142: =_xlfn.XLOOKUP(A142,[1]CALCULO_VR!$D:$D,[1]CALCULO_VR!$O:$O) -> -10.680353 | Y142: =_xlfn.XLOOKUP(A142,[1]CALCULO_VR!$D:$D,[1]CALCULO_VR!$P:$P) -> -64.813318
A143: 2583933 | B143: ASSOCIACAO MARIA PIWAN ORO | C143: Guajará-Mirim | D143: 45456 | E143: 45456 | F143: 34042.861 | G143: 1 | H143: 1 | J143: 0 | Q143: 129.94411 | R143: 3 | S143: 3 | T143: 187 | U143: 9 | W143: =_xlfn.XLOOKUP(A143,[1]CALCULO_VR!$D:$D,[1]CALCULO_VR!$J:$J) -> 80 | X143: =_xlfn.XLOOKUP(A143,[1]CALCULO_VR!$D:$D,[1]CALCULO_VR!$O:$O) -> -11.151477 | Y143: =_xlfn.XLOOKUP(A143,[1]CALCULO_VR!$D:$D,[1]CALCULO_VR!$P:$P) -> -64.19746
A144: 2583674 | B144: WASHINGTON LUIZ CASSIMIRO DA SILVA | C144: Guajará-Mirim | D144: 45460 | E144: 45460 | F144: 34042.861 | G144: 1 | H144: 1 | J144: 0 | Q144: 60.67794 | R144: 1 | S144: 1 | T144: 450 | U144: 27 | W144: =_xlfn.XLOOKUP(A144,[1]CALCULO_VR!$D:$D,[1]CALCULO_VR!$J:$J) -> 80 | X144: =_xlfn.XLOOKUP(A144,[1]CALCULO_VR!$D:$D,[1]CALCULO_VR!$O:$O) -> -10.633953 | Y144: =_xlfn.XLOOKUP(A144,[1]CALCULO_VR!$D:$D,[1]CALCULO_VR!$P:$P) -> -64.787168
A145: 2583675 | B145: ALDELINNO FIRMINO NEVES | C145: Guajará-Mirim | D145: 45460 | E145: 45460 | F145: 34042.861 | G145: 1 | H145: 1 | J145: 0 | Q145: 56.729213 | R145: 1 | S145: 1 | T145: 450 | U145: 27 | V145: Selecionado | W145: =_xlfn.XLOOKUP(A145,[1]CALCULO_VR!$D:$D,[1]CALCULO_VR!$J:$J) -> 80 | X145: =_xlfn.XLOOKUP(A145,[1]CALCULO_VR!$D:$D,[1]CALCULO_VR!$O:$O) -> -10.680527 | Y145: =_xlfn.XLOOKUP(A145,[1]CALCULO_VR!$D:$D,[1]CALCULO_VR!$P:$P) -> -64.813467
A146: 2583873 | B146: SERGIO ORO WIN CABIXI | C146: Guajará-Mirim | D146: 45456 | E146: 45456 | F146: 34042.861 | G146: 1 | H146: 1 | J146: 0 | Q146: 130.0693 | R146: 3 | S146: 3 | T146: 187 | U146: 9 | W146: =_xlfn.XLOOKUP(A146,[1]CALCULO_VR!$D:$D,[1]CALCULO_VR!$J:$J) -> 80 | X146: =_xlfn.XLOOKUP(A146,[1]CALCULO_VR!$D:$D,[1]CALCULO_VR!$O:$O) -> -11.15165 | Y146: =_xlfn.XLOOKUP(A146,[1]CALCULO_VR!$D:$D,[1]CALCULO_VR!$P:$P) -> -64.196308
A147: 2583874 | B147: ROSA MACURAPE | C147: Guajará-Mirim | D147: 45458 | E147: 45458 | F147: 34042.861 | G147: 1 | H147: 1 | J147: 0 | Q147: 140.3633 | R147: 3 | S147: 3 | T147: 187 | U147: 9 | W147: =_xlfn.XLOOKUP(A147,[1]CALCULO_VR!$D:$D,[1]CALCULO_VR!$J:$J) -> 80 | X147: =_xlfn.XLOOKUP(A147,[1]CALCULO_VR!$D:$D,[1]CALCULO_VR!$O:$O) -> -11.07969 | Y147: =_xlfn.XLOOKUP(A147,[1]CALCULO_VR!$D:$D,[1]CALCULO_VR!$P:$P) -> -64.07662
A148: 2585880 | B148: JO ORO MON | C148: Nova Mamoré | D148: 45462 | E148: 45462 | F148: 34042.861 | G148: 1 | H148: 1 | J148: 0 | Q148: 27.574873 | R148: 1 | S148: 1 | T148: 450 | U148: 27 | W148: =_xlfn.XLOOKUP(A148,[1]CALCULO_VR!$D:$D,[1]CALCULO_VR!$J:$J) -> 80 | X148: =_xlfn.XLOOKUP(A148,[1]CALCULO_VR!$D:$D,[1]CALCULO_VR!$O:$O) -> -10.365242 | Y148: =_xlfn.XLOOKUP(A148,[1]CALCULO_VR!$D:$D,[1]CALCULO_VR!$P:$P) -> -65.081507
A149: 2583676 | B149: RONALDO SOUZA DE HOLANDA | C149: Guajará-Mirim | D149: 45459 | E149: 45459 | F149: 34042.861 | G149: 1 | H149: 1 | J149: 0 | Q149: 58.47153 | R149: 1 | S149: 1 | T149: 450 | U149: 27 | W149: =_xlfn.XLOOKUP(A149,[1]CALCULO_VR!$D:$D,[1]CALCULO_VR!$J:$J) -> 80 | X149: =_xlfn.XLOOKUP(A149,[1]CALCULO_VR!$D:$D,[1]CALCULO_VR!$O:$O) -> -10.67119 | Y149: =_xlfn.XLOOKUP(A149,[1]CALCULO_VR!$D:$D,[1]CALCULO_VR!$P:$P) -> -64.799065
A150: 2583703 | B150: ANDREIA ORO EO | C150: Guajará-Mirim | D150: 45475 | E150: 45475 | F150: 34042.861 | G150: 1 | H150: 1 | J150: 0 | Q150: 35.230416 | R150: 1 | S150: 1 | T150: 450 | U150: 27 | W150: =_xlfn.XLOOKUP(A150,[1]CALCULO_VR!$D:$D,[1]CALCULO_VR!$J:$J) -> 80 | X150: =_xlfn.XLOOKUP(A150,[1]CALCULO_VR!$D:$D,[1]CALCULO_VR!$O:$O) -> -11.087475 | Y150: =_xlfn.XLOOKUP(A150,[1]CALCULO_VR!$D:$D,[1]CALCULO_VR!$P:$P) -> -65.277897
A151: 2583704 | B151: NERIZE JABUTI | C151: Guajará-Mirim | D151: 45475 | E151: 45475 | F151: 34042.861 | G151: 1 | H151: 1 | J151: 0 | Q151: 35.081457 | R151: 1 | S151: 1 | T151: 450 | U151: 27 | W151: =_xlfn.XLOOKUP(A151,[1]CALCULO_VR!$D:$D,[1]CALCULO_VR!$J:$J) -> 80 | X151: =_xlfn.XLOOKUP(A151,[1]CALCULO_VR!$D:$D,[1]CALCULO_VR!$O:$O) -> -11.086058 | Y151: =_xlfn.XLOOKUP(A151,[1]CALCULO_VR!$D:$D,[1]CALCULO_VR!$P:$P) -> -65.277453
A152: 2583875 | B152: ALBERTO AJURU | C152: Guajará-Mirim | D152: 45475 | E152: 45475 | F152: 34042.861 | G152: 1 | H152: 1 | J152: 0 | Q152: 147.95098 | R152: 3 | S152: 3 | T152: 187 | U152: 9 | W152: =_xlfn.XLOOKUP(A152,[1]CALCULO_VR!$D:$D,[1]CALCULO_VR!$J:$J) -> 80 | X152: =_xlfn.XLOOKUP(A152,[1]CALCULO_VR!$D:$D,[1]CALCULO_VR!$O:$O) -> -12.010872 | Y152: =_xlfn.XLOOKUP(A152,[1]CALCULO_VR!$D:$D,[1]CALCULO_VR!$P:$P) -> -64.82395
A153: 2583644 | B153: DEBORA CRISTINA SALES | C153: Guajará-Mirim | D153: 45474 | E153: 45474 | F153: 34042.861 | G153: 1 | H153: 1 | J153: 0 | Q153: 118.03643 | R153: 3 | S153: 3 | T153: 187 | U153: 9 | W153: =_xlfn.XLOOKUP(A153,[1]CALCULO_VR!$D:$D,[1]CALCULO_VR!$J:$J) -> 80 | X153: =_xlfn.XLOOKUP(A153,[1]CALCULO_VR!$D:$D,[1]CALCULO_VR!$O:$O) -> -11.786992 | Y153: =_xlfn.XLOOKUP(A153,[1]CALCULO_VR!$D:$D,[1]CALCULO_VR!$P:$P) -> -65.000763
A154: 2583876 | B154: JAIME WAJURU | C154: Guajará-Mirim | D154: 45475 | E154: 45475 | F154: 34042.861 | G154: 1 | H154: 1 | J154: 0 | Q154: 147.80401 | R154: 3 | S154: 3 | T154: 187 | U154: 9 | W154: =_xlfn.XLOOKUP(A154,[1]CALCULO_VR!$D:$D,[1]CALCULO_VR!$J:$J) -> 80 | X154: =_xlfn.XLOOKUP(A154,[1]CALCULO_VR!$D:$D,[1]CALCULO_VR!$O:$O) -> -12.01046 | Y154: =_xlfn.XLOOKUP(A154,[1]CALCULO_VR!$D:$D,[1]CALCULO_VR!$P:$P) -> -64.826555
A155: 2583877 | B155: ADRIANA MACURAP | C155: Guajará-Mirim | D155: 45475 | E155: 45475 | F155: 34042.861 | G155: 1 | H155: 1 | J155: 0 | Q155: 147.78628 | R155: 3 | S155: 3 | T155: 187 | U155: 9 | W155: =_xlfn.XLOOKUP(A155,[1]CALCULO_VR!$D:$D,[1]CALCULO_VR!$J:$J) -> 80 | X155: =_xlfn.XLOOKUP(A155,[1]CALCULO_VR!$D:$D,[1]CALCULO_VR!$O:$O) -> -12.010333 | Y155: =_xlfn.XLOOKUP(A155,[1]CALCULO_VR!$D:$D,[1]CALCULO_VR!$P:$P) -> -64.82667
A156: 2583650 | B156: MEIRELES SILVA KARITIANA | C156: Candeias do Jamari | D156: 45475 | E156: 45475 | F156: 34042.861 | G156: 1 | H156: 1 | J156: 0 | Q156: 56.928289 | R156: 1 | S156: 1 | T156: 450 | U156: 27 | W156: =_xlfn.XLOOKUP(A156,[1]CALCULO_VR!$D:$D,[1]CALCULO_VR!$J:$J) -> 80 | X156: =_xlfn.XLOOKUP(A156,[1]CALCULO_VR!$D:$D,[1]CALCULO_VR!$O:$O) -> -9.291147 | Y156: =_xlfn.XLOOKUP(A156,[1]CALCULO_VR!$D:$D,[1]CALCULO_VR!$P:$P) -> -63.778112
A157: 2583878 | B157: JOAO MEJIAS VALENTE | C157: Guajará-Mirim | D157: 45475 | E157: 45475 | F157: 34042.861 | G157: 1 | H157: 1 | J157: 0 | Q157: 20.650626 | R157: 1 | S157: 1 | T157: 450 | U157: 27 | W157: =_xlfn.XLOOKUP(A157,[1]CALCULO_VR!$D:$D,[1]CALCULO_VR!$J:$J) -> 80 | X157: =_xlfn.XLOOKUP(A157,[1]CALCULO_VR!$D:$D,[1]CALCULO_VR!$O:$O) -> -10.951152 | Y157: =_xlfn.XLOOKUP(A157,[1]CALCULO_VR!$D:$D,[1]CALCULO_VR!$P:$P) -> -65.267568
... A165: 2583678 | B165: SANDRO FERNANDES LEITE | C165: Guajará-Mirim | D165: 45460 | E165: 45460 | F165: 34042.861 | G165: 1 | H165: 1 | J165: 0 | Q165: 59.116606 | R165: 1 | S165: 1 | T165: 450 | U165: 27 | W165: =_xlfn.XLOOKUP(A165,[1]CALCULO_VR!$D:$D,[1]CALCULO_VR!$J:$J) -> 80 | X165: =_xlfn.XLOOKUP(A165,[1]CALCULO_VR!$D:$D,[1]CALCULO_VR!$O:$O) -> -10.676857 | Y165: =_xlfn.XLOOKUP(A165,[1]CALCULO_VR!$D:$D,[1]CALCULO_VR!$P:$P) -> -64.791938
A166: 2583679 | B166: EULIDES BRASIL DA SILVA | C166: Guajará-Mirim | D166: 45460 | E166: 45460 | F166: 34042.861 | G166: 1 | H166: 1 | J166: 0 | Q166: 57.400191 | R166: 1 | S166: 1 | T166: 450 | U166: 27 | V166: Selecionado | W166: =_xlfn.XLOOKUP(A166,[1]CALCULO_VR!$D:$D,[1]CALCULO_VR!$J:$J) -> 80 | X166: =_xlfn.XLOOKUP(A166,[1]CALCULO_VR!$D:$D,[1]CALCULO_VR!$O:$O) -> -10.685668 | Y166: =_xlfn.XLOOKUP(A166,[1]CALCULO_VR!$D:$D,[1]CALCULO_VR!$P:$P) -> -64.806282
A167: 2583936 | B167: POSTO DE SAUDE ALDEIA CRISTO REI | C167: Guajará-Mirim | D167: 45461 | E167: 45461 | F167: 34042.861 | G167: 1 | H167: 1 | J167: 0 | Q167: 134.33919 | R167: 3 | S167: 3 | T167: 187 | U167: 9 | V167: Selecionado | W167: =_xlfn.XLOOKUP(A167,[1]CALCULO_VR!$D:$D,[1]CALCULO_VR!$J:$J) -> 80 | X167: =_xlfn.XLOOKUP(A167,[1]CALCULO_VR!$D:$D,[1]CALCULO_VR!$O:$O) -> -11.121872 | Y167: =_xlfn.XLOOKUP(A167,[1]CALCULO_VR!$D:$D,[1]CALCULO_VR!$P:$P) -> -64.145563
A168: 2583880 | B168: RAIMUNDO DURAES PEREIRA DA SILVA | C168: Guajará-Mirim | D168: 45475 | E168: 45475 | F168: 34042.861 | G168: 1 | H168: 1 | J168: 0 | Q168: 21.172808 | R168: 1 | S168: 1 | T168: 450 | U168: 27 | V168: Selecionado | W168: =_xlfn.XLOOKUP(A168,[1]CALCULO_VR!$D:$D,[1]CALCULO_VR!$J:$J) -> 80 | X168: =_xlfn.XLOOKUP(A168,[1]CALCULO_VR!$D:$D,[1]CALCULO_VR!$O:$O) -> -10.955988 | Y168: =_xlfn.XLOOKUP(A168,[1]CALCULO_VR!$D:$D,[1]CALCULO_VR!$P:$P) -> -65.267307
A169: 2583881 | B169: FRANK WAJURU | C169: Guajará-Mirim | D169: 45476 | E169: 45476 | F169: 34042.861 | G169: 1 | H169: 1 | J169: 0 | Q169: 147.95588 | R169: 3 | S169: 3 | T169: 187 | U169: 9 | W169: =_xlfn.XLOOKUP(A169,[1]CALCULO_VR!$D:$D,[1]CALCULO_VR!$J:$J) -> 80 | X169: =_xlfn.XLOOKUP(A169,[1]CALCULO_VR!$D:$D,[1]CALCULO_VR!$O:$O) -> -12.010627 | Y169: =_xlfn.XLOOKUP(A169,[1]CALCULO_VR!$D:$D,[1]CALCULO_VR!$P:$P) -> -64.823198
A170: 2583687 | B170: EDICLEIA CANDIDO DE MELO | C170: Guajará-Mirim | D170: 45466 | E170: 45466 | F170: 34042.861 | G170: 1 | H170: 1 | J170: 0 | Q170: 66.872131 | R170: 1 | S170: 1 | T170: 450 | U170: 27 | W170: =_xlfn.XLOOKUP(A170,[1]CALCULO_VR!$D:$D,[1]CALCULO_VR!$J:$J) -> 80 | X170: =_xlfn.XLOOKUP(A170,[1]CALCULO_VR!$D:$D,[1]CALCULO_VR!$O:$O) -> -11.186132 | Y170: =_xlfn.XLOOKUP(A170,[1]CALCULO_VR!$D:$D,[1]CALCULO_VR!$P:$P) -> -64.877918
...

Sheet Planilha2
A1: UC | B1: Projeto | C1: Município | D1: SIGFI | E1: Latitude | F1: Longitude
A2: 2595250 | B2: OSMAR MAINTAKA TUPARI | C2: São Francisco do Guaporé | D2: 160 | E2: -12.347225 | F2: -62.796425
A3: 2583920 | B3: ESCOLA ENSINO FUNDAMENTAL VALDEMAR CABIXI | C3: Guajará-Mirim | D3: 80 | E3: -11.15186 | F3: -64.19707
A4: 2583788 | B4: SILVANA KARITIANA | C4: Porto Velho | D4: 80 | E4: -9.192673 | F4: -63.948097
A5: 2583928 | B5: ESCOLA INDIGINA ESTADUAL DE ENSINO | C5: Porto Velho | D5: 80 | E5: -9.192465 | F5: -63.94769
A6: 2583826 | B6: SALOMAO ORO WIN | C6: Guajará-Mirim | D6: 80 | E6: -11.086663 | F6: -64.080385
A7: 2585878 | B7: ANGELINA ORO MON | C7: Nova Mamoré | D7: 80 | E7: -10.368292 | F7: -65.081318
A8: 2583675 | B8: ALDELINNO FIRMINO NEVES | C8: Guajará-Mirim | D8: 80 | E8: -10.680527 | F8: -64.813467
A9: 2583679 | B9: EULIDES BRASIL DA SILVA | C9: Guajará-Mirim | D9: 80 | E9: -10.685668 | F9: -64.806282
A10: 2583936 | B10: POSTO DE SAUDE ALDEIA CRISTO REI | C10: Guajará-Mirim | D10: 80 | E10: -11.121872 | F10: -64.145563
A11: 2583880 | B11: RAIMUNDO DURAES PEREIRA DA SILVA | C11: Guajará-Mirim | D11: 80 | E11: -10.955988 | F11: -65.267307
A12: 2583904 | B12: MARIA DEL CARMEN RUIZ ARAUZ | C12: Guajará-Mirim | D12: 80 | E12: -10.949367 | F12: -65.26786
A13: 2595017 | B13: MIRIAN MACURAP | C13: Guajará-Mirim | D13: 80 | E13: -12.029373 | F13: -64.805922
... A46: 2787454 | B46: ELIENAI ROSALINO DA SILVA FERNANDES | C46: Vilhena | D46: 80 | E46: -12.513032 | F46: -60.269265

Sheet Planilha3
A1: UC | B1: Projeto | C1: Município | D1: SIGFI | E1: Latitude | F1: Longitude
A2: 2583701 | B2: MARIA LILIA OLIVEIRA GONCALVES | C2: Guajará-Mirim | D2: 80 | E2: -11.20843 | F2: -64.80945
A3: 2583802 | B3: RAIMUNDO NONATO KARITIANA | C3: Porto Velho | D3: 80 | E3: -9.191817 | F3: -63.947215
A4: 2583810 | B4: JEAN ORO WARAM | C4: Guajará-Mirim | D4: 80 | E4: -11.087268 | F4: -64.079673
A5: 2583839 | B5: ALEX FRANCISCO DELGADO PIN KARITIANA | C5: Porto Velho | D5: 80 | E5: -9.440863 | F5: -64.197193
A6: 2583862 | B6: TANGAE URU EU WAU WAU DE OLIVEIRA | C6: Porto Velho | D6: 80 | E6: -9.754347 | F6: -64.31926
A7: 2583873 | B7: SERGIO ORO WIN CABIXI | C7: Guajará-Mirim | D7: 80 | E7: -11.15165 | F7: -64.196308
A8: 2583705 | B8: CLEONICE MASSAKA | C8: Guajará-Mirim | D8: 80 | E8: -11.08904 | F8: -65.278228
A9: 2595137 | B9: VALDEIR SEV KALAV GAVIAO | C9: Ji-Paraná | D9: 80 | E9: -10.712018 | F9: -61.599498
A10: 2595287 | B10: ANTONIO BORTONE NETO DIAS | C10: Pimenta Bueno | D10: 80 | E10: -12.243135 | F10: -60.396132
A11: 2595585 | B11: DIVA CINTA LARGA | C11: Espigão D'Oeste | D11: 80 | E11: -11.357113 | F11: -60.556003
A12: 2614648 | B12: VALDIR CHEREMBOMBAL GAVIAO | C12: Ji-Paraná | D12: 80 | E12: -10.434537 | F12: -61.65337
A13: 2629576 | B13: NATANAEL JESUS DO VALE SANTOS | C13: Cujubim | D13: 80 | E13: -8.851893 | F13: -62.35451
... A23: 2787427 | B23: DEIVIDE STEFANI CACULA ARCOVERDE | C23: Vilhena | D23: 80 | E23: -12.525523 | F23: -60.265687

Sheet Amostra 1_4_extrato_erro_5%
A1: UC | B1: Projeto | C1: Município | D1: Data Inicio | E1: Data Fim | F1: Custo(R$) | G1: Cons. | H1: Kit | I1: Regional | J1: Grupo | K1: Poste | L1: Rede AT km | M1: Rede BT km | N1: Medidor | O1: Trafo | P1: Equip. | Q1: VR | R1: Estrato | S1: regionale | T1: NGH | U1: NPH | V1: STATUS | W1: SIGFI | X1: Latitude_UC | Y1: Longitude_UC
A2: 2595147 | B2: POSTO DE SAUDE ALDEIA PALHAL | C2: Vilhena | D2: 45500 | E2: 45500 | F2: 34042.861 | G2: 1 | H2: 1 | J2: 0 | Q2: 144.5618 | R2: 4 | S2: 4 | T2: 163 | U2: 5 | W2: =_xlfn.XLOOKUP(A2,[1]CALCULO_VR!$D:$D,[1]CALCULO_VR!$J:$J) -> 80 | X2: =_xlfn.XLOOKUP(A2,[1]CALCULO_VR!$D:$D,[1]CALCULO_VR!$O:$O) -> -11.479878 | Y2: =_xlfn.XLOOKUP(A2,[1]CALCULO_VR!$D:$D,[1]CALCULO_VR!$P:$P) -> -60.460112
A3: 2595177 | B3: GERSON CINTA LARGA | C3: São Francisco do Guaporé | D3: 45504 | E3: 45504 | F3: 52970.941 | G3: 1 | H3: 1 | J3: 0 | Q3: 70.928033 | R3: 2 | S3: 2 | T3: 251 | U3: 5 | W3: =_xlfn.XLOOKUP(A3,[1]CALCULO_VR!$D:$D,[1]CALCULO_VR!$J:$J) -> 160 | X3: =_xlfn.XLOOKUP(A3,[1]CALCULO_VR!$D:$D,[1]CALCULO_VR!$O:$O) -> -12.408093 | Y3: =_xlfn.XLOOKUP(A3,[1]CALCULO_VR!$D:$D,[1]CALCULO_VR!$P:$P) -> -63.021408
A4: 2595236 | B4: POSTO DE SAUDE ALDEIA CAJUI | C4: São Francisco do Guaporé | D4: 45505 | E4: 45505 | F4: 34042.861 | G4: 1 | H4: 1 | J4: 0 | Q4: 70.937531 | R4: 2 | S4: 2 | T4: 251 | U4: 5 | W4: =_xlfn.XLOOKUP(A4,[1]CALCULO_VR!$D:$D,[1]CALCULO_VR!$J:$J) -> 80 | X4: =_xlfn.XLOOKUP(A4,[1]CALCULO_VR!$D:$D,[1]CALCULO_VR!$O:$O) -> -12.407253 | Y4: =_xlfn.XLOOKUP(A4,[1]CALCULO_VR!$D:$D,[1]CALCULO_VR!$P:$P) -> -63.020755
A5: 2595237 | B5: EIEEFM KON KOATT TUPARI | C5: São Francisco do Guaporé | D5: 45505 | E5: 45505 | F5: 34042.861 | G5: 1 | H5: 1 | J5: 0 | Q5: 70.910302 | R5: 2 | S5: 2 | T5: 251 | U5: 5 | W5: =_xlfn.XLOOKUP(A5,[1]CALCULO_VR!$D:$D,[1]CALCULO_VR!$J:$J) -> 80 | X5: =_xlfn.XLOOKUP(A5,[1]CALCULO_VR!$D:$D,[1]CALCULO_VR!$O:$O) -> -12.40728 | Y5: =_xlfn.XLOOKUP(A5,[1]CALCULO_VR!$D:$D,[1]CALCULO_VR!$P:$P) -> -63.02107
A6: 2595249 | B6: ROSEANE TENHARIN | C6: São Francisco do Guaporé | D6: 45500 | E6: 45500 | F6: 52970.941 | G6: 1 | H6: 1 | J6: 0 | Q6: 90.038796 | R6: 3 | S6: 3 | T6: 223 | U6: 6 | W6: =_xlfn.XLOOKUP(A6,[1]CALCULO_VR!$D:$D,[1]CALCULO_VR!$J:$J) -> 160 | X6: =_xlfn.XLOOKUP(A6,[1]CALCULO_VR!$D:$D,[1]CALCULO_VR!$O:$O) -> -12.34808 | Y6: =_xlfn.XLOOKUP(A6,[1]CALCULO_VR!$D:$D,[1]CALCULO_VR!$P:$P) -> -62.795132
A7: 2595250 | B7: OSMAR MAINTAKA TUPARI | C7: São Francisco do Guaporé | D7: 45500 | E7: 45500 | F7: 52970.941 | G7: 1 | H7: 1 | J7: 0 | Q7: 89.873976 | R7: 3 | S7: 3 | T7: 223 | U7: 6 | W7: =_xlfn.XLOOKUP(A7,[1]CALCULO_VR!$D:$D,[1]CALCULO_VR!$J:$J) -> 160 | X7: =_xlfn.XLOOKUP(A7,[1]CALCULO_VR!$D:$D,[1]CALCULO_VR!$O:$O) -> -12.347225 | Y7: =_xlfn.XLOOKUP(A7,[1]CALCULO_VR!$D:$D,[1]CALCULO_VR!$P:$P) -> -62.796425
A8: 2595269 | B8: EIEEFM KON KOATT TUPARI | C8: São Francisco do Guaporé | D8: 45506 | E8: 45506 | F8: 34042.861 | G8: 1 | H8: 1 | J8: 0 | Q8: 70.974094 | R8: 2 | S8: 2 | T8: 251 | U8: 5 | W8: =_xlfn.XLOOKUP(A8,[1]CALCULO_VR!$D:$D,[1]CALCULO_VR!$J:$J) -> 80 | X8: =_xlfn.XLOOKUP(A8,[1]CALCULO_VR!$D:$D,[1]CALCULO_VR!$O:$O) -> -12.41203 | Y8: =_xlfn.XLOOKUP(A8,[1]CALCULO_VR!$D:$D,[1]CALCULO_VR!$P:$P) -> -63.023502
A9: 2595272 | B9: WALDIR FIRMINO VALE | C9: São Francisco do Guaporé | D9: 45502 | E9: 45502 | F9: 52970.941 | G9: 1 | H9: 1 | J9: 0 | Q9: 89.869751 | R9: 3 | S9: 3 | T9: 223 | U9: 6 | W9: =_xlfn.XLOOKUP(A9,[1]CALCULO_VR!$D:$D,[1]CALCULO_VR!$J:$J) -> 160 | X9: =_xlfn.XLOOKUP(A9,[1]CALCULO_VR!$D:$D,[1]CALCULO_VR!$O:$O) -> -12.347462 | Y9: =_xlfn.XLOOKUP(A9,[1]CALCULO_VR!$D:$D,[1]CALCULO_VR!$P:$P) -> -62.796557
A10: 2583661 | B10: DIVINO GOMES LIMA | C10: Guajará-Mirim | D10: 45459 | E10: 45459 | F10: 34042.861 | G10: 1 | H10: 1 | J10: 0 | Q10: 54.60863 | R10: 2 | S10: 2 | T10: 251 | U10: 5 | W10: =_xlfn.XLOOKUP(A10,[1]CALCULO_VR!$D:$D,[1]CALCULO_VR!$J:$J) -> 80 | X10: =_xlfn.XLOOKUP(A10,[1]CALCULO_VR!$D:$D,[1]CALCULO_VR!$O:$O) -> -10.681757 | Y10: =_xlfn.XLOOKUP(A10,[1]CALCULO_VR!$D:$D,[1]CALCULO_VR!$P:$P) -> -64.832982
A11: 2583662 | B11: JOSE PEREIRA ALVES | C11: Guajará-Mirim | D11: 45458 | E11: 45458 | F11: 34042.861 | G11: 1 | H11: 1 | J11: 0 | Q11: 56.302057 | R11: 2 | S11: 2 | T11: 251 | U11: 5 | W11: =_xlfn.XLOOKUP(A11,[1]CALCULO_VR!$D:$D,[1]CALCULO_VR!$J:$J) -> 80 | X11: =_xlfn.XLOOKUP(A11,[1]CALCULO_VR!$D:$D,[1]CALCULO_VR!$O:$O) -> -10.673628 | Y11: =_xlfn.XLOOKUP(A11,[1]CALCULO_VR!$D:$D,[1]CALCULO_VR!$P:$P) -> -64.818818
A12: 2583663 | B12: ELIETE BIRA MACIEL | C12: Guajará-Mirim | D12: 45459 | E12: 45459 | F12: 34042.861 | G12: 1 | H12: 1 | J12: 0 | Q12: 56.649232 | R12: 2 | S12: 2 | T12: 251 | U12: 5 | W12: =_xlfn.XLOOKUP(A12,[1]CALCULO_VR!$D:$D,[1]CALCULO_VR!$J:$J) -> 80 | X12: =_xlfn.XLOOKUP(A12,[1]CALCULO_VR!$D:$D,[1]CALCULO_VR!$O:$O) -> -10.669567 | Y12: =_xlfn.XLOOKUP(A12,[1]CALCULO_VR!$D:$D,[1]CALCULO_VR!$P:$P) -> -64.816427
A13: 2583664 | B13: JOSE ELEUTERIO FILHO | C13: Guajará-Mirim | D13: 45459 | E13: 45459 | F13: 34042.861 | G13: 1 | H13: 1 | J13: 0 | Q13: 57.074959 | R13: 2 | S13: 2 | T13: 251 | U13: 5 | W13: =_xlfn.XLOOKUP(A13,[1]CALCULO_VR!$D:$D,[1]CALCULO_VR!$J:$J) -> 80 | X13: =_xlfn.XLOOKUP(A13,[1]CALCULO_VR!$D:$D,[1]CALCULO_VR!$O:$O) -> -10.674992 | Y13: =_xlfn.XLOOKUP(A13,[1]CALCULO_VR!$D:$D,[1]CALCULO_VR!$P:$P) -> -64.811327
... A54: 2583787 | B54: FRANCIELE PAMOTO KARITIANA | C54: Porto Velho | D54: 45468 | E54: 45468 | F54: 34042.861 | G54: 1 | H54: 1 | J54: 0 | Q54: 48.789481 | R54: 2 | S54: 2 | T54: 251 | U54: 5 | W54: =_xlfn.XLOOKUP(A54,[1]CALCULO_VR!$D:$D,[1]CALCULO_VR!$J:$J) -> 80 | X54: =_xlfn.XLOOKUP(A54,[1]CALCULO_VR!$D:$D,[1]CALCULO_VR!$O:$O) -> -9.192407 | Y54: =_xlfn.XLOOKUP(A54,[1]CALCULO_VR!$D:$D,[1]CALCULO_VR!$P:$P) -> -63.947577
A55: 2583701 | B55: MARIA LILIA OLIVEIRA GONCALVES | C55: Guajará-Mirim | D55: 45467 | E55: 45467 | F55: 34042.861 | G55: 1 | H55: 1 | J55: 0 | Q55: 74.086101 | R55: 2 | S55: 2 | T55: 251 | U55: 5 | V55: Selecionado | W55: =_xlfn.XLOOKUP(A55,[1]CALCULO_VR!$D:$D,[1]CALCULO_VR!$J:$J) -> 80 | X55: =_xlfn.XLOOKUP(A55,[1]CALCULO_VR!$D:$D,[1]CALCULO_VR!$O:$O) -> -11.20843 | Y55: =_xlfn.XLOOKUP(A55,[1]CALCULO_VR!$D:$D,[1]CALCULO_VR!$P:$P) -> -64.80945
A56: 2583921 | B56: POSTO DE SAUDE ALDEIA SAO LUIZ | C56: Guajará-Mirim | D56: 45460 | E56: 45460 | F56: 34042.861 | G56: 1 | H56: 1 | J56: 0 | Q56: 140.19241 | R56: 4 | S56: 4 | T56: 163 | U56: 5 | W56: =_xlfn.XLOOKUP(A56,[1]CALCULO_VR!$D:$D,[1]CALCULO_VR!$J:$J) -> 80 | X56: =_xlfn.XLOOKUP(A56,[1]CALCULO_VR!$D:$D,[1]CALCULO_VR!$O:$O) -> -11.085762 | Y56: =_xlfn.XLOOKUP(A56,[1]CALCULO_VR!$D:$D,[1]CALCULO_VR!$P:$P) -> -64.079783
A57: 2583685 | B57: WALDEMIR LOPES DE AMORIM | C57: Guajará-Mirim | D57: 45464 | E57: 45464 | F57: 34042.861 | G57: 1 | H57: 1 | J57: 0 | Q57: 65.495643 | R57: 2 | S57: 2 | T57: 251 | U57: 5 | W57: =_xlfn.XLOOKUP(A57,[1]CALCULO_VR!$D:$D,[1]CALCULO_VR!$J:$J) -> 80 | X57: =_xlfn.XLOOKUP(A57,[1]CALCULO_VR!$D:$D,[1]CALCULO_VR!$O:$O) -> -11.200607 | Y57: =_xlfn.XLOOKUP(A57,[1]CALCULO_VR!$D:$D,[1]CALCULO_VR!$P:$P) -> -64.910355
A58: 2583686 | B58: JOSE MARIA DE SOUZA RUFINO | C58: Guajará-Mirim | D58: 45464 | E58: 45464 | F58: 34042.861 | G58: 1 | H58: 1 | J58: 0 | Q58: 65.745664 | R58: 2 | S58: 2 | T58: 251 | U58: 5 | W58: =_xlfn.XLOOKUP(A58,[1]CALCULO_VR!$D:$D,[1]CALCULO_VR!$J:$J) -> 80 | X58: =_xlfn.XLOOKUP(A58,[1]CALCULO_VR!$D:$D,[1]CALCULO_VR!$O:$O) -> -11.198337 | Y58: =_xlfn.XLOOKUP(A58,[1]CALCULO_VR!$D:$D,[1]CALCULO_VR!$P:$P) -> -64.904643
A59: 2583922 | B59: ESCOLA JOAO FARIAS DE BARROS | C59: Guajará-Mirim | D59: 45460 | E59: 45460 | F59: 34042.861 | G59: 1 | H59: 1 | J59: 0 | Q59: 140.12685 | R59: 4 | S59: 4 | T59: 163 | U59: 5 | W59: =_xlfn.XLOOKUP(A59,[1]CALCULO_VR!$D:$D,[1]CALCULO_VR!$J:$J) -> 80 | X59: =_xlfn.XLOOKUP(A59,[1]CALCULO_VR!$D:$D,[1]CALCULO_VR!$O:$O) -> -11.087058 | Y59: =_xlfn.XLOOKUP(A59,[1]CALCULO_VR!$D:$D,[1]CALCULO_VR!$P:$P) -> -64.080738
A60: 2583788 | B60: SILVANA KARITIANA | C60: Porto Velho | D60: 45468 | E60: 45468 | F60: 34042.861 | G60: 1 | H60: 1 | J60: 0 | Q60: 48.832983 | R60: 2 | S60: 2 | T60: 251 | U60: 5 | W60: =_xlfn.XLOOKUP(A60,[1]CALCULO_VR!$D:$D,[1]CALCULO_VR!$J:$J) -> 80 | X60: =_xlfn.XLOOKUP(A60,[1]CALCULO_VR!$D:$D,[1]CALCULO_VR!$O:$O) -> -9.192673 | Y60: =_xlfn.XLOOKUP(A60,[1]CALCULO_VR!$D:$D,[1]CALCULO_VR!$P:$P) -> -63.948097
A61: 2583789 | B61: GEICILENE ORO JOWIN | C61: Guajará-Mirim | D61: 45460 | E61: 45460 | F61: 34042.861 | G61: 1 | H61: 1 | J61: 0 | Q61: 140.19906 | R61: 4 | S61: 4 | T61: 163 | U61: 5 | W61: =_xlfn.XLOOKUP(A61,[1]CALCULO_VR!$D:$D,[1]CALCULO_VR!$J:$J) -> 80 | X61: =_xlfn.XLOOKUP(A61,[1]CALCULO_VR!$D:$D,[1]CALCULO_VR!$O:$O) -> -11.087127 | Y61: =_xlfn.XLOOKUP(A61,[1]CALCULO_VR!$D:$D,[1]CALCULO_VR!$P:$P) -> -64.080073
A62: 2583790 | B62: ROSENDA FERREIRA INUMA | C62: Guajará-Mirim | D62: 45469 | E62: 45469 | F62: 34042.861 | G62: 1 | H62: 1 | J62: 0 | Q62: 94.114195 | R62: 3 | S62: 3 | T62: 223 | U62: 6 | W62: =_xlfn.XLOOKUP(A62,[1]CALCULO_VR!$D:$D,[1]CALCULO_VR!$J:$J) -> 80 | X62: =_xlfn.XLOOKUP(A62,[1]CALCULO_VR!$D:$D,[1]CALCULO_VR!$O:$O) -> -11.380303 | Y62: =_xlfn.XLOOKUP(A62,[1]CALCULO_VR!$D:$D,[1]CALCULO_VR!$P:$P) -> -64.72229
A63: 2583791 | B63: NEIDE MORAIS KARITIANA LOPES | C63: Porto Velho | D63: 45469 | E63: 45469 | F63: 34042.861 | G63: 1 | H63: 1 | J63: 0 | Q63: 66.468637 | R63: 2 | S63: 2 | T63: 251 | U63: 5 | W63: =_xlfn.XLOOKUP(A63,[1]CALCULO_VR!$D:$D,[1]CALCULO_VR!$J:$J) -> 80 | X63: =_xlfn.XLOOKUP(A63,[1]CALCULO_VR!$D:$D,[1]CALCULO_VR!$O:$O) -> -9.320778 | Y63: =_xlfn.XLOOKUP(A63,[1]CALCULO_VR!$D:$D,[1]CALCULO_VR!$P:$P) -> -64.064005
A64: 2583792 | B64: JOAO FERREIRA LOPES | C64: Guajará-Mirim | D64: 45468 | E64: 45468 | F64: 34042.861 | G64: 1 | H64: 1 | J64: 0 | Q64: 86.782843 | R64: 3 | S64: 3 | T64: 223 | U64: 6 | W64: =_xlfn.XLOOKUP(A64,[1]CALCULO_VR!$D:$D,[1]CALCULO_VR!$J:$J) -> 80 | X64: =_xlfn.XLOOKUP(A64,[1]CALCULO_VR!$D:$D,[1]CALCULO_VR!$O:$O) -> -11.353395 | Y64: =_xlfn.XLOOKUP(A64,[1]CALCULO_VR!$D:$D,[1]CALCULO_VR!$P:$P) -> -64.791288
A65: 2583923 | B65: ESCOLA INDIGENA NYJNYJI | C65: Porto Velho | D65: 45469 | E65: 45469 | F65: 34042.861 | G65: 1 | H65: 1 | J65: 0 | Q65: 66.366 | R65: 2 | S65: 2 | T65: 251 | U65: 5 | W65: =_xlfn.XLOOKUP(A65,[1]CALCULO_VR!$D:$D,[1]CALCULO_VR!$J:$J) -> 80 | X65: =_xlfn.XLOOKUP(A65,[1]CALCULO_VR!$D:$D,[1]CALCULO_VR!$O:$O) -> -9.32021 | Y65: =_xlfn.XLOOKUP(A65,[1]CALCULO_VR!$D:$D,[1]CALCULO_VR!$P:$P) -> -64.062953
A66: 2583681 | B66: MIZAEL ORO NAO | C66: Guajará-Mirim | D66: 45467 | E66: 45467 | F66: 34042.861 | G66: 1 | H66: 1 | J66: 0 | Q66: 63.415301 | R66: 2 | S66: 2 | T66: 251 | U66: 5 | W66: =_xlfn.XLOOKUP(A66,[1]CALCULO_VR!$D:$D,[1]CALCULO_VR!$J:$J) -> 80 | X66: =_xlfn.XLOOKUP(A66,[1]CALCULO_VR!$D:$D,[1]CALCULO_VR!$O:$O) -> -11.219857 | Y66: =_xlfn.XLOOKUP(A66,[1]CALCULO_VR!$D:$D,[1]CALCULO_VR!$P:$P) -> -64.961832
A67: 2583793 | B67: CELIANE DA SILVA KARITIANA | C67: Porto Velho | D67: 45467 | E67: 45467 | F67: 34042.861 | G67: 1 | H67: 1 | J67: 0 | Q67: 48.79447 | R67: 2 | S67: 2 | T67: 251 | U67: 5 | W67: =_xlfn.XLOOKUP(A67,[1]CALCULO_VR!$D:$D,[1]CALCULO_VR!$J:$J) -> 80 | X67: =_xlfn.XLOOKUP(A67,[1]CALCULO_VR!$D:$D,[1]CALCULO_VR!$O:$O) -> -9.192733 | Y67: =_xlfn.XLOOKUP(A67,[1]CALCULO_VR!$D:$D,[1]CALCULO_VR!$P:$P) -> -63.946527
... A74: 2583801 | B74: GEANE MARIA GARCIA KARITIANA | C74: Porto Velho | D74: 45469 | E74: 45469 | F74: 34042.861 | G74: 1 | H74: 1 | J74: 0 | Q74: 66.471653 | R74: 2 | S74: 2 | T74: 251 | U74: 5 | W74: =_xlfn.XLOOKUP(A74,[1]CALCULO_VR!$D:$D,[1]CALCULO_VR!$J:$J) -> 80 | X74: =_xlfn.XLOOKUP(A74,[1]CALCULO_VR!$D:$D,[1]CALCULO_VR!$O:$O) -> -9.320793 | Y74: =_xlfn.XLOOKUP(A74,[1]CALCULO_VR!$D:$D,[1]CALCULO_VR!$P:$P) -> -64.06404
A75: 2583802 | B75: RAIMUNDO NONATO KARITIANA | C75: Porto Velho | D75: 45467 | E75: 45467 | F75: 34042.861 | G75: 1 | H75: 1 | J75: 0 | Q75: 48.715771 | R75: 2 | S75: 2 | T75: 251 | U75: 5 | V75: Selecionado | W75: =_xlfn.XLOOKUP(A75,[1]CALCULO_VR!$D:$D,[1]CALCULO_VR!$J:$J) -> 80 | X75: =_xlfn.XLOOKUP(A75,[1]CALCULO_VR!$D:$D,[1]CALCULO_VR!$O:$O) -> -9.191817 | Y75: =_xlfn.XLOOKUP(A75,[1]CALCULO_VR!$D:$D,[1]CALCULO_VR!$P:$P) -> -63.947215
A76: 2583682 | B76: CLEICIELE ORO NAO | C76: Guajará-Mirim | D76: 45467 | E76: 45467 | F76: 34042.861 | G76: 1 | H76: 1 | J76: 0 | Q76: 63.907334 | R76: 2 | S76: 2 | T76: 251 | U76: 5 | W76: =_xlfn.XLOOKUP(A76,[1]CALCULO_VR!$D:$D,[1]CALCULO_VR!$J:$J) -> 80 | X76: =_xlfn.XLOOKUP(A76,[1]CALCULO_VR!$D:$D,[1]CALCULO_VR!$O:$O) -> -11.222135 | Y76: =_xlfn.XLOOKUP(A76,[1]CALCULO_VR!$D:$D,[1]CALCULO_VR!$P:$P) -> -64.957515
A77: 2583804 | B77: FABIO SOARES LIMA | C77: Guajará-Mirim | D77: 45459 | E77: 45459 | F77: 34042.861 | G77: 1 | H77: 1 | J77: 0 | Q77: 140.16655 | R77: 4 | S77: 4 | T77: 163 | U77: 5 | W77: =_xlfn.XLOOKUP(A77,[1]CALCULO_VR!$D:$D,[1]CALCULO_VR!$J:$J) -> 80 | X77: =_xlfn.XLOOKUP(A77,[1]CALCULO_VR!$D:$D,[1]CALCULO_VR!$O:$O) -> -11.086225 | Y77: =_xlfn.XLOOKUP(A77,[1]CALCULO_VR!$D:$D,[1]CALCULO_VR!$P:$P) -> -64.080147
A78: 2583805 | B78: JOABE ORO WIN | C78: Guajará-Mirim | D78: 45465 | E78: 45465 | F78: 34042.861 | G78: 1 | H78: 1 | J78: 0 | Q78: 140.30324 | R78: 4 | S78: 4 | T78: 163 | U78: 5 | W78: =_xlfn.XLOOKUP(A78,[1]CALCULO_VR!$D:$D,[1]CALCULO_VR!$J:$J) -> 80 | X78: =_xlfn.XLOOKUP(A78,[1]CALCULO_VR!$D:$D,[1]CALCULO_VR!$O:$O) -> -11.085935 | Y78: =_xlfn.XLOOKUP(A78,[1]CALCULO_VR!$D:$D,[1]CALCULO_VR!$P:$P) -> -64.07878
A79: 2583807 | B79: JOSEMAR JACOME LOPES | C79: Guajará-Mirim | D79: 45468 | E79: 45468 | F79: 34042.861 | G79: 1 | H79: 1 | J79: 0 | Q79: 86.804844 | R79: 3 | S79: 3 | T79: 223 | U79: 6 | W79: =_xlfn.XLOOKUP(A79,[1]CALCULO_VR!$D:$D,[1]CALCULO_VR!$J:$J) -> 80 | X79: =_xlfn.XLOOKUP(A79,[1]CALCULO_VR!$D:$D,[1]CALCULO_VR!$O:$O) -> -11.353457 | Y79: =_xlfn.XLOOKUP(A79,[1]CALCULO_VR!$D:$D,[1]CALCULO_VR!$P:$P) -> -64.791057
A80: 2583808 | B80: DANIEL NONATO KARITIANA | C80: Porto Velho | D80: 45468 | E80: 45468 | F80: 34042.861 | G80: 1 | H80: 1 | J80: 0 | Q80: 48.735626 | R80: 2 | S80: 2 | T80: 251 | U80: 5 | W80: =_xlfn.XLOOKUP(A80,[1]CALCULO_VR!$D:$D,[1]CALCULO_VR!$J:$J) -> 80 | X80: =_xlfn.XLOOKUP(A80,[1]CALCULO_VR!$D:$D,[1]CALCULO_VR!$O:$O) -> -9.191895 | Y80: =_xlfn.XLOOKUP(A80,[1]CALCULO_VR!$D:$D,[1]CALCULO_VR!$P:$P) -> -63.947615
A81: 2583809 | B81: MARCIO KARINTIANA | C81: Porto Velho | D81: 45469 | E81: 45469 | F81: 34042.861 | G81: 1 | H81: 1 | J81: 0 | Q81: 66.470852 | R81: 2 | S81: 2 | T81: 251 | U81: 5 | W81: =_xlfn.XLOOKUP(A81,[1]CALCULO_VR!$D:$D,[1]CALCULO_VR!$J:$J) -> 80 | X81: =_xlfn.XLOOKUP(A81,[1]CALCULO_VR!$D:$D,[1]CALCULO_VR!$O:$O) -> -9.320473 | Y81: =_xlfn.XLOOKUP(A81,[1]CALCULO_VR!$D:$D,[1]CALCULO_VR!$P:$P) -> -64.064798
A82: 2583680 | B82: REGIANE ORO EO | C82: Guajará-Mirim | D82: 45469 | E82: 45469 | F82: 34042.861 | G82: 1 | H82: 1 | J82: 0 | Q82: 78.373186 | R82: 3 | S82: 3 | T82: 223 | U82: 6 | W82: =_xlfn.XLOOKUP(A82,[1]CALCULO_VR!$D:$D,[1]CALCULO_VR!$J:$J) -> 80 | X82: =_xlfn.XLOOKUP(A82,[1]CALCULO_VR!$D:$D,[1]CALCULO_VR!$O:$O) -> -11.187977 | Y82: =_xlfn.XLOOKUP(A82,[1]CALCULO_VR!$D:$D,[1]CALCULO_VR!$P:$P) -> -64.742955
A83: 2583810 | B83: JEAN ORO WARAM | C83: Guajará-Mirim | D83: 45460 | E83: 45460 | F83: 34042.861 | G83: 1 | H83: 1 | J83: 0 | Q83: 140.24523 | R83: 4 | S83: 4 | T83: 163 | U83: 5 | V83: Selecionado | W83: =_xlfn.XLOOKUP(A83,[1]CALCULO_VR!$D:$D,[1]CALCULO_VR!$J:$J) -> 80 | X83: =_xlfn.XLOOKUP(A83,[1]CALCULO_VR!$D:$D,[1]CALCULO_VR!$O:$O) -> -11.087268 | Y83: =_xlfn.XLOOKUP(A83,[1]CALCULO_VR!$D:$D,[1]CALCULO_VR!$P:$P) -> -64.079673
A84: 2583926 | B84: IGREJA PENTECOSTAL MISTERIO MOVER DO | C84: Porto Velho | D84: 45469 | E84: 45469 | F84: 34042.861 | G84: 1 | H84: 1 | J84: 0 | Q84: 66.470358 | R84: 2 | S84: 2 | T84: 251 | U84: 5 | W84: =_xlfn.XLOOKUP(A84,[1]CALCULO_VR!$D:$D,[1]CALCULO_VR!$J:$J) -> 80 | X84: =_xlfn.XLOOKUP(A84,[1]CALCULO_VR!$D:$D,[1]CALCULO_VR!$O:$O) -> -9.320872 | Y84: =_xlfn.XLOOKUP(A84,[1]CALCULO_VR!$D:$D,[1]CALCULO_VR!$P:$P) -> -64.063817
A85: 2585871 | B85: KATIA ORO MON | C85: Nova Mamoré | D85: 45464 | E85: 45464 | F85: 34042.861 | G85: 1 | H85: 1 | J85: 0 | Q85: 26.543438 | R85: 1 | S85: 1 | T85: 225 | U85: 6 | W85: =_xlfn.XLOOKUP(A85,[1]CALCULO_VR!$D:$D,[1]CALCULO_VR!$J:$J) -> 80 | X85: =_xlfn.XLOOKUP(A85,[1]CALCULO_VR!$D:$D,[1]CALCULO_VR!$O:$O) -> -10.326277 | Y85: =_xlfn.XLOOKUP(A85,[1]CALCULO_VR!$D:$D,[1]CALCULO_VR!$P:$P) -> -65.102573
A86: 2583811 | B86: ROBERTO ORO WIN | C86: Guajará-Mirim | D86: 45460 | E86: 45460 | F86: 34042.861 | G86: 1 | H86: 1 | J86: 0 | Q86: 139.74196 | R86: 4 | S86: 4 | T86: 163 | U86: 5 | W86: =_xlfn.XLOOKUP(A86,[1]CALCULO_VR!$D:$D,[1]CALCULO_VR!$J:$J) -> 80 | X86: =_xlfn.XLOOKUP(A86,[1]CALCULO_VR!$D:$D,[1]CALCULO_VR!$O:$O) -> -11.093202 | Y86: =_xlfn.XLOOKUP(A86,[1]CALCULO_VR!$D:$D,[1]CALCULO_VR!$P:$P) -> -64.085992
A87: 2583812 | B87: VITOR GARCIA POROGNGA KARITIANA | C87: Porto Velho | D87: 45469 | E87: 45469 | F87: 34042.861 | G87: 1 | H87: 1 | J87: 0 | Q87: 66.490199 | R87: 2 | S87: 2 | T87: 251 | U87: 5 | W87: =_xlfn.XLOOKUP(A87,[1]CALCULO_VR!$D:$D,[1]CALCULO_VR!$J:$J) -> 80 | X87: =_xlfn.XLOOKUP(A87,[1]CALCULO_VR!$D:$D,[1]CALCULO_VR!$O:$O) -> -9.321055 | Y87: =_xlfn.XLOOKUP(A87,[1]CALCULO_VR!$D:$D,[1]CALCULO_VR!$P:$P) -> -64.063842
A88: 2583690 | B88: JOAQUIM MAMEDE CARNEIRO | C88: Guajará-Mirim | D88: 45468 | E88: 45468 | F88: 34042.861 | G88: 1 | H88: 1 | J88: 0 | Q88: 39.829242 | R88: 1 | S88: 1 | T88: 225 | U88: 6 | W88: =_xlfn.XLOOKUP(A88,[1]CALCULO_VR!$D:$D,[1]CALCULO_VR!$J:$J) -> 80 | X88: =_xlfn.XLOOKUP(A88,[1]CALCULO_VR!$D:$D,[1]CALCULO_VR!$O:$O) -> -11.080777 | Y88: =_xlfn.XLOOKUP(A88,[1]CALCULO_VR!$D:$D,[1]CALCULO_VR!$P:$P) -> -65.135828
A89: 2583813 | B89: ADILIO ORO WIN | C89: Guajará-Mirim | D89: 45460 | E89: 45460 | F89: 34042.861 | G89: 1 | H89: 1 | J89: 0 | Q89: 140.25107 | R89: 4 | S89: 4 | T89: 163 | U89: 5 | W89: =_xlfn.XLOOKUP(A89,[1]CALCULO_VR!$D:$D,[1]CALCULO_VR!$J:$J) -> 80 | X89: =_xlfn.XLOOKUP(A89,[1]CALCULO_VR!$D:$D,[1]CALCULO_VR!$O:$O) -> -11.087207 | Y89: =_xlfn.XLOOKUP(A89,[1]CALCULO_VR!$D:$D,[1]CALCULO_VR!$P:$P) -> -64.079602
A90: 2583814 | B90: EDILENE CANOE | C90: Guajará-Mirim | D90: 45465 | E90: 45465 | F90: 34042.861 | G90: 1 | H90: 1 | J90: 0 | Q90: 140.27414 | R90: 4 | S90: 4 | T90: 163 | U90: 5 | W90: =_xlfn.XLOOKUP(A90,[1]CALCULO_VR!$D:$D,[1]CALCULO_VR!$J:$J) -> 80 | X90: =_xlfn.XLOOKUP(A90,[1]CALCULO_VR!$D:$D,[1]CALCULO_VR!$O:$O) -> -11.085838 | Y90: =_xlfn.XLOOKUP(A90,[1]CALCULO_VR!$D:$D,[1]CALCULO_VR!$P:$P) -> -64.07903
A91: 2583691 | B91: FRANCISCO CHAGAS DE LIMA | C91: Guajará-Mirim | D91: 45468 | E91: 45468 | F91: 34042.861 | G91: 1 | H91: 1 | J91: 0 | Q91: 42.491227 | R91: 1 | S91: 1 | T91: 225 | U91: 6 | W91: =_xlfn.XLOOKUP(A91,[1]CALCULO_VR!$D:$D,[1]CALCULO_VR!$J:$J) -> 80 | X91: =_xlfn.XLOOKUP(A91,[1]CALCULO_VR!$D:$D,[1]CALCULO_VR!$O:$O) -> -11.086615 | Y91: =_xlfn.XLOOKUP(A91,[1]CALCULO_VR!$D:$D,[1]CALCULO_VR!$P:$P) -> -65.100293
A92: 2583815 | B92: EDIELSON NONATO KARITIANA | C92: Porto Velho | D92: 45467 | E92: 45467 | F92: 34042.861 | G92: 1 | H92: 1 | J92: 0 | Q92: 48.744503 | R92: 2 | S92: 2 | T92: 251 | U92: 5 | W92: =_xlfn.XLOOKUP(A92,[1]CALCULO_VR!$D:$D,[1]CALCULO_VR!$J:$J) -> 80 | X92: =_xlfn.XLOOKUP(A92,[1]CALCULO_VR!$D:$D,[1]CALCULO_VR!$O:$O) -> -9.192078 | Y92: =_xlfn.XLOOKUP(A92,[1]CALCULO_VR!$D:$D,[1]CALCULO_VR!$P:$P) -> -63.94724
A93: 2583816 | B93: AILTON JOSE ORO WIN | C93: Guajará-Mirim | D93: 45464 | E93: 45464 | F93: 34042.861 | G93: 1 | H93: 1 | J93: 0 | Q93: 140.41415 | R93: 4 | S93: 4 | T93: 163 | U93: 5 | W93: =_xlfn.XLOOKUP(A93,[1]CALCULO_VR!$D:$D,[1]CALCULO_VR!$J:$J) -> 80 | X93: =_xlfn.XLOOKUP(A93,[1]CALCULO_VR!$D:$D,[1]CALCULO_VR!$O:$O) -> -11.080035 | Y93: =_xlfn.XLOOKUP(A93,[1]CALCULO_VR!$D:$D,[1]CALCULO_VR!$P:$P) -> -64.076227
A94: 2583817 | B94: NARON ORO WIN | C94: Guajará-Mirim | D94: 45464 | E94: 45464 | F94: 34042.861 | G94: 1 | H94: 1 | J94: 0 | Q94: 140.2681 | R94: 4 | S94: 4 | T94: 163 | U94: 5 | W94: =_xlfn.XLOOKUP(A94,[1]CALCULO_VR!$D:$D,[1]CALCULO_VR!$J:$J) -> 80 | X94: =_xlfn.XLOOKUP(A94,[1]CALCULO_VR!$D:$D,[1]CALCULO_VR!$O:$O) -> -11.0865 | Y94: =_xlfn.XLOOKUP(A94,[1]CALCULO_VR!$D:$D,[1]CALCULO_VR!$P:$P) -> -64.079258
A95: 2583818 | B95: LUCIANE KARITIANA | C95: Porto Velho | D95: 45467 | E95: 45467 | F95: 34042.861 | G95: 1 | H95: 1 | J95: 0 | Q95: 48.784004 | R95: 2 | S95: 2 | T95: 251 | U95: 5 | W95: =_xlfn.XLOOKUP(A95,[1]CALCULO_VR!$D:$D,[1]CALCULO_VR!$J:$J) -> 80 | X95: =_xlfn.XLOOKUP(A95,[1]CALCULO_VR!$D:$D,[1]CALCULO_VR!$O:$O) -> -9.192458 | Y95: =_xlfn.XLOOKUP(A95,[1]CALCULO_VR!$D:$D,[1]CALCULO_VR!$P:$P) -> -63.947195
... A123: 2583838 | B123: EMERSON POOA KARITIANA | C123: Porto Velho | D123: 45473 | E123: 45473 | F123: 34042.861 | G123: 1 | H123: 1 | J123: 0 | Q123: 84.804683 | R123: 3 | S123: 3 | T123: 223 | U123: 6 | W123: =_xlfn.XLOOKUP(A123,[1]CALCULO_VR!$D:$D,[1]CALCULO_VR!$J:$J) -> 80 | X123: =_xlfn.XLOOKUP(A123,[1]CALCULO_VR!$D:$D,[1]CALCULO_VR!$O:$O) -> -9.440785 | Y123: =_xlfn.XLOOKUP(A123,[1]CALCULO_VR!$D:$D,[1]CALCULO_VR!$P:$P) -> -64.196913
A124: 2583839 | B124: ALEX FRANCISCO DELGADO PIN KARITIANA | C124: Porto Velho | D124: 45473 | E124: 45473 | F124: 34042.861 | G124: 1 | H124: 1 | J124: 0 | Q124: 84.82687 | R124: 3 | S124: 3 | T124: 223 | U124: 6 | V124: Selecionado | W124: =_xlfn.XLOOKUP(A124,[1]CALCULO_VR!$D:$D,[1]CALCULO_VR!$J:$J) -> 80 | X124: =_xlfn.XLOOKUP(A124,[1]CALCULO_VR!$D:$D,[1]CALCULO_VR!$O:$O) -> -9.440863 | Y124: =_xlfn.XLOOKUP(A124,[1]CALCULO_VR!$D:$D,[1]CALCULO_VR!$P:$P) -> -64.197193
A125: 2583840 | B125: ANA MOZER GOMES DA SILVA KARIPUNA | C125: Porto Velho | D125: 45472 | E125: 45472 | F125: 34042.861 | G125: 1 | H125: 1 | J125: 0 | Q125: 121.88881 | R125: 4 | S125: 4 | T125: 163 | U125: 5 | W125: =_xlfn.XLOOKUP(A125,[1]CALCULO_VR!$D:$D,[1]CALCULO_VR!$J:$J) -> 80 | X125: =_xlfn.XLOOKUP(A125,[1]CALCULO_VR!$D:$D,[1]CALCULO_VR!$O:$O) -> -9.754157 | Y125: =_xlfn.XLOOKUP(A125,[1]CALCULO_VR!$D:$D,[1]CALCULO_VR!$P:$P) -> -64.318263
A126: 2583931 | B126: POSTO DE SAUDE FANTASIA KARIPUNA | C126: Porto Velho | D126: 45471 | E126: 45471 | F126: 34042.861 | G126: 1 | H126: 1 | J126: 0 | Q126: 121.90993 | R126: 4 | S126: 4 | T126: 163 | U126: 5 | W126: =_xlfn.XLOOKUP(A126,[1]CALCULO_VR!$D:$D,[1]CALCULO_VR!$J:$J) -> 80 | X126: =_xlfn.XLOOKUP(A126,[1]CALCULO_VR!$D:$D,[1]CALCULO_VR!$O:$O) -> -9.75421 | Y126: =_xlfn.XLOOKUP(A126,[1]CALCULO_VR!$D:$D,[1]CALCULO_VR!$P:$P) -> -64.318592
A127: 2583841 | B127: ANDRE LUIZ KARIPUNA | C127: Porto Velho | D127: 45471 | E127: 45471 | F127: 34042.861 | G127: 1 | H127: 1 | J127: 0 | Q127: 121.98141 | R127: 4 | S127: 4 | T127: 163 | U127: 5 | W127: =_xlfn.XLOOKUP(A127,[1]CALCULO_VR!$D:$D,[1]CALCULO_VR!$J:$J) -> 80 | X127: =_xlfn.XLOOKUP(A127,[1]CALCULO_VR!$D:$D,[1]CALCULO_VR!$O:$O) -> -9.754688 | Y127: =_xlfn.XLOOKUP(A127,[1]CALCULO_VR!$D:$D,[1]CALCULO_VR!$P:$P) -> -64.319085
A128: 2583862 | B128: TANGAE URU EU WAU WAU DE OLIVEIRA | C128: Porto Velho | D128: 45470 | E128: 45470 | F128: 34042.861 | G128: 1 | H128: 1 | J128: 0 | Q128: 121.95578 | R128: 4 | S128: 4 | T128: 163 | U128: 5 | V128: Selecionado | W128: =_xlfn.XLOOKUP(A128,[1]CALCULO_VR!$D:$D,[1]CALCULO_VR!$J:$J) -> 80 | X128: =_xlfn.XLOOKUP(A128,[1]CALCULO_VR!$D:$D,[1]CALCULO_VR!$O:$O) -> -9.754347 | Y128: =_xlfn.XLOOKUP(A128,[1]CALCULO_VR!$D:$D,[1]CALCULO_VR!$P:$P) -> -64.31926
A129: 2583863 | B129: LENI ONE PAULA | C129: Porto Velho | D129: 45472 | E129: 45472 | F129: 34042.861 | G129: 1 | H129: 1 | J129: 0 | Q129: 121.89738 | R129: 4 | S129: 4 | T129: 163 | U129: 5 | W129: =_xlfn.XLOOKUP(A129,[1]CALCULO_VR!$D:$D,[1]CALCULO_VR!$J:$J) -> 80 | X129: =_xlfn.XLOOKUP(A129,[1]CALCULO_VR!$D:$D,[1]CALCULO_VR!$O:$O) -> -9.754197 | Y129: =_xlfn.XLOOKUP(A129,[1]CALCULO_VR!$D:$D,[1]CALCULO_VR!$P:$P) -> -64.318358
A130: 2583864 | B130: ANDRESSA KARIPUNA URU EU WAU WAU BORI | C130: Porto Velho | D130: 45471 | E130: 45471 | F130: 34042.861 | G130: 1 | H130: 1 | J130: 0 | Q130: 121.9433 | R130: 4 | S130: 4 | T130: 163 | U130: 5 | W130: =_xlfn.XLOOKUP(A130,[1]CALCULO_VR!$D:$D,[1]CALCULO_VR!$J:$J) -> 80 | X130: =_xlfn.XLOOKUP(A130,[1]CALCULO_VR!$D:$D,[1]CALCULO_VR!$O:$O) -> -9.754397 | Y130: =_xlfn.XLOOKUP(A130,[1]CALCULO_VR!$D:$D,[1]CALCULO_VR!$P:$P) -> -64.318897
A131: 2583865 | B131: RAIMUNDO GOMES DA SILVA | C131: Porto Velho | D131: 45470 | E131: 45470 | F131: 34042.861 | G131: 1 | H131: 1 | J131: 0 | Q131: 121.96643 | R131: 4 | S131: 4 | T131: 163 | U131: 5 | W131: =_xlfn.XLOOKUP(A131,[1]CALCULO_VR!$D:$D,[1]CALCULO_VR!$J:$J) -> 80 | X131: =_xlfn.XLOOKUP(A131,[1]CALCULO_VR!$D:$D,[1]CALCULO_VR!$O:$O) -> -9.754643 | Y131: =_xlfn.XLOOKUP(A131,[1]CALCULO_VR!$D:$D,[1]CALCULO_VR!$P:$P) -> -64.318867
A132: 2583866 | B132: LAURA VICUNA PEREIRA MANSO | C132: Porto Velho | D132: 45470 | E132: 45470 | F132: 34042.861 | G132: 1 | H132: 1 | J132: 0 | Q132: 121.97457 | R132: 4 | S132: 4 | T132: 163 | U132: 5 | W132: =_xlfn.XLOOKUP(A132,[1]CALCULO_VR!$D:$D,[1]CALCULO_VR!$J:$J) -> 80 | X132: =_xlfn.XLOOKUP(A132,[1]CALCULO_VR!$D:$D,[1]CALCULO_VR!$O:$O) -> -9.754523 | Y132: =_xlfn.XLOOKUP(A132,[1]CALCULO_VR!$D:$D,[1]CALCULO_VR!$P:$P) -> -64.319285
A133: 2583867 | B133: MARQUES JOSE DE FIGUEIROA | C133: Porto Velho | D133: 45472 | E133: 45472 | F133: 34042.861 | G133: 1 | H133: 1 | J133: 0 | Q133: 121.92415 | R133: 4 | S133: 4 | T133: 163 | U133: 5 | W133: =_xlfn.XLOOKUP(A133,[1]CALCULO_VR!$D:$D,[1]CALCULO_VR!$J:$J) -> 80 | X133: =_xlfn.XLOOKUP(A133,[1]CALCULO_VR!$D:$D,[1]CALCULO_VR!$O:$O) -> -9.754542 | Y133: =_xlfn.XLOOKUP(A133,[1]CALCULO_VR!$D:$D,[1]CALCULO_VR!$P:$P) -> -64.318198
A134: 2583868 | B134: FRANCISCO FERREIRA DA SILVA | C134: Guajará-Mirim | D134: 45470 | E134: 45470 | F134: 34042.861 | G134: 1 | H134: 1 | J134: 0 | Q134: 78.012543 | R134: 3 | S134: 3 | T134: 223 | U134: 6 | W134: =_xlfn.XLOOKUP(A134,[1]CALCULO_VR!$D:$D,[1]CALCULO_VR!$J:$J) -> 80 | X134: =_xlfn.XLOOKUP(A134,[1]CALCULO_VR!$D:$D,[1]CALCULO_VR!$O:$O) -> -11.298548 | Y134: =_xlfn.XLOOKUP(A134,[1]CALCULO_VR!$D:$D,[1]CALCULO_VR!$P:$P) -> -64.849398
A135: 2583869 | B135: FRANCISCO FERREIRA DA SILVA | C135: Guajará-Mirim | D135: 45470 | E135: 45470 | F135: 34042.861 | G135: 1 | H135: 1 | J135: 0 | Q135: 84.371148 | R135: 3 | S135: 3 | T135: 223 | U135: 6 | W135: =_xlfn.XLOOKUP(A135,[1]CALCULO_VR!$D:$D,[1]CALCULO_VR!$J:$J) -> 80 | X135: =_xlfn.XLOOKUP(A135,[1]CALCULO_VR!$D:$D,[1]CALCULO_VR!$O:$O) -> -11.33905 | Y135: =_xlfn.XLOOKUP(A135,[1]CALCULO_VR!$D:$D,[1]CALCULO_VR!$P:$P) -> -64.808098
A136: 2585878 | B136: ANGELINA ORO MON | C136: Nova Mamoré | D136: 45463 | E136: 45463 | F136: 34042.861 | G136: 1 | H136: 1 | J136: 0 | Q136: 27.533476 | R136: 1 | S136: 1 | T136: 225 | U136: 6 | W136: =_xlfn.XLOOKUP(A136,[1]CALCULO_VR!$D:$D,[1]CALCULO_VR!$J:$J) -> 80 | X136: =_xlfn.XLOOKUP(A136,[1]CALCULO_VR!$D:$D,[1]CALCULO_VR!$O:$O) -> -10.368292 | Y136: =_xlfn.XLOOKUP(A136,[1]CALCULO_VR!$D:$D,[1]CALCULO_VR!$P:$P) -> -65.081318
A137: 2583871 | B137: REGINA ORO WIN | C137: Guajará-Mirim | D137: 45459 | E137: 45459 | F137: 34042.861 | G137: 1 | H137: 1 | J137: 0 | Q137: 140.18986 | R137: 4 | S137: 4 | T137: 163 | U137: 5 | W137: =_xlfn.XLOOKUP(A137,[1]CALCULO_VR!$D:$D,[1]CALCULO_VR!$J:$J) -> 80 | X137: =_xlfn.XLOOKUP(A137,[1]CALCULO_VR!$D:$D,[1]CALCULO_VR!$O:$O) -> -11.085385 | Y137: =_xlfn.XLOOKUP(A137,[1]CALCULO_VR!$D:$D,[1]CALCULO_VR!$P:$P) -> -64.07971
A138: 2585874 | B138: REBECA ORO WARAM XIJEIN | C138: Nova Mamoré | D138: 45464 | E138: 45464 | F138: 34042.861 | G138: 1 | H138: 1 | J138: 0 | Q138: 26.513264 | R138: 1 | S138: 1 | T138: 225 | U138: 6 | W138: =_xlfn.XLOOKUP(A138,[1]CALCULO_VR!$D:$D,[1]CALCULO_VR!$J:$J) -> 80 | X138: =_xlfn.XLOOKUP(A138,[1]CALCULO_VR!$D:$D,[1]CALCULO_VR!$O:$O) -> -10.326222 | Y138: =_xlfn.XLOOKUP(A138,[1]CALCULO_VR!$D:$D,[1]CALCULO_VR!$P:$P) -> -65.10289
A139: 2583872 | B139: RIKELVI MACURAP CABIXI | C139: Guajará-Mirim | D139: 45457 | E139: 45457 | F139: 34042.861 | G139: 1 | H139: 1 | J139: 0 | Q139: 130.18577 | R139: 4 | S139: 4 | T139: 163 | U139: 5 | W139: =_xlfn.XLOOKUP(A139,[1]CALCULO_VR!$D:$D,[1]CALCULO_VR!$J:$J) -> 80 | X139: =_xlfn.XLOOKUP(A139,[1]CALCULO_VR!$D:$D,[1]CALCULO_VR!$O:$O) -> -11.150807 | Y139: =_xlfn.XLOOKUP(A139,[1]CALCULO_VR!$D:$D,[1]CALCULO_VR!$P:$P) -> -64.19489
A140: 2583672 | B140: ALCILENE CASIMIRO DOS SANTOS | C140: Guajará-Mirim | D140: 45460 | E140: 45460 | F140: 34042.861 | G140: 1 | H140: 1 | J140: 0 | Q140: 60.536913 | R140: 2 | S140: 2 | T140: 251 | U140: 5 | W140: =_xlfn.XLOOKUP(A140,[1]CALCULO_VR!$D:$D,[1]CALCULO_VR!$J:$J) -> 80 | X140: =_xlfn.XLOOKUP(A140,[1]CALCULO_VR!$D:$D,[1]CALCULO_VR!$O:$O) -> -10.634712 | Y140: =_xlfn.XLOOKUP(A140,[1]CALCULO_VR!$D:$D,[1]CALCULO_VR!$P:$P) -> -64.788298
... A145: 2583675 | B145: ALDELINNO FIRMINO NEVES | C145: Guajará-Mirim | D145: 45460 | E145: 45460 | F145: 34042.861 | G145: 1 | H145: 1 | J145: 0 | Q145: 56.729213 | R145: 2 | S145: 2 | T145: 251 | U145: 5 | W145: =_xlfn.XLOOKUP(A145,[1]CALCULO_VR!$D:$D,[1]CALCULO_VR!$J:$J) -> 80 | X145: =_xlfn.XLOOKUP(A145,[1]CALCULO_VR!$D:$D,[1]CALCULO_VR!$O:$O) -> -10.680527 | Y145: =_xlfn.XLOOKUP(A145,[1]CALCULO_VR!$D:$D,[1]CALCULO_VR!$P:$P) -> -64.813467
A146: 2583873 | B146: SERGIO ORO WIN CABIXI | C146: Guajará-Mirim | D146: 45456 | E146: 45456 | F146: 34042.861 | G146: 1 | H146: 1 | J146: 0 | Q146: 130.0693 | R146: 4 | S146: 4 | T146: 163 | U146: 5 | V146: Selecionado | W146: =_xlfn.XLOOKUP(A146,[1]CALCULO_VR!$D:$D,[1]CALCULO_VR!$J:$J) -> 80 | X146: =_xlfn.XLOOKUP(A146,[1]CALCULO_VR!$D:$D,[1]CALCULO_VR!$O:$O) -> -11.15165 | Y146: =_xlfn.XLOOKUP(A146,[1]CALCULO_VR!$D:$D,[1]CALCULO_VR!$P:$P) -> -64.196308
A147: 2583874 | B147: ROSA MACURAPE | C147: Guajará-Mirim | D147: 45458 | E147: 45458 | F147: 34042.861 | G147: 1 | H147: 1 | J147: 0 | Q147: 140.3633 | R147: 4 | S147: 4 | T147: 163 | U147: 5 | W147: =_xlfn.XLOOKUP(A147,[1]CALCULO_VR!$D:$D,[1]CALCULO_VR!$J:$J) -> 80 | X147: =_xlfn.XLOOKUP(A147,[1]CALCULO_VR!$D:$D,[1]CALCULO_VR!$O:$O) -> -11.07969 | Y147: =_xlfn.XLOOKUP(A147,[1]CALCULO_VR!$D:$D,[1]CALCULO_VR!$P:$P) -> -64.07662
A148: 2585880 | B148: JO ORO MON | C148: Nova Mamoré | D148: 45462 | E148: 45462 | F148: 34042.861 | G148: 1 | H148: 1 | J148: 0 | Q148: 27.574873 | R148: 1 | S148: 1 | T148: 225 | U148: 6 | W148: =_xlfn.XLOOKUP(A148,[1]CALCULO_VR!$D:$D,[1]CALCULO_VR!$J:$J) -> 80 | X148: =_xlfn.XLOOKUP(A148,[1]CALCULO_VR!$D:$D,[1]CALCULO_VR!$O:$O) -> -10.365242 | Y148: =_xlfn.XLOOKUP(A148,[1]CALCULO_VR!$D:$D,[1]CALCULO_VR!$P:$P) -> -65.081507
A149: 2583676 | B149: RONALDO SOUZA DE HOLANDA | C149: Guajará-Mirim | D149: 45459 | E149: 45459 | F149: 34042.861 | G149: 1 | H149: 1 | J149: 0 | Q149: 58.47153 | R149: 2 | S149: 2 | T149: 251 | U149: 5 | W149: =_xlfn.XLOOKUP(A149,[1]CALCULO_VR!$D:$D,[1]CALCULO_VR!$J:$J) -> 80 | X149: =_xlfn.XLOOKUP(A149,[1]CALCULO_VR!$D:$D,[1]CALCULO_VR!$O:$O) -> -10.67119 | Y149: =_xlfn.XLOOKUP(A149,[1]CALCULO_VR!$D:$D,[1]CALCULO_VR!$P:$P) -> -64.799065
A150: 2583703 | B150: ANDREIA ORO EO | C150: Guajará-Mirim | D150: 45475 | E150: 45475 | F150: 34042.861 | G150: 1 | H150: 1 | J150: 0 | Q150: 35.230416 | R150: 1 | S150: 1 | T150: 225 | U150: 6 | W150: =_xlfn.XLOOKUP(A150,[1]CALCULO_VR!$D:$D,[1]CALCULO_VR!$J:$J) -> 80 | X150: =_xlfn.XLOOKUP(A150,[1]CALCULO_VR!$D:$D,[1]CALCULO_VR!$O:$O) -> -11.087475 | Y150: =_xlfn.XLOOKUP(A150,[1]CALCULO_VR!$D:$D,[1]CALCULO_VR!$P:$P) -> -65.277897
A151: 2583704 | B151: NERIZE JABUTI | C151: Guajará-Mirim | D151: 45475 | E151: 45475 | F151: 34042.861 | G151: 1 | H151: 1 | J151: 0 | Q151: 35.081457 | R151: 1 | S151: 1 | T151: 225 | U151: 6 | W151: =_xlfn.XLOOKUP(A151,[1]CALCULO_VR!$D:$D,[1]CALCULO_VR!$J:$J) -> 80 | X151: =_xlfn.XLOOKUP(A151,[1]CALCULO_VR!$D:$D,[1]CALCULO_VR!$O:$O) -> -11.086058 | Y151: =_xlfn.XLOOKUP(A151,[1]CALCULO_VR!$D:$D,[1]CALCULO_VR!$P:$P) -> -65.277453
A152: 2583875 | B152: ALBERTO AJURU | C152: Guajará-Mirim | D152: 45475 | E152: 45475 | F152: 34042.861 | G152: 1 | H152: 1 | J152: 0 | Q152: 147.95098 | R152: 4 | S152: 4 | T152: 163 | U152: 5 | W152: =_xlfn.XLOOKUP(A152,[1]CALCULO_VR!$D:$D,[1]CALCULO_VR!$J:$J) -> 80 | X152: =_xlfn.XLOOKUP(A152,[1]CALCULO_VR!$D:$D,[1]CALCULO_VR!$O:$O) -> -12.010872 | Y152: =_xlfn.XLOOKUP(A152,[1]CALCULO_VR!$D:$D,[1]CALCULO_VR!$P:$P) -> -64.82395
A153: 2583644 | B153: DEBORA CRISTINA SALES | C153: Guajará-Mirim | D153: 45474 | E153: 45474 | F153: 34042.861 | G153: 1 | H153: 1 | J153: 0 | Q153: 118.03643 | R153: 4 | S153: 4 | T153: 163 | U153: 5 | W153: =_xlfn.XLOOKUP(A153,[1]CALCULO_VR!$D:$D,[1]CALCULO_VR!$J:$J) -> 80 | X153: =_xlfn.XLOOKUP(A153,[1]CALCULO_VR!$D:$D,[1]CALCULO_VR!$O:$O) -> -11.786992 | Y153: =_xlfn.XLOOKUP(A153,[1]CALCULO_VR!$D:$D,[1]CALCULO_VR!$P:$P) -> -65.000763
A154: 2583876 | B154: JAIME WAJURU | C154: Guajará-Mirim | D154: 45475 | E154: 45475 | F154: 34042.861 | G154: 1 | H154: 1 | J154: 0 | Q154: 147.80401 | R154: 4 | S154: 4 | T154: 163 | U154: 5 | W154: =_xlfn.XLOOKUP(A154,[1]CALCULO_VR!$D:$D,[1]CALCULO_VR!$J:$J) -> 80 | X154: =_xlfn.XLOOKUP(A154,[1]CALCULO_VR!$D:$D,[1]CALCULO_VR!$O:$O) -> -12.01046 | Y154: =_xlfn.XLOOKUP(A154,[1]CALCULO_VR!$D:$D,[1]CALCULO_VR!$P:$P) -> -64.826555
A155: 2583877 | B155: ADRIANA MACURAP | C155: Guajará-Mirim | D155: 45475 | E155: 45475 | F155: 34042.861 | G155: 1 | H155: 1 | J155: 0 | Q155: 147.78628 | R155: 4 | S155: 4 | T155: 163 | U155: 5 | W155: =_xlfn.XLOOKUP(A155,[1]CALCULO_VR!$D:$D,[1]CALCULO_VR!$J:$J) -> 80 | X155: =_xlfn.XLOOKUP(A155,[1]CALCULO_VR!$D:$D,[1]CALCULO_VR!$O:$O) -> -12.010333 | Y155: =_xlfn.XLOOKUP(A155,[1]CALCULO_VR!$D:$D,[1]CALCULO_VR!$P:$P) -> -64.82667
A156: 2583650 | B156: MEIRELES SILVA KARITIANA | C156: Candeias do Jamari | D156: 45475 | E156: 45475 | F156: 34042.861 | G156: 1 | H156: 1 | J156: 0 | Q156: 56.928289 | R156: 2 | S156: 2 | T156: 251 | U156: 5 | W156: =_xlfn.XLOOKUP(A156,[1]CALCULO_VR!$D:$D,[1]CALCULO_VR!$J:$J) -> 80 | X156: =_xlfn.XLOOKUP(A156,[1]CALCULO_VR!$D:$D,[1]CALCULO_VR!$O:$O) -> -9.291147 | Y156: =_xlfn.XLOOKUP(A156,[1]CALCULO_VR!$D:$D,[1]CALCULO_VR!$P:$P) -> -63.778112
A157: 2583878 | B157: JOAO MEJIAS VALENTE | C157: Guajará-Mirim | D157: 45475 | E157: 45475 | F157: 34042.861 | G157: 1 | H157: 1 | J157: 0 | Q157: 20.650626 | R157: 1 | S157: 1 | T157: 225 | U157: 6 | W157: =_xlfn.XLOOKUP(A157,[1]CALCULO_VR!$D:$D,[1]CALCULO_VR!$J:$J) -> 80 | X157: =_xlfn.XLOOKUP(A157,[1]CALCULO_VR!$D:$D,[1]CALCULO_VR!$O:$O) -> -10.951152 | Y157: =_xlfn.XLOOKUP(A157,[1]CALCULO_VR!$D:$D,[1]CALCULO_VR!$P:$P) -> -65.267568
A158: 2583651 | B158: NADIA MARIA DYSABIBMA KARITIANA | C158: Candeias do Jamari | D158: 45475 | E158: 45475 | F158: 34042.861 | G158: 1 | H158: 1 | J158: 0 | Q158: 56.935085 | R158: 2 | S158: 2 | T158: 251 | U158: 5 | W158: =_xlfn.XLOOKUP(A158,[1]CALCULO_VR!$D:$D,[1]CALCULO_VR!$J:$J) -> 80 | X158: =_xlfn.XLOOKUP(A158,[1]CALCULO_VR!$D:$D,[1]CALCULO_VR!$O:$O) -> -9.291373 | Y158: =_xlfn.XLOOKUP(A158,[1]CALCULO_VR!$D:$D,[1]CALCULO_VR!$P:$P) -> -63.777013
... A179: 2583902 | B179: SEVERINO SOARES DE ANDRADE | C179: Guajará-Mirim | D179: 45476 | E179: 45476 | F179: 34042.861 | G179: 1 | H179: 1 | J179: 0 | Q179: 19.65356 | R179: 1 | S179: 1 | T179: 225 | U179: 6 | W179: =_xlfn.XLOOKUP(A179,[1]CALCULO_VR!$D:$D,[1]CALCULO_VR!$J:$J) -> 80 | X179: =_xlfn.XLOOKUP(A179,[1]CALCULO_VR!$D:$D,[1]CALCULO_VR!$O:$O) -> -10.942145 | Y179: =_xlfn.XLOOKUP(A179,[1]CALCULO_VR!$D:$D,[1]CALCULO_VR!$P:$P) -> -65.268852
A180: 2583705 | B180: CLEONICE MASSAKA | C180: Guajará-Mirim | D180: 45476 | E180: 45476 | F180: 34042.861 | G180: 1 | H180: 1 | J180: 0 | Q180: 35.397547 | R180: 1 | S180: 1 | T180: 225 | U180: 6 | V180: Selecionado | W180: =_xlfn.XLOOKUP(A180,[1]CALCULO_VR!$D:$D,[1]CALCULO_VR!$J:$J) -> 80 | X180: =_xlfn.XLOOKUP(A180,[1]CALCULO_VR!$D:$D,[1]CALCULO_VR!$O:$O) -> -11.08904 | Y180: =_xlfn.XLOOKUP(A180,[1]CALCULO_VR!$D:$D,[1]CALCULO_VR!$P:$P) -> -65.278228
A181: 2583697 | B181: LINO BORGES DE AMORIM | C181: Guajará-Mirim | D181: 45465 | E181: 45465 | F181: 34042.861 | G181: 1 | H181: 1 | J181: 0 | Q181: 51.176127 | R181: 2 | S181: 2 | T181: 251 | U181: 5 | W181: =_xlfn.XLOOKUP(A181,[1]CALCULO_VR!$D:$D,[1]CALCULO_VR!$J:$J) -> 80 | X181: =_xlfn.XLOOKUP(A181,[1]CALCULO_VR!$D:$D,[1]CALCULO_VR!$O:$O) -> -11.12942 | Y181: =_xlfn.XLOOKUP(A181,[1]CALCULO_VR!$D:$D,[1]CALCULO_VR!$P:$P) -> -65.026275
A182: 2583937 | B182: CASA DE APOIO ALDEIA PEDREIRA ANEXO II | C182: Guajará-Mirim | D182: 45456 | E182: 45456 | F182: 34042.861 | G182: 1 | H182: 1 | J182: 0 | Q182: 129.99957 | R182: 4 | S182: 4 | T182: 163 | U182: 5 | W182: =_xlfn.XLOOKUP(A182,[1]CALCULO_VR!$D:$D,[1]CALCULO_VR!$J:$J) -> 80 | X182: =_xlfn.XLOOKUP(A182,[1]CALCULO_VR!$D:$D,[1]CALCULO_VR!$O:$O) -> -11.15245 | Y182: =_xlfn.XLOOKUP(A182,[1]CALCULO_VR!$D:$D,[1]CALCULO_VR!$P:$P) -> -64.19726
A183: 2583698 | B183: ELINO JULIAO BORGES DE AMORIM | C183: Guajará-Mirim | D183: 45467 | E183: 45467 | F183: 34042.861 | G183: 1 | H183: 1 | J183: 0 | Q183: 51.145234 | R183: 2 | S183: 2 | T183: 251 | U183: 5 | W183: =_xlfn.XLOOKUP(A183,[1]CALCULO_VR!$D:$D,[1]CALCULO_VR!$J:$J) -> 80 | X183: =_xlfn.XLOOKUP(A183,[1]CALCULO_VR!$D:$D,[1]CALCULO_VR!$O:$O) -> -11.129258 | Y183: =_xlfn.XLOOKUP(A183,[1]CALCULO_VR!$D:$D,[1]CALCULO_VR!$P:$P) -> -65.02652
A184: 2583903 | B184: LIVINO FERREIRA DOS SANTOS | C184: Guajará-Mirim | D184: 45469 | E184: 45469 | F184: 34042.861 | G184: 1 | H184: 1 | J184: 0 | Q184: 105.46824 | R184: 3 | S184: 3 | T184: 223 | U184: 6 | W184: =_xlfn.XLOOKUP(A184,[1]CALCULO_VR!$D:$D,[1]CALCULO_VR!$J:$J) -> 80 | X184: =_xlfn.XLOOKUP(A184,[1]CALCULO_VR!$D:$D,[1]CALCULO_VR!$O:$O) -> -11.454268 | Y184: =_xlfn.XLOOKUP(A184,[1]CALCULO_VR!$D:$D,[1]CALCULO_VR!$P:$P) -> -64.650463
A185: 2583699 | B185: CRISTIANE OLIVEIRA DE FARIA | C185: Guajará-Mirim | D185: 45468 | E185: 45468 | F185: 34042.861 | G185: 1 | H185: 1 | J185: 0 | Q185: 46.067171 | R185: 2 | S185: 2 | T185: 251 | U185: 5 | W185: =_xlfn.XLOOKUP(A185,[1]CALCULO_VR!$D:$D,[1]CALCULO_VR!$J:$J) -> 80 | X185: =_xlfn.XLOOKUP(A185,[1]CALCULO_VR!$D:$D,[1]CALCULO_VR!$O:$O) -> -11.096632 | Y185: =_xlfn.XLOOKUP(A185,[1]CALCULO_VR!$D:$D,[1]CALCULO_VR!$P:$P) -> -65.059395
A186: 2583653 | B186: MARCELO KARITIANA | C186: Candeias do Jamari | D186: 45475 | E186: 45475 | F186: 34042.861 | G186: 1 | H186: 1 | J186: 0 | Q186: 56.886818 | R186: 2 | S186: 2 | T186: 251 | U186: 5 | W186: =_xlfn.XLOOKUP(A186,[1]CALCULO_VR!$D:$D,[1]CALCULO_VR!$J:$J) -> 80 | X186: =_xlfn.XLOOKUP(A186,[1]CALCULO_VR!$D:$D,[1]CALCULO_VR!$O:$O) -> -9.290907 | Y186: =_xlfn.XLOOKUP(A186,[1]CALCULO_VR!$D:$D,[1]CALCULO_VR!$P:$P) -> -63.777195
A187: 2583938 | B187: ESCOLA INDIGENA ESTADUAL DE ENSINO | C187: Porto Velho | D187: 45472 | E187: 45472 | F187: 34042.861 | G187: 1 | H187: 1 | J187: 0 | Q187: 121.90618 | R187: 4 | S187: 4 | T187: 163 | U187: 5 | W187: =_xlfn.XLOOKUP(A187,[1]CALCULO_VR!$D:$D,[1]CALCULO_VR!$J:$J) -> 80 | X187: =_xlfn.XLOOKUP(A187,[1]CALCULO_VR!$D:$D,[1]CALCULO_VR!$O:$O) -> -9.754467 | Y187: =_xlfn.XLOOKUP(A187,[1]CALCULO_VR!$D:$D,[1]CALCULO_VR!$P:$P) -> -64.31798
A188: 2585882 | B188: SEVERINO OROBONE | C188: Nova Mamoré | D188: 45464 | E188: 45464 | F188: 34042.861 | G188: 1 | H188: 1 | J188: 0 | Q188: 26.558201 | R188: 1 | S188: 1 | T188: 225 | U188: 6 | W188: =_xlfn.XLOOKUP(A188,[1]CALCULO_VR!$D:$D,[1]CALCULO_VR!$J:$J) -> 80 | X188: =_xlfn.XLOOKUP(A188,[1]CALCULO_VR!$D:$D,[1]CALCULO_VR!$O:$O) -> -10.325915 | Y188: =_xlfn.XLOOKUP(A188,[1]CALCULO_VR!$D:$D,[1]CALCULO_VR!$P:$P) -> -65.10257
A189: 2583904 | B189: MARIA DEL CARMEN RUIZ ARAUZ | C189: Guajará-Mirim | D189: 45478 | E189: 45478 | F189: 34042.861 | G189: 1 | H189: 1 | J189: 0 | Q189: 20.451689 | R189: 1 | S189: 1 | T189: 225 | U189: 6 | W189: =_xlfn.XLOOKUP(A189,[1]CALCULO_VR!$D:$D,[1]CALCULO_VR!$J:$J) -> 80 | X189: =_xlfn.XLOOKUP(A189,[1]CALCULO_VR!$D:$D,[1]CALCULO_VR!$O:$O) -> -10.949367 | Y189: =_xlfn.XLOOKUP(A189,[1]CALCULO_VR!$D:$D,[1]CALCULO_VR!$P:$P) -> -65.26786
A190: 2583654 | B190: UILZA CLEMANCI ALVES DOS SANTOS | C190: Candeias do Jamari | D190: 45477 | E190: 45477 | F190: 34042.861 | G190: 1 | H190: 1 | J190: 0 | Q190: 57.000701 | R190: 2 | S190: 2 | T190: 251 | U190: 5 | W190: =_xlfn.XLOOKUP(A190,[1]CALCULO_VR!$D:$D,[1]CALCULO_VR!$J:$J) -> 80 | X190: =_xlfn.XLOOKUP(A190,[1]CALCULO_VR!$D:$D,[1]CALCULO_VR!$O:$O) -> -9.291737 | Y190: =_xlfn.XLOOKUP(A190,[1]CALCULO_VR!$D:$D,[1]CALCULO_VR!$P:$P) -> -63.778568
A191: 2583656 | B191: FABIO GARCIA KARITIANA | C191: Candeias do Jamari | D191: 45477 | E191: 45477 | F191: 34042.861 | G191: 1 | H191: 1 | J191: 0 | Q191: 56.909845 | R191: 2 | S191: 2 | T191: 251 | U191: 5 | W191: =_xlfn.XLOOKUP(A191,[1]CALCULO_VR!$D:$D,[1]CALCULO_VR!$J:$J) -> 80 | X191: =_xlfn.XLOOKUP(A191,[1]CALCULO_VR!$D:$D,[1]CALCULO_VR!$O:$O) -> -9.290975 | Y191: =_xlfn.XLOOKUP(A191,[1]CALCULO_VR!$D:$D,[1]CALCULO_VR!$P:$P) -> -63.77814
A192: 2583905 | B192: RITA TUPI KAWAHIB | C192: Porto Velho | D192: 45471 | E192: 45471 | F192: 34042.861 | G192: 1 | H192: 1 | J192: 0 | Q192: 121.99502 | R192: 4 | S192: 4 | T192: 163 | U192: 5 | W192: =_xlfn.XLOOKUP(A192,[1]CALCULO_VR!$D:$D,[1]CALCULO_VR!$J:$J) -> 80 | X192: =_xlfn.XLOOKUP(A192,[1]CALCULO_VR!$D:$D,[1]CALCULO_VR!$O:$O) -> -9.754628 | Y192: =_xlfn.XLOOKUP(A192,[1]CALCULO_VR!$D:$D,[1]CALCULO_VR!$P:$P) -> -64.319492
... A303: 2595136 | B303: JOAO PA AT TUPARI | C303: São Francisco do Guaporé | D303: 45494 | E303: 45494 | F303: 34042.861 | G303: 1 | H303: 1 | J303: 0 | Q303: 90.074662 | R303: 3 | S303: 3 | T303: 223 | U303: 6 | W303: =_xlfn.XLOOKUP(A303,[1]CALCULO_VR!$D:$D,[1]CALCULO_VR!$J:$J) -> 80 | X303: =_xlfn.XLOOKUP(A303,[1]CALCULO_VR!$D:$D,[1]CALCULO_VR!$O:$O) -> -12.348212 | Y303: =_xlfn.XLOOKUP(A303,[1]CALCULO_VR!$D:$D,[1]CALCULO_VR!$P:$P) -> -62.79483
A304: 2595137 | B304: VALDEIR SEV KALAV GAVIAO | C304: Ji-Paraná | D304: 45497 | E304: 45497 | F304: 34042.861 | G304: 1 | H304: 1 | J304: 0 | Q304: 42.218483 | R304: 1 | S304: 1 | T304: 225 | U304: 6 | V304: Selecionado | W304: =_xlfn.XLOOKUP(A304,[1]CALCULO_VR!$D:$D,[1]CALCULO_VR!$J:$J) -> 80 | X304: =_xlfn.XLOOKUP(A304,[1]CALCULO_VR!$D:$D,[1]CALCULO_VR!$O:$O) -> -10.712018 | Y304: =_xlfn.XLOOKUP(A304,[1]CALCULO_VR!$D:$D,[1]CALCULO_VR!$P:$P) -> -61.599498
A305: 2595138 | B305: EDISLEIA VAZER KUV ZORO | C305: Ji-Paraná | D305: 45502 | E305: 45502 | F305: 34042.861 | G305: 1 | H305: 1 | J305: 0 | Q305: 47.592678 | R305: 2 | S305: 2 | T305: 251 | U305: 5 | W305: =_xlfn.XLOOKUP(A305,[1]CALCULO_VR!$D:$D,[1]CALCULO_VR!$J:$J) -> 80 | X305: =_xlfn.XLOOKUP(A305,[1]CALCULO_VR!$D:$D,[1]CALCULO_VR!$O:$O) -> -10.766147 | Y305: =_xlfn.XLOOKUP(A305,[1]CALCULO_VR!$D:$D,[1]CALCULO_VR!$P:$P) -> -61.525612
A306: 2595139 | B306: EDILEUZA SAA ZORO | C306: Ji-Paraná | D306: 45502 | E306: 45502 | F306: 34042.861 | G306: 1 | H306: 1 | J306: 0 | Q306: 42.104737 | R306: 1 | S306: 1 | T306: 225 | U306: 6 | W306: =_xlfn.XLOOKUP(A306,[1]CALCULO_VR!$D:$D,[1]CALCULO_VR!$J:$J) -> 80 | X306: =_xlfn.XLOOKUP(A306,[1]CALCULO_VR!$D:$D,[1]CALCULO_VR!$O:$O) -> -10.750543 | Y306: =_xlfn.XLOOKUP(A306,[1]CALCULO_VR!$D:$D,[1]CALCULO_VR!$P:$P) -> -61.583585
A307: 2595140 | B307: NABAYARA CINTA LARGA | C307: Vilhena | D307: 45502 | E307: 45502 | F307: 34042.861 | G307: 1 | H307: 1 | J307: 0 | Q307: 150.66673 | R307: 4 | S307: 4 | T307: 163 | U307: 5 | W307: =_xlfn.XLOOKUP(A307,[1]CALCULO_VR!$D:$D,[1]CALCULO_VR!$J:$J) -> 80 | X307: =_xlfn.XLOOKUP(A307,[1]CALCULO_VR!$D:$D,[1]CALCULO_VR!$O:$O) -> -11.418715 | Y307: =_xlfn.XLOOKUP(A307,[1]CALCULO_VR!$D:$D,[1]CALCULO_VR!$P:$P) -> -60.439432
...

Sheet Amostra 1_5_extrato_erro_5%
A1: UC | B1: Projeto | C1: Município | D1: Data Inicio | E1: Data Fim | F1: Custo(R$) | G1: Cons. | H1: Kit | I1: Regional | J1: Grupo | K1: Poste | L1: Rede AT km | M1: Rede BT km | N1: Medidor | O1: Trafo | P1: Equip. | Q1: VR | R1: Estrato | S1: regionale | T1: NGH | U1: NPH | V1: STATUS | W1: SIGFI | X1: Latitude_UC | Y1: Longitude_UC
A2: 2595147 | B2: POSTO DE SAUDE ALDEIA PALHAL | C2: Vilhena | D2: 45500 | E2: 45500 | F2: 34042.861 | G2: 1 | H2: 1 | J2: 0 | Q2: 144.5618 | R2: 5 | S2: 5 | T2: 118 | U2: 2 | W2: =_xlfn.XLOOKUP(A2,[1]CALCULO_VR!$D:$D,[1]CALCULO_VR!$J:$J) -> 80 | X2: =_xlfn.XLOOKUP(A2,[1]CALCULO_VR!$D:$D,[1]CALCULO_VR!$O:$O) -> -11.479878 | Y2: =_xlfn.XLOOKUP(A2,[1]CALCULO_VR!$D:$D,[1]CALCULO_VR!$P:$P) -> -60.460112
A3: 2595177 | B3: GERSON CINTA LARGA | C3: São Francisco do Guaporé | D3: 45504 | E3: 45504 | F3: 52970.941 | G3: 1 | H3: 1 | J3: 0 | Q3: 70.928033 | R3: 2 | S3: 2 | T3: 247 | U3: 4 | W3: =_xlfn.XLOOKUP(A3,[1]CALCULO_VR!$D:$D,[1]CALCULO_VR!$J:$J) -> 160 | X3: =_xlfn.XLOOKUP(A3,[1]CALCULO_VR!$D:$D,[1]CALCULO_VR!$O:$O) -> -12.408093 | Y3: =_xlfn.XLOOKUP(A3,[1]CALCULO_VR!$D:$D,[1]CALCULO_VR!$P:$P) -> -63.021408
A4: 2595236 | B4: POSTO DE SAUDE ALDEIA CAJUI | C4: São Francisco do Guaporé | D4: 45505 | E4: 45505 | F4: 34042.861 | G4: 1 | H4: 1 | J4: 0 | Q4: 70.937531 | R4: 2 | S4: 2 | T4: 247 | U4: 4 | W4: =_xlfn.XLOOKUP(A4,[1]CALCULO_VR!$D:$D,[1]CALCULO_VR!$J:$J) -> 80 | X4: =_xlfn.XLOOKUP(A4,[1]CALCULO_VR!$D:$D,[1]CALCULO_VR!$O:$O) -> -12.407253 | Y4: =_xlfn.XLOOKUP(A4,[1]CALCULO_VR!$D:$D,[1]CALCULO_VR!$P:$P) -> -63.020755
A5: 2595237 | B5: EIEEFM KON KOATT TUPARI | C5: São Francisco do Guaporé | D5: 45505 | E5: 45505 | F5: 34042.861 | G5: 1 | H5: 1 | J5: 0 | Q5: 70.910302 | R5: 2 | S5: 2 | T5: 247 | U5: 4 | W5: =_xlfn.XLOOKUP(A5,[1]CALCULO_VR!$D:$D,[1]CALCULO_VR!$J:$J) -> 80 | X5: =_xlfn.XLOOKUP(A5,[1]CALCULO_VR!$D:$D,[1]CALCULO_VR!$O:$O) -> -12.40728 | Y5: =_xlfn.XLOOKUP(A5,[1]CALCULO_VR!$D:$D,[1]CALCULO_VR!$P:$P) -> -63.02107
A6: 2595249 | B6: ROSEANE TENHARIN | C6: São Francisco do Guaporé | D6: 45500 | E6: 45500 | F6: 52970.941 | G6: 1 | H6: 1 | J6: 0 | Q6: 90.038796 | R6: 3 | S6: 3 | T6: 161 | U6: 2 | W6: =_xlfn.XLOOKUP(A6,[1]CALCULO_VR!$D:$D,[1]CALCULO_VR!$J:$J) -> 160 | X6: =_xlfn.XLOOKUP(A6,[1]CALCULO_VR!$D:$D,[1]CALCULO_VR!$O:$O) -> -12.34808 | Y6: =_xlfn.XLOOKUP(A6,[1]CALCULO_VR!$D:$D,[1]CALCULO_VR!$P:$P) -> -62.795132
A7: 2595250 | B7: OSMAR MAINTAKA TUPARI | C7: São Francisco do Guaporé | D7: 45500 | E7: 45500 | F7: 52970.941 | G7: 1 | H7: 1 | J7: 0 | Q7: 89.873976 | R7: 3 | S7: 3 | T7: 161 | U7: 2 | W7: =_xlfn.XLOOKUP(A7,[1]CALCULO_VR!$D:$D,[1]CALCULO_VR!$J:$J) -> 160 | X7: =_xlfn.XLOOKUP(A7,[1]CALCULO_VR!$D:$D,[1]CALCULO_VR!$O:$O) -> -12.347225 | Y7: =_xlfn.XLOOKUP(A7,[1]CALCULO_VR!$D:$D,[1]CALCULO_VR!$P:$P) -> -62.796425
A8: 2595269 | B8: EIEEFM KON KOATT TUPARI | C8: São Francisco do Guaporé | D8: 45506 | E8: 45506 | F8: 34042.861 | G8: 1 | H8: 1 | J8: 0 | Q8: 70.974094 | R8: 2 | S8: 2 | T8: 247 | U8: 4 | W8: =_xlfn.XLOOKUP(A8,[1]CALCULO_VR!$D:$D,[1]CALCULO_VR!$J:$J) -> 80 | X8: =_xlfn.XLOOKUP(A8,[1]CALCULO_VR!$D:$D,[1]CALCULO_VR!$O:$O) -> -12.41203 | Y8: =_xlfn.XLOOKUP(A8,[1]CALCULO_VR!$D:$D,[1]CALCULO_VR!$P:$P) -> -63.023502
A9: 2595272 | B9: WALDIR FIRMINO VALE | C9: São Francisco do Guaporé | D9: 45502 | E9: 45502 | F9: 52970.941 | G9: 1 | H9: 1 | J9: 0 | Q9: 89.869751 | R9: 3 | S9: 3 | T9: 161 | U9: 2 | W9: =_xlfn.XLOOKUP(A9,[1]CALCULO_VR!$D:$D,[1]CALCULO_VR!$J:$J) -> 160 | X9: =_xlfn.XLOOKUP(A9,[1]CALCULO_VR!$D:$D,[1]CALCULO_VR!$O:$O) -> -12.347462 | Y9: =_xlfn.XLOOKUP(A9,[1]CALCULO_VR!$D:$D,[1]CALCULO_VR!$P:$P) -> -62.796557
A10: 2583661 | B10: DIVINO GOMES LIMA | C10: Guajará-Mirim | D10: 45459 | E10: 45459 | F10: 34042.861 | G10: 1 | H10: 1 | J10: 0 | Q10: 54.60863 | R10: 2 | S10: 2 | T10: 247 | U10: 4 | W10: =_xlfn.XLOOKUP(A10,[1]CALCULO_VR!$D:$D,[1]CALCULO_VR!$J:$J) -> 80 | X10: =_xlfn.XLOOKUP(A10,[1]CALCULO_VR!$D:$D,[1]CALCULO_VR!$O:$O) -> -10.681757 | Y10: =_xlfn.XLOOKUP(A10,[1]CALCULO_VR!$D:$D,[1]CALCULO_VR!$P:$P) -> -64.832982
A11: 2583662 | B11: JOSE PEREIRA ALVES | C11: Guajará-Mirim | D11: 45458 | E11: 45458 | F11: 34042.861 | G11: 1 | H11: 1 | J11: 0 | Q11: 56.302057 | R11: 2 | S11: 2 | T11: 247 | U11: 4 | W11: =_xlfn.XLOOKUP(A11,[1]CALCULO_VR!$D:$D,[1]CALCULO_VR!$J:$J) -> 80 | X11: =_xlfn.XLOOKUP(A11,[1]CALCULO_VR!$D:$D,[1]CALCULO_VR!$O:$O) -> -10.673628 | Y11: =_xlfn.XLOOKUP(A11,[1]CALCULO_VR!$D:$D,[1]CALCULO_VR!$P:$P) -> -64.818818
A12: 2583663 | B12: ELIETE BIRA MACIEL | C12: Guajará-Mirim | D12: 45459 | E12: 45459 | F12: 34042.861 | G12: 1 | H12: 1 | J12: 0 | Q12: 56.649232 | R12: 2 | S12: 2 | T12: 247 | U12: 4 | W12: =_xlfn.XLOOKUP(A12,[1]CALCULO_VR!$D:$D,[1]CALCULO_VR!$J:$J) -> 80 | X12: =_xlfn.XLOOKUP(A12,[1]CALCULO_VR!$D:$D,[1]CALCULO_VR!$O:$O) -> -10.669567 | Y12: =_xlfn.XLOOKUP(A12,[1]CALCULO_VR!$D:$D,[1]CALCULO_VR!$P:$P) -> -64.816427
A13: 2583664 | B13: JOSE ELEUTERIO FILHO | C13: Guajará-Mirim | D13: 45459 | E13: 45459 | F13: 34042.861 | G13: 1 | H13: 1 | J13: 0 | Q13: 57.074959 | R13: 2 | S13: 2 | T13: 247 | U13: 4 | W13: =_xlfn.XLOOKUP(A13,[1]CALCULO_VR!$D:$D,[1]CALCULO_VR!$J:$J) -> 80 | X13: =_xlfn.XLOOKUP(A13,[1]CALCULO_VR!$D:$D,[1]CALCULO_VR!$O:$O) -> -10.674992 | Y13: =_xlfn.XLOOKUP(A13,[1]CALCULO_VR!$D:$D,[1]CALCULO_VR!$P:$P) -> -64.811327
... A52: 2583785 | B52: SAMUEL ORO WIN | C52: Guajará-Mirim | D52: 45461 | E52: 45461 | F52: 34042.861 | G52: 1 | H52: 1 | J52: 0 | Q52: 134.37134 | R52: 5 | S52: 5 | T52: 118 | U52: 2 | W52: =_xlfn.XLOOKUP(A52,[1]CALCULO_VR!$D:$D,[1]CALCULO_VR!$J:$J) -> 80 | X52: =_xlfn.XLOOKUP(A52,[1]CALCULO_VR!$D:$D,[1]CALCULO_VR!$O:$O) -> -11.121525 | Y52: =_xlfn.XLOOKUP(A52,[1]CALCULO_VR!$D:$D,[1]CALCULO_VR!$P:$P) -> -64.14515
A53: 2583786 | B53: MARINA ORO WIN | C53: Guajará-Mirim | D53: 45461 | E53: 45461 | F53: 34042.861 | G53: 1 | H53: 1 | J53: 0 | Q53: 134.2749 | R53: 5 | S53: 5 | T53: 118 | U53: 2 | V53: Selecionado | W53: =_xlfn.XLOOKUP(A53,[1]CALCULO_VR!$D:$D,[1]CALCULO_VR!$J:$J) -> 80 | X53: =_xlfn.XLOOKUP(A53,[1]CALCULO_VR!$D:$D,[1]CALCULO_VR!$O:$O) -> -11.121458 | Y53: =_xlfn.XLOOKUP(A53,[1]CALCULO_VR!$D:$D,[1]CALCULO_VR!$P:$P) -> -64.146052
A54: 2583787 | B54: FRANCIELE PAMOTO KARITIANA | C54: Porto Velho | D54: 45468 | E54: 45468 | F54: 34042.861 | G54: 1 | H54: 1 | J54: 0 | Q54: 48.789481 | R54: 2 | S54: 2 | T54: 247 | U54: 4 | W54: =_xlfn.XLOOKUP(A54,[1]CALCULO_VR!$D:$D,[1]CALCULO_VR!$J:$J) -> 80 | X54: =_xlfn.XLOOKUP(A54,[1]CALCULO_VR!$D:$D,[1]CALCULO_VR!$O:$O) -> -9.192407 | Y54: =_xlfn.XLOOKUP(A54,[1]CALCULO_VR!$D:$D,[1]CALCULO_VR!$P:$P) -> -63.947577
A55: 2583701 | B55: MARIA LILIA OLIVEIRA GONCALVES | C55: Guajará-Mirim | D55: 45467 | E55: 45467 | F55: 34042.861 | G55: 1 | H55: 1 | J55: 0 | Q55: 74.086101 | R55: 3 | S55: 3 | T55: 161 | U55: 2 | W55: =_xlfn.XLOOKUP(A55,[1]CALCULO_VR!$D:$D,[1]CALCULO_VR!$J:$J) -> 80 | X55: =_xlfn.XLOOKUP(A55,[1]CALCULO_VR!$D:$D,[1]CALCULO_VR!$O:$O) -> -11.20843 | Y55: =_xlfn.XLOOKUP(A55,[1]CALCULO_VR!$D:$D,[1]CALCULO_VR!$P:$P) -> -64.80945
A56: 2583921 | B56: POSTO DE SAUDE ALDEIA SAO LUIZ | C56: Guajará-Mirim | D56: 45460 | E56: 45460 | F56: 34042.861 | G56: 1 | H56: 1 | J56: 0 | Q56: 140.19241 | R56: 5 | S56: 5 | T56: 118 | U56: 2 | W56: =_xlfn.XLOOKUP(A56,[1]CALCULO_VR!$D:$D,[1]CALCULO_VR!$J:$J) -> 80 | X56: =_xlfn.XLOOKUP(A56,[1]CALCULO_VR!$D:$D,[1]CALCULO_VR!$O:$O) -> -11.085762 | Y56: =_xlfn.XLOOKUP(A56,[1]CALCULO_VR!$D:$D,[1]CALCULO_VR!$P:$P) -> -64.079783
A57: 2583685 | B57: WALDEMIR LOPES DE AMORIM | C57: Guajará-Mirim | D57: 45464 | E57: 45464 | F57: 34042.861 | G57: 1 | H57: 1 | J57: 0 | Q57: 65.495643 | R57: 2 | S57: 2 | T57: 247 | U57: 4 | W57: =_xlfn.XLOOKUP(A57,[1]CALCULO_VR!$D:$D,[1]CALCULO_VR!$J:$J) -> 80 | X57: =_xlfn.XLOOKUP(A57,[1]CALCULO_VR!$D:$D,[1]CALCULO_VR!$O:$O) -> -11.200607 | Y57: =_xlfn.XLOOKUP(A57,[1]CALCULO_VR!$D:$D,[1]CALCULO_VR!$P:$P) -> -64.910355
A58: 2583686 | B58: JOSE MARIA DE SOUZA RUFINO | C58: Guajará-Mirim | D58: 45464 | E58: 45464 | F58: 34042.861 | G58: 1 | H58: 1 | J58: 0 | Q58: 65.745664 | R58: 2 | S58: 2 | T58: 247 | U58: 4 | W58: =_xlfn.XLOOKUP(A58,[1]CALCULO_VR!$D:$D,[1]CALCULO_VR!$J:$J) -> 80 | X58: =_xlfn.XLOOKUP(A58,[1]CALCULO_VR!$D:$D,[1]CALCULO_VR!$O:$O) -> -11.198337 | Y58: =_xlfn.XLOOKUP(A58,[1]CALCULO_VR!$D:$D,[1]CALCULO_VR!$P:$P) -> -64.904643
A59: 2583922 | B59: ESCOLA JOAO FARIAS DE BARROS | C59: Guajará-Mirim | D59: 45460 | E59: 45460 | F59: 34042.861 | G59: 1 | H59: 1 | J59: 0 | Q59: 140.12685 | R59: 5 | S59: 5 | T59: 118 | U59: 2 | W59: =_xlfn.XLOOKUP(A59,[1]CALCULO_VR!$D:$D,[1]CALCULO_VR!$J:$J) -> 80 | X59: =_xlfn.XLOOKUP(A59,[1]CALCULO_VR!$D:$D,[1]CALCULO_VR!$O:$O) -> -11.087058 | Y59: =_xlfn.XLOOKUP(A59,[1]CALCULO_VR!$D:$D,[1]CALCULO_VR!$P:$P) -> -64.080738
A60: 2583788 | B60: SILVANA KARITIANA | C60: Porto Velho | D60: 45468 | E60: 45468 | F60: 34042.861 | G60: 1 | H60: 1 | J60: 0 | Q60: 48.832983 | R60: 2 | S60: 2 | T60: 247 | U60: 4 | W60: =_xlfn.XLOOKUP(A60,[1]CALCULO_VR!$D:$D,[1]CALCULO_VR!$J:$J) -> 80 | X60: =_xlfn.XLOOKUP(A60,[1]CALCULO_VR!$D:$D,[1]CALCULO_VR!$O:$O) -> -9.192673 | Y60: =_xlfn.XLOOKUP(A60,[1]CALCULO_VR!$D:$D,[1]CALCULO_VR!$P:$P) -> -63.948097
A61: 2583789 | B61: GEICILENE ORO JOWIN | C61: Guajará-Mirim | D61: 45460 | E61: 45460 | F61: 34042.861 | G61: 1 | H61: 1 | J61: 0 | Q61: 140.19906 | R61: 5 | S61: 5 | T61: 118 | U61: 2 | W61: =_xlfn.XLOOKUP(A61,[1]CALCULO_VR!$D:$D,[1]CALCULO_VR!$J:$J) -> 80 | X61: =_xlfn.XLOOKUP(A61,[1]CALCULO_VR!$D:$D,[1]CALCULO_VR!$O:$O) -> -11.087127 | Y61: =_xlfn.XLOOKUP(A61,[1]CALCULO_VR!$D:$D,[1]CALCULO_VR!$P:$P) -> -64.080073
A62: 2583790 | B62: ROSENDA FERREIRA INUMA | C62: Guajará-Mirim | D62: 45469 | E62: 45469 | F62: 34042.861 | G62: 1 | H62: 1 | J62: 0 | Q62: 94.114195 | R62: 3 | S62: 3 | T62: 161 | U62: 2 | W62: =_xlfn.XLOOKUP(A62,[1]CALCULO_VR!$D:$D,[1]CALCULO_VR!$J:$J) -> 80 | X62: =_xlfn.XLOOKUP(A62,[1]CALCULO_VR!$D:$D,[1]CALCULO_VR!$O:$O) -> -11.380303 | Y62: =_xlfn.XLOOKUP(A62,[1]CALCULO_VR!$D:$D,[1]CALCULO_VR!$P:$P) -> -64.72229
A63: 2583791 | B63: NEIDE MORAIS KARITIANA LOPES | C63: Porto Velho | D63: 45469 | E63: 45469 | F63: 34042.861 | G63: 1 | H63: 1 | J63: 0 | Q63: 66.468637 | R63: 2 | S63: 2 | T63: 247 | U63: 4 | W63: =_xlfn.XLOOKUP(A63,[1]CALCULO_VR!$D:$D,[1]CALCULO_VR!$J:$J) -> 80 | X63: =_xlfn.XLOOKUP(A63,[1]CALCULO_VR!$D:$D,[1]CALCULO_VR!$O:$O) -> -9.320778 | Y63: =_xlfn.XLOOKUP(A63,[1]CALCULO_VR!$D:$D,[1]CALCULO_VR!$P:$P) -> -64.064005
A64: 2583792 | B64: JOAO FERREIRA LOPES | C64: Guajará-Mirim | D64: 45468 | E64: 45468 | F64: 34042.861 | G64: 1 | H64: 1 | J64: 0 | Q64: 86.782843 | R64: 3 | S64: 3 | T64: 161 | U64: 2 | W64: =_xlfn.XLOOKUP(A64,[1]CALCULO_VR!$D:$D,[1]CALCULO_VR!$J:$J) -> 80 | X64: =_xlfn.XLOOKUP(A64,[1]CALCULO_VR!$D:$D,[1]CALCULO_VR!$O:$O) -> -11.353395 | Y64: =_xlfn.XLOOKUP(A64,[1]CALCULO_VR!$D:$D,[1]CALCULO_VR!$P:$P) -> -64.791288
A65: 2583923 | B65: ESCOLA INDIGENA NYJNYJI | C65: Porto Velho | D65: 45469 | E65: 45469 | F65: 34042.861 | G65: 1 | H65: 1 | J65: 0 | Q65: 66.366 | R65: 2 | S65: 2 | T65: 247 | U65: 4 | W65: =_xlfn.XLOOKUP(A65,[1]CALCULO_VR!$D:$D,[1]CALCULO_VR!$J:$J) -> 80 | X65: =_xlfn.XLOOKUP(A65,[1]CALCULO_VR!$D:$D,[1]CALCULO_VR!$O:$O) -> -9.32021 | Y65: =_xlfn.XLOOKUP(A65,[1]CALCULO_VR!$D:$D,[1]CALCULO_VR!$P:$P) -> -64.062953
... A80: 2583808 | B80: DANIEL NONATO KARITIANA | C80: Porto Velho | D80: 45468 | E80: 45468 | F80: 34042.861 | G80: 1 | H80: 1 | J80: 0 | Q80: 48.735626 | R80: 2 | S80: 2 | T80: 247 | U80: 4 | W80: =_xlfn.XLOOKUP(A80,[1]CALCULO_VR!$D:$D,[1]CALCULO_VR!$J:$J) -> 80 | X80: =_xlfn.XLOOKUP(A80,[1]CALCULO_VR!$D:$D,[1]CALCULO_VR!$O:$O) -> -9.191895 | Y80: =_xlfn.XLOOKUP(A80,[1]CALCULO_VR!$D:$D,[1]CALCULO_VR!$P:$P) -> -63.947615
A81: 2583809 | B81: MARCIO KARINTIANA | C81: Porto Velho | D81: 45469 | E81: 45469 | F81: 34042.861 | G81: 1 | H81: 1 | J81: 0 | Q81: 66.470852 | R81: 2 | S81: 2 | T81: 247 | U81: 4 | V81: Selecionado | W81: =_xlfn.XLOOKUP(A81,[1]CALCULO_VR!$D:$D,[1]CALCULO_VR!$J:$J) -> 80 | X81: =_xlfn.XLOOKUP(A81,[1]CALCULO_VR!$D:$D,[1]CALCULO_VR!$O:$O) -> -9.320473 | Y81: =_xlfn.XLOOKUP(A81,[1]CALCULO_VR!$D:$D,[1]CALCULO_VR!$P:$P) -> -64.064798
A82: 2583680 | B82: REGIANE ORO EO | C82: Guajará-Mirim | D82: 45469 | E82: 45469 | F82: 34042.861 | G82: 1 | H82: 1 | J82: 0 | Q82: 78.373186 | R82: 3 | S82: 3 | T82: 161 | U82: 2 | W82: =_xlfn.XLOOKUP(A82,[1]CALCULO_VR!$D:$D,[1]CALCULO_VR!$J:$J) -> 80 | X82: =_xlfn.XLOOKUP(A82,[1]CALCULO_VR!$D:$D,[1]CALCULO_VR!$O:$O) -> -11.187977 | Y82: =_xlfn.XLOOKUP(A82,[1]CALCULO_VR!$D:$D,[1]CALCULO_VR!$P:$P) -> -64.742955
A83: 2583810 | B83: JEAN ORO WARAM | C83: Guajará-Mirim | D83: 45460 | E83: 45460 | F83: 34042.861 | G83: 1 | H83: 1 | J83: 0 | Q83: 140.24523 | R83: 5 | S83: 5 | T83: 118 | U83: 2 | W83: =_xlfn.XLOOKUP(A83,[1]CALCULO_VR!$D:$D,[1]CALCULO_VR!$J:$J) -> 80 | X83: =_xlfn.XLOOKUP(A83,[1]CALCULO_VR!$D:$D,[1]CALCULO_VR!$O:$O) -> -11.087268 | Y83: =_xlfn.XLOOKUP(A83,[1]CALCULO_VR!$D:$D,[1]CALCULO_VR!$P:$P) -> -64.079673
A84: 2583926 | B84: IGREJA PENTECOSTAL MISTERIO MOVER DO | C84: Porto Velho | D84: 45469 | E84: 45469 | F84: 34042.861 | G84: 1 | H84: 1 | J84: 0 | Q84: 66.470358 | R84: 2 | S84: 2 | T84: 247 | U84: 4 | W84: =_xlfn.XLOOKUP(A84,[1]CALCULO_VR!$D:$D,[1]CALCULO_VR!$J:$J) -> 80 | X84: =_xlfn.XLOOKUP(A84,[1]CALCULO_VR!$D:$D,[1]CALCULO_VR!$O:$O) -> -9.320872 | Y84: =_xlfn.XLOOKUP(A84,[1]CALCULO_VR!$D:$D,[1]CALCULO_VR!$P:$P) -> -64.063817
A85: 2585871 | B85: KATIA ORO MON | C85: Nova Mamoré | D85: 45464 | E85: 45464 | F85: 34042.861 | G85: 1 | H85: 1 | J85: 0 | Q85: 26.543438 | R85: 1 | S85: 1 | T85: 225 | U85: 5 | W85: =_xlfn.XLOOKUP(A85,[1]CALCULO_VR!$D:$D,[1]CALCULO_VR!$J:$J) -> 80 | X85: =_xlfn.XLOOKUP(A85,[1]CALCULO_VR!$D:$D,[1]CALCULO_VR!$O:$O) -> -10.326277 | Y85: =_xlfn.XLOOKUP(A85,[1]CALCULO_VR!$D:$D,[1]CALCULO_VR!$P:$P) -> -65.102573
A86: 2583811 | B86: ROBERTO ORO WIN | C86: Guajará-Mirim | D86: 45460 | E86: 45460 | F86: 34042.861 | G86: 1 | H86: 1 | J86: 0 | Q86: 139.74196 | R86: 5 | S86: 5 | T86: 118 | U86: 2 | W86: =_xlfn.XLOOKUP(A86,[1]CALCULO_VR!$D:$D,[1]CALCULO_VR!$J:$J) -> 80 | X86: =_xlfn.XLOOKUP(A86,[1]CALCULO_VR!$D:$D,[1]CALCULO_VR!$O:$O) -> -11.093202 | Y86: =_xlfn.XLOOKUP(A86,[1]CALCULO_VR!$D:$D,[1]CALCULO_VR!$P:$P) -> -64.085992
A87: 2583812 | B87: VITOR GARCIA POROGNGA KARITIANA | C87: Porto Velho | D87: 45469 | E87: 45469 | F87: 34042.861 | G87: 1 | H87: 1 | J87: 0 | Q87: 66.490199 | R87: 2 | S87: 2 | T87: 247 | U87: 4 | W87: =_xlfn.XLOOKUP(A87,[1]CALCULO_VR!$D:$D,[1]CALCULO_VR!$J:$J) -> 80 | X87: =_xlfn.XLOOKUP(A87,[1]CALCULO_VR!$D:$D,[1]CALCULO_VR!$O:$O) -> -9.321055 | Y87: =_xlfn.XLOOKUP(A87,[1]CALCULO_VR!$D:$D,[1]CALCULO_VR!$P:$P) -> -64.063842
A88: 2583690 | B88: JOAQUIM MAMEDE CARNEIRO | C88: Guajará-Mirim | D88: 45468 | E88: 45468 | F88: 34042.861 | G88: 1 | H88: 1 | J88: 0 | Q88: 39.829242 | R88: 1 | S88: 1 | T88: 225 | U88: 5 | W88: =_xlfn.XLOOKUP(A88,[1]CALCULO_VR!$D:$D,[1]CALCULO_VR!$J:$J) -> 80 | X88: =_xlfn.XLOOKUP(A88,[1]CALCULO_VR!$D:$D,[1]CALCULO_VR!$O:$O) -> -11.080777 | Y88: =_xlfn.XLOOKUP(A88,[1]CALCULO_VR!$D:$D,[1]CALCULO_VR!$P:$P) -> -65.135828
A89: 2583813 | B89: ADILIO ORO WIN | C89: Guajará-Mirim | D89: 45460 | E89: 45460 | F89: 34042.861 | G89: 1 | H89: 1 | J89: 0 | Q89: 140.25107 | R89: 5 | S89: 5 | T89: 118 | U89: 2 | W89: =_xlfn.XLOOKUP(A89,[1]CALCULO_VR!$D:$D,[1]CALCULO_VR!$J:$J) -> 80 | X89: =_xlfn.XLOOKUP(A89,[1]CALCULO_VR!$D:$D,[1]CALCULO_VR!$O:$O) -> -11.087207 | Y89: =_xlfn.XLOOKUP(A89,[1]CALCULO_VR!$D:$D,[1]CALCULO_VR!$P:$P) -> -64.079602
A90: 2583814 | B90: EDILENE CANOE | C90: Guajará-Mirim | D90: 45465 | E90: 45465 | F90: 34042.861 | G90: 1 | H90: 1 | J90: 0 | Q90: 140.27414 | R90: 5 | S90: 5 | T90: 118 | U90: 2 | W90: =_xlfn.XLOOKUP(A90,[1]CALCULO_VR!$D:$D,[1]CALCULO_VR!$J:$J) -> 80 | X90: =_xlfn.XLOOKUP(A90,[1]CALCULO_VR!$D:$D,[1]CALCULO_VR!$O:$O) -> -11.085838 | Y90: =_xlfn.XLOOKUP(A90,[1]CALCULO_VR!$D:$D,[1]CALCULO_VR!$P:$P) -> -64.07903
A91: 2583691 | B91: FRANCISCO CHAGAS DE LIMA | C91: Guajará-Mirim | D91: 45468 | E91: 45468 | F91: 34042.861 | G91: 1 | H91: 1 | J91: 0 | Q91: 42.491227 | R91: 1 | S91: 1 | T91: 225 | U91: 5 | W91: =_xlfn.XLOOKUP(A91,[1]CALCULO_VR!$D:$D,[1]CALCULO_VR!$J:$J) -> 80 | X91: =_xlfn.XLOOKUP(A91,[1]CALCULO_VR!$D:$D,[1]CALCULO_VR!$O:$O) -> -11.086615 | Y91: =_xlfn.XLOOKUP(A91,[1]CALCULO_VR!$D:$D,[1]CALCULO_VR!$P:$P) -> -65.100293
A92: 2583815 | B92: EDIELSON NONATO KARITIANA | C92: Porto Velho | D92: 45467 | E92: 45467 | F92: 34042.861 | G92: 1 | H92: 1 | J92: 0 | Q92: 48.744503 | R92: 2 | S92: 2 | T92: 247 | U92: 4 | W92: =_xlfn.XLOOKUP(A92,[1]CALCULO_VR!$D:$D,[1]CALCULO_VR!$J:$J) -> 80 | X92: =_xlfn.XLOOKUP(A92,[1]CALCULO_VR!$D:$D,[1]CALCULO_VR!$O:$O) -> -9.192078 | Y92: =_xlfn.XLOOKUP(A92,[1]CALCULO_VR!$D:$D,[1]CALCULO_VR!$P:$P) -> -63.94724
A93: 2583816 | B93: AILTON JOSE ORO WIN | C93: Guajará-Mirim | D93: 45464 | E93: 45464 | F93: 34042.861 | G93: 1 | H93: 1 | J93: 0 | Q93: 140.41415 | R93: 5 | S93: 5 | T93: 118 | U93: 2 | W93: =_xlfn.XLOOKUP(A93,[1]CALCULO_VR!$D:$D,[1]CALCULO_VR!$J:$J) -> 80 | X93: =_xlfn.XLOOKUP(A93,[1]CALCULO_VR!$D:$D,[1]CALCULO_VR!$O:$O) -> -11.080035 | Y93: =_xlfn.XLOOKUP(A93,[1]CALCULO_VR!$D:$D,[1]CALCULO_VR!$P:$P) -> -64.076227
... A195: 2583658 | B195: ROBERTO CARLOS KARITIANA | C195: Candeias do Jamari | D195: 45477 | E195: 45477 | F195: 34042.861 | G195: 1 | H195: 1 | J195: 0 | Q195: 56.969413 | R195: 2 | S195: 2 | T195: 247 | U195: 4 | W195: =_xlfn.XLOOKUP(A195,[1]CALCULO_VR!$D:$D,[1]CALCULO_VR!$J:$J) -> 80 | X195: =_xlfn.XLOOKUP(A195,[1]CALCULO_VR!$D:$D,[1]CALCULO_VR!$O:$O) -> -9.291383 | Y195: =_xlfn.XLOOKUP(A195,[1]CALCULO_VR!$D:$D,[1]CALCULO_VR!$P:$P) -> -63.779025
A196: 2583906 | B196: ETIENNE MEIRA SILVEIRA | C196: Guajará-Mirim | D196: 45478 | E196: 45478 | F196: 34042.861 | G196: 1 | H196: 1 | J196: 0 | Q196: 21.698617 | R196: 1 | S196: 1 | T196: 225 | U196: 5 | V196: Selecionado | W196: =_xlfn.XLOOKUP(A196,[1]CALCULO_VR!$D:$D,[1]CALCULO_VR!$J:$J) -> 80 | X196: =_xlfn.XLOOKUP(A196,[1]CALCULO_VR!$D:$D,[1]CALCULO_VR!$O:$O) -> -10.960403 | Y196: =_xlfn.XLOOKUP(A196,[1]CALCULO_VR!$D:$D,[1]CALCULO_VR!$P:$P) -> -65.265543
A197: 2583907 | B197: JONAS CASTEDO MENDONCA | C197: Guajará-Mirim | D197: 45478 | E197: 45478 | F197: 34042.861 | G197: 1 | H197: 1 | J197: 0 | Q197: 22.861877 | R197: 1 | S197: 1 | T197: 225 | U197: 5 | W197: =_xlfn.XLOOKUP(A197,[1]CALCULO_VR!$D:$D,[1]CALCULO_VR!$J:$J) -> 80 | X197: =_xlfn.XLOOKUP(A197,[1]CALCULO_VR!$D:$D,[1]CALCULO_VR!$O:$O) -> -10.969067 | Y197: =_xlfn.XLOOKUP(A197,[1]CALCULO_VR!$D:$D,[1]CALCULO_VR!$P:$P) -> -65.258152
A198: 2583908 | B198: EVA RUIZ | C198: Guajará-Mirim | D198: 45478 | E198: 45478 | F198: 34042.861 | G198: 1 | H198: 1 | J198: 0 | Q198: 23.34699 | R198: 1 | S198: 1 | T198: 225 | U198: 5 | W198: =_xlfn.XLOOKUP(A198,[1]CALCULO_VR!$D:$D,[1]CALCULO_VR!$J:$J) -> 80 | X198: =_xlfn.XLOOKUP(A198,[1]CALCULO_VR!$D:$D,[1]CALCULO_VR!$O:$O) -> -10.972492 | Y198: =_xlfn.XLOOKUP(A198,[1]CALCULO_VR!$D:$D,[1]CALCULO_VR!$P:$P) -> -65.25459
A199: 2583909 | B199: JOCICLEI MACURAP | C199: Guajará-Mirim | D199: 45478 | E199: 45478 | F199: 34042.861 | G199: 1 | H199: 1 | J199: 0 | Q199: 140.98735 | R199: 5 | S199: 5 | T199: 118 | U199: 2 | W199: =_xlfn.XLOOKUP(A199,[1]CALCULO_VR!$D:$D,[1]CALCULO_VR!$J:$J) -> 80 | X199: =_xlfn.XLOOKUP(A199,[1]CALCULO_VR!$D:$D,[1]CALCULO_VR!$O:$O) -> -11.956762 | Y199: =_xlfn.XLOOKUP(A199,[1]CALCULO_VR!$D:$D,[1]CALCULO_VR!$P:$P) -> -64.858253
A200: 2583910 | B200: NILZETE ALVES ARUA | C200: Guajará-Mirim | D200: 45477 | E200: 45477 | F200: 34042.861 | G200: 1 | H200: 1 | J200: 0 | Q200: 140.3446 | R200: 5 | S200: 5 | T200: 118 | U200: 2 | W200: =_xlfn.XLOOKUP(A200,[1]CALCULO_VR!$D:$D,[1]CALCULO_VR!$J:$J) -> 80 | X200: =_xlfn.XLOOKUP(A200,[1]CALCULO_VR!$D:$D,[1]CALCULO_VR!$O:$O) -> -11.952523 | Y200: =_xlfn.XLOOKUP(A200,[1]CALCULO_VR!$D:$D,[1]CALCULO_VR!$P:$P) -> -64.86344
A201: 2583911 | B201: ANDRIEL ARUAK | C201: Guajará-Mirim | D201: 45477 | E201: 45477 | F201: 34042.861 | G201: 1 | H201: 1 | J201: 0 | Q201: 140.3748 | R201: 5 | S201: 5 | T201: 118 | U201: 2 | W201: =_xlfn.XLOOKUP(A201,[1]CALCULO_VR!$D:$D,[1]CALCULO_VR!$J:$J) -> 80 | X201: =_xlfn.XLOOKUP(A201,[1]CALCULO_VR!$D:$D,[1]CALCULO_VR!$O:$O) -> -11.952815 | Y201: =_xlfn.XLOOKUP(A201,[1]CALCULO_VR!$D:$D,[1]CALCULO_VR!$P:$P) -> -64.863443
A202: 2583912 | B202: JONAS JABOTI | C202: Guajará-Mirim | D202: 45477 | E202: 45477 | F202: 34042.861 | G202: 1 | H202: 1 | J202: 0 | Q202: 151.9773 | R202: 5 | S202: 5 | T202: 118 | U202: 2 | W202: =_xlfn.XLOOKUP(A202,[1]CALCULO_VR!$D:$D,[1]CALCULO_VR!$J:$J) -> 80 | X202: =_xlfn.XLOOKUP(A202,[1]CALCULO_VR!$D:$D,[1]CALCULO_VR!$O:$O) -> -12.035658 | Y202: =_xlfn.XLOOKUP(A202,[1]CALCULO_VR!$D:$D,[1]CALCULO_VR!$P:$P) -> -64.788028
A203: 2583913 | B203: VANGILENE JABOTI | C203: Guajará-Mirim | D203: 45477 | E203: 45477 | F203: 34042.861 | G203: 1 | H203: 1 | J203: 0 | Q203: 152.53799 | R203: 5 | S203: 5 | T203: 118 | U203: 2 | V203: Selecionado | W203: =_xlfn.XLOOKUP(A203,[1]CALCULO_VR!$D:$D,[1]CALCULO_VR!$J:$J) -> 80 | X203: =_xlfn.XLOOKUP(A203,[1]CALCULO_VR!$D:$D,[1]CALCULO_VR!$O:$O) -> -12.033205 | Y203: =_xlfn.XLOOKUP(A203,[1]CALCULO_VR!$D:$D,[1]CALCULO_VR!$P:$P) -> -64.768957
A204: 2583939 | B204: CASA DE APOIO ALDEIA PEDREIRA ANEXO | C204: Guajará-Mirim | D204: 45456 | E204: 45456 | F204: 34042.861 | G204: 1 | H204: 1 | J204: 0 | Q204: 130.05587 | R204: 5 | S204: 5 | T204: 118 | U204: 2 | W204: =_xlfn.XLOOKUP(A204,[1]CALCULO_VR!$D:$D,[1]CALCULO_VR!$J:$J) -> 80 | X204: =_xlfn.XLOOKUP(A204,[1]CALCULO_VR!$D:$D,[1]CALCULO_VR!$O:$O) -> -11.152277 | Y204: =_xlfn.XLOOKUP(A204,[1]CALCULO_VR!$D:$D,[1]CALCULO_VR!$P:$P) -> -64.196655
A205: 2583649 | B205: CLAUDENIR APARECIDO FERNANDES | C205: Guajará-Mirim | D205: 45474 | E205: 45474 | F205: 34042.861 | G205: 1 | H205: 1 | J205: 0 | Q205: 121.9803 | R205: 4 | S205: 4 | T205: 111 | U205: 2 | W205: =_xlfn.XLOOKUP(A205,[1]CALCULO_VR!$D:$D,[1]CALCULO_VR!$J:$J) -> 80 | X205: =_xlfn.XLOOKUP(A205,[1]CALCULO_VR!$D:$D,[1]CALCULO_VR!$O:$O) -> -11.820325 | Y205: =_xlfn.XLOOKUP(A205,[1]CALCULO_VR!$D:$D,[1]CALCULO_VR!$P:$P) -> -64.988263
A206: 2583919 | B206: ESCOLA KITY PYPYDNIPA | C206: Candeias do Jamari | D206: 45476 | E206: 45476 | F206: 34042.861 | G206: 1 | H206: 1 | J206: 0 | Q206: 56.933152 | R206: 2 | S206: 2 | T206: 247 | U206: 4 | W206: =_xlfn.XLOOKUP(A206,[1]CALCULO_VR!$D:$D,[1]CALCULO_VR!$J:$J) -> 80 | X206: =_xlfn.XLOOKUP(A206,[1]CALCULO_VR!$D:$D,[1]CALCULO_VR!$O:$O) -> -9.291115 | Y206: =_xlfn.XLOOKUP(A206,[1]CALCULO_VR!$D:$D,[1]CALCULO_VR!$P:$P) -> -63.778617
A207: 2585884 | B207: ESCOLA AWO CAMIP ORO MON | C207: Nova Mamoré | D207: 45464 | E207: 45464 | F207: 34042.861 | G207: 1 | H207: 1 | J207: 0 | Q207: 26.550086 | R207: 1 | S207: 1 | T207: 225 | U207: 5 | W207: =_xlfn.XLOOKUP(A207,[1]CALCULO_VR!$D:$D,[1]CALCULO_VR!$J:$J) -> 80 | X207: =_xlfn.XLOOKUP(A207,[1]CALCULO_VR!$D:$D,[1]CALCULO_VR!$O:$O) -> -10.32571 | Y207: =_xlfn.XLOOKUP(A207,[1]CALCULO_VR!$D:$D,[1]CALCULO_VR!$P:$P) -> -65.10273
A208: 2585883 | B208: ROMILTO ORO MON | C208: Nova Mamoré | D208: 45464 | E208: 45464 | F208: 34042.861 | G208: 1 | H208: 1 | J208: 0 | Q208: 26.502299 | R208: 1 | S208: 1 | T208: 225 | U208: 5 | W208: =_xlfn.XLOOKUP(A208,[1]CALCULO_VR!$D:$D,[1]CALCULO_VR!$J:$J) -> 80 | X208: =_xlfn.XLOOKUP(A208,[1]CALCULO_VR!$D:$D,[1]CALCULO_VR!$O:$O) -> -10.3258 | Y208: =_xlfn.XLOOKUP(A208,[1]CALCULO_VR!$D:$D,[1]CALCULO_VR!$P:$P) -> -65.103163
A209: 2595013 | B209: JOAO CINTA LARGA | C209: Espigão D'Oeste | D209: 45490 | E209: 45490 | F209: 34042.861 | G209: 1 | H209: 1 | J209: 0 | Q209: 56.825988 | R209: 2 | S209: 2 | T209: 247 | U209: 4 | W209: =_xlfn.XLOOKUP(A209,[1]CALCULO_VR!$D:$D,[1]CALCULO_VR!$J:$J) -> 80 | X209: =_xlfn.XLOOKUP(A209,[1]CALCULO_VR!$D:$D,[1]CALCULO_VR!$O:$O) -> -11.08612 | Y209: =_xlfn.XLOOKUP(A209,[1]CALCULO_VR!$D:$D,[1]CALCULO_VR!$P:$P) -> -60.759332
A210: 2595015 | B210: CLAUDINETE MACURAP | C210: Guajará-Mirim | D210: 45490 | E210: 45490 | F210: 34042.861 | G210: 1 | H210: 1 | J210: 0 | Q210: 140.89148 | R210: 5 | S210: 5 | T210: 118 | U210: 2 | W210: =_xlfn.XLOOKUP(A210,[1]CALCULO_VR!$D:$D,[1]CALCULO_VR!$J:$J) -> 80 | X210: =_xlfn.XLOOKUP(A210,[1]CALCULO_VR!$D:$D,[1]CALCULO_VR!$O:$O) -> -11.956032 | Y210: =_xlfn.XLOOKUP(A210,[1]CALCULO_VR!$D:$D,[1]CALCULO_VR!$P:$P) -> -64.858767
A211: 2595016 | B211: KERLI APARECIDO MOREIRA | C211: Guajará-Mirim | D211: 45488 | E211: 45488 | F211: 34042.861 | G211: 1 | H211: 1 | J211: 0 | Q211: 15.189853 | R211: 1 | S211: 1 | T211: 225 | U211: 5 | W211: =_xlfn.XLOOKUP(A211,[1]CALCULO_VR!$D:$D,[1]CALCULO_VR!$J:$J) -> 80 | X211: =_xlfn.XLOOKUP(A211,[1]CALCULO_VR!$D:$D,[1]CALCULO_VR!$O:$O) -> -10.89692 | Y211: =_xlfn.XLOOKUP(A211,[1]CALCULO_VR!$D:$D,[1]CALCULO_VR!$P:$P) -> -65.263518
A212: 2595017 | B212: MIRIAN MACURAP | C212: Guajará-Mirim | D212: 45490 | E212: 45490 | F212: 34042.861 | G212: 1 | H212: 1 | J212: 0 | Q212: 150.5905 | R212: 5 | S212: 5 | T212: 118 | U212: 2 | W212: =_xlfn.XLOOKUP(A212,[1]CALCULO_VR!$D:$D,[1]CALCULO_VR!$J:$J) -> 80 | X212: =_xlfn.XLOOKUP(A212,[1]CALCULO_VR!$D:$D,[1]CALCULO_VR!$O:$O) -> -12.029373 | Y212: =_xlfn.XLOOKUP(A212,[1]CALCULO_VR!$D:$D,[1]CALCULO_VR!$P:$P) -> -64.805922
A213: 2595018 | B213: LUANA JABOTI | C213: Guajará-Mirim | D213: 45490 | E213: 45490 | F213: 34042.861 | G213: 1 | H213: 1 | J213: 0 | Q213: 151.3799 | R213: 5 | S213: 5 | T213: 118 | U213: 2 | W213: =_xlfn.XLOOKUP(A213,[1]CALCULO_VR!$D:$D,[1]CALCULO_VR!$J:$J) -> 80 | X213: =_xlfn.XLOOKUP(A213,[1]CALCULO_VR!$D:$D,[1]CALCULO_VR!$O:$O) -> -12.03332 | Y213: =_xlfn.XLOOKUP(A213,[1]CALCULO_VR!$D:$D,[1]CALCULO_VR!$P:$P) -> -64.796607
A214: 2595019 | B214: CORINA AMARAL COSTA | C214: Guajará-Mirim | D214: 45491 | E214: 45491 | F214: 34042.861 | G214: 1 | H214: 1 | J214: 0 | Q214: 96.112194 | R214: 3 | S214: 3 | T214: 161 | U214: 2 | W214: =_xlfn.XLOOKUP(A214,[1]CALCULO_VR!$D:$D,[1]CALCULO_VR!$J:$J) -> 80 | X214: =_xlfn.XLOOKUP(A214,[1]CALCULO_VR!$D:$D,[1]CALCULO_VR!$O:$O) -> -11.629382 | Y214: =_xlfn.XLOOKUP(A214,[1]CALCULO_VR!$D:$D,[1]CALCULO_VR!$P:$P) -> -65.198115
A215: 2595020 | B215: AWANDA ASSOCIACAO DO POVOS MAKURAP DO RIO GUAPORE | C215: Guajará-Mirim | D215: 45488 | E215: 45488 | F215: 34042.861 | G215: 1 | H215: 1 | J215: 0 | Q215: 148.09356 | R215: 5 | S215: 5 | T215: 118 | U215: 2 | W215: =_xlfn.XLOOKUP(A215,[1]CALCULO_VR!$D:$D,[1]CALCULO_VR!$J:$J) -> 80 | X215: =_xlfn.XLOOKUP(A215,[1]CALCULO_VR!$D:$D,[1]CALCULO_VR!$O:$O) -> -12.013415 | Y215: =_xlfn.XLOOKUP(A215,[1]CALCULO_VR!$D:$D,[1]CALCULO_VR!$P:$P) -> -64.826958
... A226: 2595031 | B226: JOAO CINTA LARGA | C226: Vilhena | D226: 45490 | E226: 45490 | F226: 34042.861 | G226: 1 | H226: 1 | J226: 0 | Q226: 127.35628 | R226: 5 | S226: 5 | T226: 118 | U226: 2 | W226: =_xlfn.XLOOKUP(A226,[1]CALCULO_VR!$D:$D,[1]CALCULO_VR!$J:$J) -> 80 | X226: =_xlfn.XLOOKUP(A226,[1]CALCULO_VR!$D:$D,[1]CALCULO_VR!$O:$O) -> -11.637263 | Y226: =_xlfn.XLOOKUP(A226,[1]CALCULO_VR!$D:$D,[1]CALCULO_VR!$P:$P) -> -60.450162
A227: 2595032 | B227: IZAQUE CINTA LARGA | C227: Espigão D'Oeste | D227: 45489 | E227: 45489 | F227: 34042.861 | G227: 1 | H227: 1 | J227: 0 | Q227: 56.852514 | R227: 2 | S227: 2 | T227: 247 | U227: 4 | V227: Selecionado | W227: =_xlfn.XLOOKUP(A227,[1]CALCULO_VR!$D:$D,[1]CALCULO_VR!$J:$J) -> 80 | X227: =_xlfn.XLOOKUP(A227,[1]CALCULO_VR!$D:$D,[1]CALCULO_VR!$O:$O) -> -11.085925 | Y227: =_xlfn.XLOOKUP(A227,[1]CALCULO_VR!$D:$D,[1]CALCULO_VR!$P:$P) -> -60.75919
A228: 2595033 | B228: SHAYENE CINTA LARGA | C228: Espigão D'Oeste | D228: 45490 | E228: 45490 | F228: 34042.861 | G228: 1 | H228: 1 | J228: 0 | Q228: 57.999068 | R228: 2 | S228: 2 | T228: 247 | U228: 4 | W228: =_xlfn.XLOOKUP(A228,[1]CALCULO_VR!$D:$D,[1]CALCULO_VR!$J:$J) -> 80 | X228: =_xlfn.XLOOKUP(A228,[1]CALCULO_VR!$D:$D,[1]CALCULO_VR!$O:$O) -> -11.081895 | Y228: =_xlfn.XLOOKUP(A228,[1]CALCULO_VR!$D:$D,[1]CALCULO_VR!$P:$P) -> -60.745473
A229: 2595034 | B229: MANOEL CINTA LARGA | C229: Espigão D'Oeste | D229: 45489 | E229: 45489 | F229: 34042.861 | G229: 1 | H229: 1 | J229: 0 | Q229: 56.802141 | R229: 2 | S229: 2 | T229: 247 | U229: 4 | W229: =_xlfn.XLOOKUP(A229,[1]CALCULO_VR!$D:$D,[1]CALCULO_VR!$J:$J) -> 80 | X229: =_xlfn.XLOOKUP(A229,[1]CALCULO_VR!$D:$D,[1]CALCULO_VR!$O:$O) -> -11.086345 | Y229: =_xlfn.XLOOKUP(A229,[1]CALCULO_VR!$D:$D,[1]CALCULO_VR!$P:$P) -> -60.759372
A230: 2595035 | B230: CARMEM VACA CORTEZ PAES | C230: Guajará-Mirim | D230: 45488 | E230: 45488 | F230: 34042.861 | G230: 1 | H230: 1 | J230: 0 | Q230: 20.806966 | R230: 1 | S230: 1 | T230: 225 | U230: 5 | W230: =_xlfn.XLOOKUP(A230,[1]CALCULO_VR!$D:$D,[1]CALCULO_VR!$J:$J) -> 80 | X230: =_xlfn.XLOOKUP(A230,[1]CALCULO_VR!$D:$D,[1]CALCULO_VR!$O:$O) -> -10.952562 | Y230: =_xlfn.XLOOKUP(A230,[1]CALCULO_VR!$D:$D,[1]CALCULO_VR!$P:$P) -> -65.267363
A231: 2595037 | B231: VAGNER MACURAP | C231: Guajará-Mirim | D231: 45490 | E231: 45490 | F231: 34042.861 | G231: 1 | H231: 1 | J231: 0 | Q231: 140.87209 | R231: 5 | S231: 5 | T231: 118 | U231: 2 | W231: =_xlfn.XLOOKUP(A231,[1]CALCULO_VR!$D:$D,[1]CALCULO_VR!$J:$J) -> 80 | X231: =_xlfn.XLOOKUP(A231,[1]CALCULO_VR!$D:$D,[1]CALCULO_VR!$O:$O) -> -11.955923 | Y231: =_xlfn.XLOOKUP(A231,[1]CALCULO_VR!$D:$D,[1]CALCULO_VR!$P:$P) -> -64.858973
A232: 2595038 | B232: HENRIQUE CINTA LARGA | C232: Vilhena | D232: 45489 | E232: 45489 | F232: 34042.861 | G232: 1 | H232: 1 | J232: 0 | Q232: 127.04916 | R232: 5 | S232: 5 | T232: 118 | U232: 2 | W232: =_xlfn.XLOOKUP(A232,[1]CALCULO_VR!$D:$D,[1]CALCULO_VR!$J:$J) -> 80 | X232: =_xlfn.XLOOKUP(A232,[1]CALCULO_VR!$D:$D,[1]CALCULO_VR!$O:$O) -> -11.63675 | Y232: =_xlfn.XLOOKUP(A232,[1]CALCULO_VR!$D:$D,[1]CALCULO_VR!$P:$P) -> -60.437382
A233: 2595039 | B233: IGOR CINTA LARGA | C233: Vilhena | D233: 45489 | E233: 45489 | F233: 34042.861 | G233: 1 | H233: 1 | J233: 0 | Q233: 127.21786 | R233: 5 | S233: 5 | T233: 118 | U233: 2 | W233: =_xlfn.XLOOKUP(A233,[1]CALCULO_VR!$D:$D,[1]CALCULO_VR!$J:$J) -> 80 | X233: =_xlfn.XLOOKUP(A233,[1]CALCULO_VR!$D:$D,[1]CALCULO_VR!$O:$O) -> -11.63541 | Y233: =_xlfn.XLOOKUP(A233,[1]CALCULO_VR!$D:$D,[1]CALCULO_VR!$P:$P) -> -60.438268
A234: 2595040 | B234: ISABEL CRISTINA JABUTI | C234: Guajará-Mirim | D234: 45489 | E234: 45489 | F234: 34042.861 | G234: 1 | H234: 1 | J234: 0 | Q234: 144.74607 | R234: 5 | S234: 5 | T234: 118 | U234: 2 | W234: =_xlfn.XLOOKUP(A234,[1]CALCULO_VR!$D:$D,[1]CALCULO_VR!$J:$J) -> 80 | X234: =_xlfn.XLOOKUP(A234,[1]CALCULO_VR!$D:$D,[1]CALCULO_VR!$O:$O) -> -11.981077 | Y234: =_xlfn.XLOOKUP(A234,[1]CALCULO_VR!$D:$D,[1]CALCULO_VR!$P:$P) -> -64.827155
A235: 2595041 | B235: DENILSON PAHGAH GAVIAO | C235: Ji-Paraná | D235: 45496 | E235: 45496 | F235: 34042.861 | G235: 1 | H235: 1 | J235: 0 | Q235: 42.604293 | R235: 1 | S235: 1 | T235: 225 | U235: 5 | W235: =_xlfn.XLOOKUP(A235,[1]CALCULO_VR!$D:$D,[1]CALCULO_VR!$J:$J) -> 80 | X235: =_xlfn.XLOOKUP(A235,[1]CALCULO_VR!$D:$D,[1]CALCULO_VR!$O:$O) -> -10.730455 | Y235: =_xlfn.XLOOKUP(A235,[1]CALCULO_VR!$D:$D,[1]CALCULO_VR!$P:$P) -> -61.586858
A236: 2595062 | B236: JANAINA XIVIR VERE ARARA | C236: Ji-Paraná | D236: 45496 | E236: 45496 | F236: 34042.861 | G236: 1 | H236: 1 | J236: 0 | Q236: 42.514462 | R236: 1 | S236: 1 | T236: 225 | U236: 5 | W236: =_xlfn.XLOOKUP(A236,[1]CALCULO_VR!$D:$D,[1]CALCULO_VR!$J:$J) -> 80 | X236: =_xlfn.XLOOKUP(A236,[1]CALCULO_VR!$D:$D,[1]CALCULO_VR!$O:$O) -> -10.729362 | Y236: =_xlfn.XLOOKUP(A236,[1]CALCULO_VR!$D:$D,[1]CALCULO_VR!$P:$P) -> -61.588237
A237: 2595063 | B237: ANDRE XIPI POHJ ARARA | C237: Ji-Paraná | D237: 45496 | E237: 45496 | F237: 34042.861 | G237: 1 | H237: 1 | J237: 0 | Q237: 42.472704 | R237: 1 | S237: 1 | T237: 225 | U237: 5 | W237: =_xlfn.XLOOKUP(A237,[1]CALCULO_VR!$D:$D,[1]CALCULO_VR!$J:$J) -> 80 | X237: =_xlfn.XLOOKUP(A237,[1]CALCULO_VR!$D:$D,[1]CALCULO_VR!$O:$O) -> -10.728922 | Y237: =_xlfn.XLOOKUP(A237,[1]CALCULO_VR!$D:$D,[1]CALCULO_VR!$P:$P) -> -61.58885
A238: 2595064 | B238: MIZAEL MIORE KAMPE | C238: São Francisco do Guaporé | D238: 45495 | E238: 45495 | F238: 34042.861 | G238: 1 | H238: 1 | J238: 0 | Q238: 90.037263 | R238: 3 | S238: 3 | T238: 161 | U238: 2 | W238: =_xlfn.XLOOKUP(A238,[1]CALCULO_VR!$D:$D,[1]CALCULO_VR!$J:$J) -> 80 | X238: =_xlfn.XLOOKUP(A238,[1]CALCULO_VR!$D:$D,[1]CALCULO_VR!$O:$O) -> -12.348553 | Y238: =_xlfn.XLOOKUP(A238,[1]CALCULO_VR!$D:$D,[1]CALCULO_VR!$P:$P) -> -62.795328
A239: 2595065 | B239: ROZILEIA KASO UHR GAVIAO | C239: Ji-Paraná | D239: 45496 | E239: 45496 | F239: 34042.861 | G239: 1 | H239: 1 | J239: 0 | Q239: 42.521868 | R239: 1 | S239: 1 | T239: 225 | U239: 5 | W239: =_xlfn.XLOOKUP(A239,[1]CALCULO_VR!$D:$D,[1]CALCULO_VR!$J:$J) -> 80 | X239: =_xlfn.XLOOKUP(A239,[1]CALCULO_VR!$D:$D,[1]CALCULO_VR!$O:$O) -> -10.728982 | Y239: =_xlfn.XLOOKUP(A239,[1]CALCULO_VR!$D:$D,[1]CALCULO_VR!$P:$P) -> -61.588332
... A390: 2595259 | B390: FRANCISCO BATISTA DA SILVA | C390: Ji-Paraná | D390: 45505 | E390: 45505 | F390: 34042.861 | G390: 1 | H390: 1 | J390: 0 | Q390: 42.762165 | R390: 1 | S390: 1 | T390: 225 | U390: 5 | W390: =_xlfn.XLOOKUP(A390,[1]CALCULO_VR!$D:$D,[1]CALCULO_VR!$J:$J) -> 80 | X390: =_xlfn.XLOOKUP(A390,[1]CALCULO_VR!$D:$D,[1]CALCULO_VR!$O:$O) -> -10.631605 | Y390: =_xlfn.XLOOKUP(A390,[1]CALCULO_VR!$D:$D,[1]CALCULO_VR!$P:$P) -> -61.648035
A391: 2595260 | B391: JOSE ROBERTO FERREIRA | C391: Pimenta Bueno | D391: 45506 | E391: 45506 | F391: 34042.861 | G391: 1 | H391: 1 | J391: 0 | Q391: 106.58438 | R391: 4 | S391: 4 | T391: 111 | U391: 2 | V391: Selecionado | W391: =_xlfn.XLOOKUP(A391,[1]CALCULO_VR!$D:$D,[1]CALCULO_VR!$J:$J) -> 80 | X391: =_xlfn.XLOOKUP(A391,[1]CALCULO_VR!$D:$D,[1]CALCULO_VR!$O:$O) -> -12.239007 | Y391: =_xlfn.XLOOKUP(A391,[1]CALCULO_VR!$D:$D,[1]CALCULO_VR!$P:$P) -> -60.389548
A392: 2595261 | B392: MARA CRISTINA VIEIRA DA ROCHA | C392: Pimenta Bueno | D392: 45506 | E392: 45506 | F392: 34042.861 | G392: 1 | H392: 1 | J392: 0 | Q392: 106.55364 | R392: 4 | S392: 4 | T392: 111 | U392: 2 | W392: =_xlfn.XLOOKUP(A392,[1]CALCULO_VR!$D:$D,[1]CALCULO_VR!$J:$J) -> 80 | X392: =_xlfn.XLOOKUP(A392,[1]CALCULO_VR!$D:$D,[1]CALCULO_VR!$O:$O) -> -12.241908 | Y392: =_xlfn.XLOOKUP(A392,[1]CALCULO_VR!$D:$D,[1]CALCULO_VR!$P:$P) -> -60.392045
A393: 2595262 | B393: CARLOS ALBERTO VIEIRA DA ROCHA | C393: Pimenta Bueno | D393: 45506 | E393: 45506 | F393: 34042.861 | G393: 1 | H393: 1 | J393: 0 | Q393: 106.52973 | R393: 4 | S393: 4 | T393: 111 | U393: 2 | W393: =_xlfn.XLOOKUP(A393,[1]CALCULO_VR!$D:$D,[1]CALCULO_VR!$J:$J) -> 80 | X393: =_xlfn.XLOOKUP(A393,[1]CALCULO_VR!$D:$D,[1]CALCULO_VR!$O:$O) -> -12.241892 | Y393: =_xlfn.XLOOKUP(A393,[1]CALCULO_VR!$D:$D,[1]CALCULO_VR!$P:$P) -> -60.392305
A394: 2595263 | B394: MARIA LUCIANA ORTIS BABICZ | C394: Pimenta Bueno | D394: 45506 | E394: 45506 | F394: 34042.861 | G394: 1 | H394: 1 | J394: 0 | Q394: 105.90742 | R394: 4 | S394: 4 | T394: 111 | U394: 2 | W394: =_xlfn.XLOOKUP(A394,[1]CALCULO_VR!$D:$D,[1]CALCULO_VR!$J:$J) -> 80 | X394: =_xlfn.XLOOKUP(A394,[1]CALCULO_VR!$D:$D,[1]CALCULO_VR!$O:$O) -> -12.24236 | Y394: =_xlfn.XLOOKUP(A394,[1]CALCULO_VR!$D:$D,[1]CALCULO_VR!$P:$P) -> -60.399747
A395: 2595264 | B395: ANTONIO PAIM CHIMENES | C395: Pimenta Bueno | D395: 45506 | E395: 45506 | F395: 34042.861 | G395: 1 | H395: 1 | J395: 0 | Q395: 105.0836 | R395: 4 | S395: 4 | T395: 111 | U395: 2 | W395: =_xlfn.XLOOKUP(A395,[1]CALCULO_VR!$D:$D,[1]CALCULO_VR!$J:$J) -> 80 | X395: =_xlfn.XLOOKUP(A395,[1]CALCULO_VR!$D:$D,[1]CALCULO_VR!$O:$O) -> -12.230957 | Y395: =_xlfn.XLOOKUP(A395,[1]CALCULO_VR!$D:$D,[1]CALCULO_VR!$P:$P) -> -60.400635
A396: 2595266 | B396: HELIO EBASSARU KAMPE | C396: São Francisco do Guaporé | D396: 45503 | E396: 45503 | F396: 34042.861 | G396: 1 | H396: 1 | J396: 0 | Q396: 87.57819 | R396: 3 | S396: 3 | T396: 161 | U396: 2 | W396: =_xlfn.XLOOKUP(A396,[1]CALCULO_VR!$D:$D,[1]CALCULO_VR!$J:$J) -> 80 | X396: =_xlfn.XLOOKUP(A396,[1]CALCULO_VR!$D:$D,[1]CALCULO_VR!$O:$O) -> -12.336905 | Y396: =_xlfn.XLOOKUP(A396,[1]CALCULO_VR!$D:$D,[1]CALCULO_VR!$P:$P) -> -62.81505
A397: 2595267 | B397: MARLON BRENO LIMA PEREIRA | C397: Ji-Paraná | D397: 45506 | E397: 45506 | F397: 34042.861 | G397: 1 | H397: 1 | J397: 0 | Q397: 41.00826 | R397: 1 | S397: 1 | T397: 225 | U397: 5 | W397: =_xlfn.XLOOKUP(A397,[1]CALCULO_VR!$D:$D,[1]CALCULO_VR!$J:$J) -> 80 | X397: =_xlfn.XLOOKUP(A397,[1]CALCULO_VR!$D:$D,[1]CALCULO_VR!$O:$O) -> -10.64612 | Y397: =_xlfn.XLOOKUP(A397,[1]CALCULO_VR!$D:$D,[1]CALCULO_VR!$P:$P) -> -61.656562
A398: 2595268 | B398: LIRDIMAR AIT AIT TUPARI | C398: São Francisco do Guaporé | D398: 45506 | E398: 45506 | F398: 34042.861 | G398: 1 | H398: 1 | J398: 0 | Q398: 70.984836 | R398: 2 | S398: 2 | T398: 247 | U398: 4 | W398: =_xlfn.XLOOKUP(A398,[1]CALCULO_VR!$D:$D,[1]CALCULO_VR!$J:$J) -> 80 | X398: =_xlfn.XLOOKUP(A398,[1]CALCULO_VR!$D:$D,[1]CALCULO_VR!$O:$O) -> -12.413707 | Y398: =_xlfn.XLOOKUP(A398,[1]CALCULO_VR!$D:$D,[1]CALCULO_VR!$P:$P) -> -63.024503
A399: 2595270 | B399: VALDEMAR CINTA LARGA | C399: Espigão D'Oeste | D399: 45506 | E399: 45506 | F399: 34042.861 | G399: 1 | H399: 1 | J399: 0 | Q399: 44.27651 | R399: 1 | S399: 1 | T399: 225 | U399: 5 | W399: =_xlfn.XLOOKUP(A399,[1]CALCULO_VR!$D:$D,[1]CALCULO_VR!$J:$J) -> 80 | X399: =_xlfn.XLOOKUP(A399,[1]CALCULO_VR!$D:$D,[1]CALCULO_VR!$O:$O) -> -11.348132 | Y399: =_xlfn.XLOOKUP(A399,[1]CALCULO_VR!$D:$D,[1]CALCULO_VR!$P:$P) -> -60.658013
A400: 2595271 | B400: ANDRE CINTA LARGA | C400: Espigão D'Oeste | D400: 45506 | E400: 45506 | F400: 34042.861 | G400: 1 | H400: 1 | J400: 0 | Q400: 48.227422 | R400: 2 | S400: 2 | T400: 247 | U400: 4 | W400: =_xlfn.XLOOKUP(A400,[1]CALCULO_VR!$D:$D,[1]CALCULO_VR!$J:$J) -> 80 | X400: =_xlfn.XLOOKUP(A400,[1]CALCULO_VR!$D:$D,[1]CALCULO_VR!$O:$O) -> -11.331922 | Y400: =_xlfn.XLOOKUP(A400,[1]CALCULO_VR!$D:$D,[1]CALCULO_VR!$P:$P) -> -60.625765
A401: 2595273 | B401: JANAINA DE OLIVEIRA CHIMENES | C401: Pimenta Bueno | D401: 45506 | E401: 45506 | F401: 34042.861 | G401: 1 | H401: 1 | J401: 0 | Q401: 106.57713 | R401: 4 | S401: 4 | T401: 111 | U401: 2 | W401: =_xlfn.XLOOKUP(A401,[1]CALCULO_VR!$D:$D,[1]CALCULO_VR!$J:$J) -> 80 | X401: =_xlfn.XLOOKUP(A401,[1]CALCULO_VR!$D:$D,[1]CALCULO_VR!$O:$O) -> -12.244683 | Y401: =_xlfn.XLOOKUP(A401,[1]CALCULO_VR!$D:$D,[1]CALCULO_VR!$P:$P) -> -60.393848
A402: 2595274 | B402: EVA KOIROKA TUPARI | C402: São Francisco do Guaporé | D402: 45507 | E402: 45507 | F402: 34042.861 | G402: 1 | H402: 1 | J402: 0 | Q402: 101.9684 | R402: 4 | S402: 4 | T402: 111 | U402: 2 | W402: =_xlfn.XLOOKUP(A402,[1]CALCULO_VR!$D:$D,[1]CALCULO_VR!$J:$J) -> 80 | X402: =_xlfn.XLOOKUP(A402,[1]CALCULO_VR!$D:$D,[1]CALCULO_VR!$O:$O) -> -12.236862 | Y402: =_xlfn.XLOOKUP(A402,[1]CALCULO_VR!$D:$D,[1]CALCULO_VR!$P:$P) -> -62.649683
A403: 2595275 | B403: JOSIELEN LIRA GUIMARAES | C403: Ji-Paraná | D403: 45507 | E403: 45507 | F403: 34042.861 | G403: 1 | H403: 1 | J403: 0 | Q403: 40.904716 | R403: 1 | S403: 1 | T403: 225 | U403: 5 | W403: =_xlfn.XLOOKUP(A403,[1]CALCULO_VR!$D:$D,[1]CALCULO_VR!$J:$J) -> 80 | X403: =_xlfn.XLOOKUP(A403,[1]CALCULO_VR!$D:$D,[1]CALCULO_VR!$O:$O) -> -10.654008 | Y403: =_xlfn.XLOOKUP(A403,[1]CALCULO_VR!$D:$D,[1]CALCULO_VR!$P:$P) -> -61.651267
... A481: 2614645 | B481: CLEIDENICE GONCALVES DO PRADO | C481: Pimenta Bueno | D481: 45529 | E481: 45529 | F481: 34042.861 | G481: 1 | H481: 1 | J481: 0 | Q481: 112.94621 | R481: 4 | S481: 4 | T481: 111 | U481: 2 | W481: =_xlfn.XLOOKUP(A481,[1]CALCULO_VR!$D:$D,[1]CALCULO_VR!$J:$J) -> 80 | X481: =_xlfn.XLOOKUP(A481,[1]CALCULO_VR!$D:$D,[1]CALCULO_VR!$O:$O) -> -12.24958 | Y481: =_xlfn.XLOOKUP(A481,[1]CALCULO_VR!$D:$D,[1]CALCULO_VR!$P:$P) -> -60.325672
A482: 2614646 | B482: ARNALDO XISAH KULIHJA GAVIAO | C482: Ji-Paraná | D482: 45527 | E482: 45527 | F482: 34042.861 | G482: 1 | H482: 1 | J482: 0 | Q482: 58.991474 | R482: 2 | S482: 2 | T482: 247 | U482: 4 | V482: Selecionado | W482: =_xlfn.XLOOKUP(A482,[1]CALCULO_VR!$D:$D,[1]CALCULO_VR!$J:$J) -> 80 | X482: =_xlfn.XLOOKUP(A482,[1]CALCULO_VR!$D:$D,[1]CALCULO_VR!$O:$O) -> -10.435408 | Y482: =_xlfn.XLOOKUP(A482,[1]CALCULO_VR!$D:$D,[1]CALCULO_VR!$P:$P) -> -61.653773
A483: 2629566 | B483: DENILSON PISSINATTI DA SILVA | C483: Cujubim | D483: 45525 | E483: 45525 | F483: 34042.861 | G483: 1 | H483: 1 | J483: 0 | Q483: 58.144592 | R483: 2 | S483: 2 | T483: 247 | U483: 4 | W483: =_xlfn.XLOOKUP(A483,[1]CALCULO_VR!$D:$D,[1]CALCULO_VR!$J:$J) -> 80 | X483: =_xlfn.XLOOKUP(A483,[1]CALCULO_VR!$D:$D,[1]CALCULO_VR!$O:$O) -> -8.90096 | Y483: =_xlfn.XLOOKUP(A483,[1]CALCULO_VR!$D:$D,[1]CALCULO_VR!$P:$P) -> -62.370697
A484: 2614647 | B484: CELIO ANTONIO AKWAT KAMPE | C484: São Francisco do Guaporé | D484: 45498 | E484: 45498 | F484: 34042.861 | G484: 1 | H484: 1 | J484: 0 | Q484: 87.482596 | R484: 3 | S484: 3 | T484: 161 | U484: 2 | W484: =_xlfn.XLOOKUP(A484,[1]CALCULO_VR!$D:$D,[1]CALCULO_VR!$J:$J) -> 80 | X484: =_xlfn.XLOOKUP(A484,[1]CALCULO_VR!$D:$D,[1]CALCULO_VR!$O:$O) -> -12.33596 | Y484: =_xlfn.XLOOKUP(A484,[1]CALCULO_VR!$D:$D,[1]CALCULO_VR!$P:$P) -> -62.815632
A485: 2614648 | B485: VALDIR CHEREMBOMBAL GAVIAO | C485: Ji-Paraná | D485: 45527 | E485: 45527 | F485: 34042.861 | G485: 1 | H485: 1 | J485: 0 | Q485: 59.096804 | R485: 2 | S485: 2 | T485: 247 | U485: 4 | W485: =_xlfn.XLOOKUP(A485,[1]CALCULO_VR!$D:$D,[1]CALCULO_VR!$J:$J) -> 80 | X485: =_xlfn.XLOOKUP(A485,[1]CALCULO_VR!$D:$D,[1]CALCULO_VR!$O:$O) -> -10.434537 | Y485: =_xlfn.XLOOKUP(A485,[1]CALCULO_VR!$D:$D,[1]CALCULO_VR!$P:$P) -> -61.65337
A486: 2614649 | B486: MAYCON MADARABAH GAVIAO | C486: Ji-Paraná | D486: 45527 | E486: 45527 | F486: 34042.861 | G486: 1 | H486: 1 | J486: 0 | Q486: 59.059962 | R486: 2 | S486: 2 | T486: 247 | U486: 4 | W486: =_xlfn.XLOOKUP(A486,[1]CALCULO_VR!$D:$D,[1]CALCULO_VR!$J:$J) -> 80 | X486: =_xlfn.XLOOKUP(A486,[1]CALCULO_VR!$D:$D,[1]CALCULO_VR!$O:$O) -> -10.43469 | Y486: =_xlfn.XLOOKUP(A486,[1]CALCULO_VR!$D:$D,[1]CALCULO_VR!$P:$P) -> -61.653752
A487: 2614650 | B487: JOSIAS TEIXEIRA ERVILHA | C487: Vilhena | D487: 45527 | E487: 45527 | F487: 34042.861 | G487: 1 | H487: 1 | J487: 0 | Q487: 55.934895 | R487: 2 | S487: 2 | T487: 247 | U487: 4 | W487: =_xlfn.XLOOKUP(A487,[1]CALCULO_VR!$D:$D,[1]CALCULO_VR!$J:$J) -> 80 | X487: =_xlfn.XLOOKUP(A487,[1]CALCULO_VR!$D:$D,[1]CALCULO_VR!$O:$O) -> -12.263413 | Y487: =_xlfn.XLOOKUP(A487,[1]CALCULO_VR!$D:$D,[1]CALCULO_VR!$P:$P) -> -60.29923
A488: 2614651 | B488: GEUZALETE LORES ROSA DE SOUZA | C488: Vilhena | D488: 45527 | E488: 45527 | F488: 34042.861 | G488: 1 | H488: 1 | J488: 0 | Q488: 56.399552 | R488: 2 | S488: 2 | T488: 247 | U488: 4 | W488: =_xlfn.XLOOKUP(A488,[1]CALCULO_VR!$D:$D,[1]CALCULO_VR!$J:$J) -> 80 | X488: =_xlfn.XLOOKUP(A488,[1]CALCULO_VR!$D:$D,[1]CALCULO_VR!$O:$O) -> -12.262435 | Y488: =_xlfn.XLOOKUP(A488,[1]CALCULO_VR!$D:$D,[1]CALCULO_VR!$P:$P) -> -60.309623
A489: 2614652 | B489: MILTON FERREIRA MARTINELLI JUNIOR | C489: Vilhena | D489: 45527 | E489: 45527 | F489: 34042.861 | G489: 1 | H489: 1 | J489: 0 | Q489: 56.628759 | R489: 2 | S489: 2 | T489: 247 | U489: 4 | W489: =_xlfn.XLOOKUP(A489,[1]CALCULO_VR!$D:$D,[1]CALCULO_VR!$J:$J) -> 80 | X489: =_xlfn.XLOOKUP(A489,[1]CALCULO_VR!$D:$D,[1]CALCULO_VR!$O:$O) -> -12.262695 | Y489: =_xlfn.XLOOKUP(A489,[1]CALCULO_VR!$D:$D,[1]CALCULO_VR!$P:$P) -> -60.316668
A490: 2614653 | B490: JOAO CHAPINHA GAVIAO | C490: Ji-Paraná | D490: 45526 | E490: 45526 | F490: 34042.861 | G490: 1 | H490: 1 | J490: 0 | Q490: 59.118597 | R490: 2 | S490: 2 | T490: 247 | U490: 4 | W490: =_xlfn.XLOOKUP(A490,[1]CALCULO_VR!$D:$D,[1]CALCULO_VR!$J:$J) -> 80 | X490: =_xlfn.XLOOKUP(A490,[1]CALCULO_VR!$D:$D,[1]CALCULO_VR!$O:$O) -> -10.434188 | Y490: =_xlfn.XLOOKUP(A490,[1]CALCULO_VR!$D:$D,[1]CALCULO_VR!$P:$P) -> -61.653555
...

Sheet Planilha5
A1: UC | B1: Projeto | C1: Município | D1: SIGFI | E1: Latitude_UC | F1: Longitude_UC
A2: 2583786 | B2: MARINA ORO WIN | C2: Guajará-Mirim | D2: 80 | E2: -11.121458 | F2: -64.146052
A3: 2583809 | B3: MARCIO KARINTIANA | C3: Porto Velho | D3: 80 | E3: -9.320473 | F3: -64.064798
A4: 2583906 | B4: ETIENNE MEIRA SILVEIRA | C4: Guajará-Mirim | D4: 80 | E4: -10.960403 | F4: -65.265543
A5: 2583913 | B5: VANGILENE JABOTI | C5: Guajará-Mirim | D5: 80 | E5: -12.033205 | F5: -64.768957
A6: 2595032 | B6: IZAQUE CINTA LARGA | C6: Espigão D'Oeste | D6: 80 | E6: -11.085925 | F6: -60.75919
A7: 2595260 | B7: JOSE ROBERTO FERREIRA | C7: Pimenta Bueno | D7: 80 | E7: -12.239007 | F7: -60.389548
A8: 2614646 | B8: ARNALDO XISAH KULIHJA GAVIAO | C8: Ji-Paraná | D8: 80 | E8: -10.435408 | F8: -61.653773
A9: 2614691 | B9: ROGORO SURUI | C9: Cacoal | D9: 80 | E9: -11.10407 | F9: -61.351443
A10: 2614717 | B10: FRANCISCO PEREIRA DA SILVA | C10: Pimenta Bueno | D10: 80 | E10: -11.978637 | F10: -60.416905
A11: 2626135 | B11: MARENILSON LEITE DA COSTA | C11: Porto Velho | D11: 80 | E11: -8.209928 | F11: -63.16077
A12: 2626213 | B12: JOSE MARIA DE SOUSA | C12: Porto Velho | D12: 80 | E12: -8.138337 | F12: -62.963812
A13: 2626276 | B13: PAULO TUPARI | C13: São Miguel do Guaporé | D13: 80 | E13: -12.11957 | F13: -62.616018
... A16: 2787458 | B16: DEUZIANE MADEIRA DE SOUZA | C16: Vilhena | D16: 80 | E16: -12.520898 | F16: -60.29114

Sheet Amostra 1_6_extrato_erro_5%
A1: ODI | B1: Projeto | C1: Município | D1: Data Inicio | E1: Data Fim | F1: Custo(R$) | G1: Cons. | H1: Kit | I1: Regional | J1: Grupo | K1: Poste | L1: Rede AT km | M1: Rede BT km | N1: Medidor | O1: Trafo | P1: Equip. | Q1: VR | R1: Estrato | S1: regionale | T1: NGH | U1: NPH | V1: STATUS | W1: SIGFI | X1: Latitude_UC | Y1: Longitude_UC
A2: 2595147 | B2: POSTO DE SAUDE ALDEIA PALHAL | C2: Vilhena | D2: 45500 | E2: 45500 | F2: 34042.861 | G2: 1 | H2: 1 | J2: 0 | Q2: 144.5618 | R2: 6 | S2: 6 | T2: 118 | U2: 2 | W2: =_xlfn.XLOOKUP(A2,[1]CALCULO_VR!$D:$D,[1]CALCULO_VR!$J:$J) -> 80 | X2: =_xlfn.XLOOKUP(A2,[1]CALCULO_VR!$D:$D,[1]CALCULO_VR!$O:$O) -> -11.479878 | Y2: =_xlfn.XLOOKUP(A2,[1]CALCULO_VR!$D:$D,[1]CALCULO_VR!$P:$P) -> -60.460112
A3: 2595177 | B3: GERSON CINTA LARGA | C3: São Francisco do Guaporé | D3: 45504 | E3: 45504 | F3: 52970.941 | G3: 1 | H3: 1 | J3: 0 | Q3: 70.928033 | R3: 3 | S3: 3 | T3: 199 | U3: 2 | W3: =_xlfn.XLOOKUP(A3,[1]CALCULO_VR!$D:$D,[1]CALCULO_VR!$J:$J) -> 160 | X3: =_xlfn.XLOOKUP(A3,[1]CALCULO_VR!$D:$D,[1]CALCULO_VR!$O:$O) -> -12.408093 | Y3: =_xlfn.XLOOKUP(A3,[1]CALCULO_VR!$D:$D,[1]CALCULO_VR!$P:$P) -> -63.021408
A4: 2595236 | B4: POSTO DE SAUDE ALDEIA CAJUI | C4: São Francisco do Guaporé | D4: 45505 | E4: 45505 | F4: 34042.861 | G4: 1 | H4: 1 | J4: 0 | Q4: 70.937531 | R4: 3 | S4: 3 | T4: 199 | U4: 2 | W4: =_xlfn.XLOOKUP(A4,[1]CALCULO_VR!$D:$D,[1]CALCULO_VR!$J:$J) -> 80 | X4: =_xlfn.XLOOKUP(A4,[1]CALCULO_VR!$D:$D,[1]CALCULO_VR!$O:$O) -> -12.407253 | Y4: =_xlfn.XLOOKUP(A4,[1]CALCULO_VR!$D:$D,[1]CALCULO_VR!$P:$P) -> -63.020755
A5: 2595237 | B5: EIEEFM KON KOATT TUPARI | C5: São Francisco do Guaporé | D5: 45505 | E5: 45505 | F5: 34042.861 | G5: 1 | H5: 1 | J5: 0 | Q5: 70.910302 | R5: 3 | S5: 3 | T5: 199 | U5: 2 | W5: =_xlfn.XLOOKUP(A5,[1]CALCULO_VR!$D:$D,[1]CALCULO_VR!$J:$J) -> 80 | X5: =_xlfn.XLOOKUP(A5,[1]CALCULO_VR!$D:$D,[1]CALCULO_VR!$O:$O) -> -12.40728 | Y5: =_xlfn.XLOOKUP(A5,[1]CALCULO_VR!$D:$D,[1]CALCULO_VR!$P:$P) -> -63.02107
A6: 2595249 | B6: ROSEANE TENHARIN | C6: São Francisco do Guaporé | D6: 45500 | E6: 45500 | F6: 52970.941 | G6: 1 | H6: 1 | J6: 0 | Q6: 90.038796 | R6: 4 | S6: 4 | T6: 160 | U6: 2 | W6: =_xlfn.XLOOKUP(A6,[1]CALCULO_VR!$D:$D,[1]CALCULO_VR!$J:$J) -> 160 | X6: =_xlfn.XLOOKUP(A6,[1]CALCULO_VR!$D:$D,[1]CALCULO_VR!$O:$O) -> -12.34808 | Y6: =_xlfn.XLOOKUP(A6,[1]CALCULO_VR!$D:$D,[1]CALCULO_VR!$P:$P) -> -62.795132
A7: 2595250 | B7: OSMAR MAINTAKA TUPARI | C7: São Francisco do Guaporé | D7: 45500 | E7: 45500 | F7: 52970.941 | G7: 1 | H7: 1 | J7: 0 | Q7: 89.873976 | R7: 4 | S7: 4 | T7: 160 | U7: 2 | W7: =_xlfn.XLOOKUP(A7,[1]CALCULO_VR!$D:$D,[1]CALCULO_VR!$J:$J) -> 160 | X7: =_xlfn.XLOOKUP(A7,[1]CALCULO_VR!$D:$D,[1]CALCULO_VR!$O:$O) -> -12.347225 | Y7: =_xlfn.XLOOKUP(A7,[1]CALCULO_VR!$D:$D,[1]CALCULO_VR!$P:$P) -> -62.796425
A8: 2595269 | B8: EIEEFM KON KOATT TUPARI | C8: São Francisco do Guaporé | D8: 45506 | E8: 45506 | F8: 34042.861 | G8: 1 | H8: 1 | J8: 0 | Q8: 70.974094 | R8: 3 | S8: 3 | T8: 199 | U8: 2 | W8: =_xlfn.XLOOKUP(A8,[1]CALCULO_VR!$D:$D,[1]CALCULO_VR!$J:$J) -> 80 | X8: =_xlfn.XLOOKUP(A8,[1]CALCULO_VR!$D:$D,[1]CALCULO_VR!$O:$O) -> -12.41203 | Y8: =_xlfn.XLOOKUP(A8,[1]CALCULO_VR!$D:$D,[1]CALCULO_VR!$P:$P) -> -63.023502
A9: 2595272 | B9: WALDIR FIRMINO VALE | C9: São Francisco do Guaporé | D9: 45502 | E9: 45502 | F9: 52970.941 | G9: 1 | H9: 1 | J9: 0 | Q9: 89.869751 | R9: 4 | S9: 4 | T9: 160 | U9: 2 | W9: =_xlfn.XLOOKUP(A9,[1]CALCULO_VR!$D:$D,[1]CALCULO_VR!$J:$J) -> 160 | X9: =_xlfn.XLOOKUP(A9,[1]CALCULO_VR!$D:$D,[1]CALCULO_VR!$O:$O) -> -12.347462 | Y9: =_xlfn.XLOOKUP(A9,[1]CALCULO_VR!$D:$D,[1]CALCULO_VR!$P:$P) -> -62.796557
A10: 2583661 | B10: DIVINO GOMES LIMA | C10: Guajará-Mirim | D10: 45459 | E10: 45459 | F10: 34042.861 | G10: 1 | H10: 1 | J10: 0 | Q10: 54.60863 | R10: 3 | S10: 3 | T10: 199 | U10: 2 | W10: =_xlfn.XLOOKUP(A10,[1]CALCULO_VR!$D:$D,[1]CALCULO_VR!$J:$J) -> 80 | X10: =_xlfn.XLOOKUP(A10,[1]CALCULO_VR!$D:$D,[1]CALCULO_VR!$O:$O) -> -10.681757 | Y10: =_xlfn.XLOOKUP(A10,[1]CALCULO_VR!$D:$D,[1]CALCULO_VR!$P:$P) -> -64.832982
A11: 2583662 | B11: JOSE PEREIRA ALVES | C11: Guajará-Mirim | D11: 45458 | E11: 45458 | F11: 34042.861 | G11: 1 | H11: 1 | J11: 0 | Q11: 56.302057 | R11: 3 | S11: 3 | T11: 199 | U11: 2 | W11: =_xlfn.XLOOKUP(A11,[1]CALCULO_VR!$D:$D,[1]CALCULO_VR!$J:$J) -> 80 | X11: =_xlfn.XLOOKUP(A11,[1]CALCULO_VR!$D:$D,[1]CALCULO_VR!$O:$O) -> -10.673628 | Y11: =_xlfn.XLOOKUP(A11,[1]CALCULO_VR!$D:$D,[1]CALCULO_VR!$P:$P) -> -64.818818
A12: 2583663 | B12: ELIETE BIRA MACIEL | C12: Guajará-Mirim | D12: 45459 | E12: 45459 | F12: 34042.861 | G12: 1 | H12: 1 | J12: 0 | Q12: 56.649232 | R12: 3 | S12: 3 | T12: 199 | U12: 2 | W12: =_xlfn.XLOOKUP(A12,[1]CALCULO_VR!$D:$D,[1]CALCULO_VR!$J:$J) -> 80 | X12: =_xlfn.XLOOKUP(A12,[1]CALCULO_VR!$D:$D,[1]CALCULO_VR!$O:$O) -> -10.669567 | Y12: =_xlfn.XLOOKUP(A12,[1]CALCULO_VR!$D:$D,[1]CALCULO_VR!$P:$P) -> -64.816427
A13: 2583664 | B13: JOSE ELEUTERIO FILHO | C13: Guajará-Mirim | D13: 45459 | E13: 45459 | F13: 34042.861 | G13: 1 | H13: 1 | J13: 0 | Q13: 57.074959 | R13: 3 | S13: 3 | T13: 199 | U13: 2 | W13: =_xlfn.XLOOKUP(A13,[1]CALCULO_VR!$D:$D,[1]CALCULO_VR!$J:$J) -> 80 | X13: =_xlfn.XLOOKUP(A13,[1]CALCULO_VR!$D:$D,[1]CALCULO_VR!$O:$O) -> -10.674992 | Y13: =_xlfn.XLOOKUP(A13,[1]CALCULO_VR!$D:$D,[1]CALCULO_VR!$P:$P) -> -64.811327
... A17: 2583668 | B17: JOSE CASIMIRO DOS SANTOS | C17: Guajará-Mirim | D17: 45461 | E17: 45461 | F17: 34042.861 | G17: 1 | H17: 1 | J17: 0 | Q17: 60.379099 | R17: 3 | S17: 3 | T17: 199 | U17: 2 | W17: =_xlfn.XLOOKUP(A17,[1]CALCULO_VR!$D:$D,[1]CALCULO_VR!$J:$J) -> 80 | X17: =_xlfn.XLOOKUP(A17,[1]CALCULO_VR!$D:$D,[1]CALCULO_VR!$O:$O) -> -10.640712 | Y17: =_xlfn.XLOOKUP(A17,[1]CALCULO_VR!$D:$D,[1]CALCULO_VR!$P:$P) -> -64.788205
A18: 2583702 | B18: IRACEMA DA SILVA GOMES | C18: Guajará-Mirim | D18: 45458 | E18: 45458 | F18: 34042.861 | G18: 1 | H18: 1 | J18: 0 | Q18: 54.615242 | R18: 3 | S18: 3 | T18: 199 | U18: 2 | V18: Selecionado | W18: =_xlfn.XLOOKUP(A18,[1]CALCULO_VR!$D:$D,[1]CALCULO_VR!$J:$J) -> 80 | X18: =_xlfn.XLOOKUP(A18,[1]CALCULO_VR!$D:$D,[1]CALCULO_VR!$O:$O) -> -10.681718 | Y18: =_xlfn.XLOOKUP(A18,[1]CALCULO_VR!$D:$D,[1]CALCULO_VR!$P:$P) -> -64.832928
A19: 2583669 | B19: CICERO MACIEL DO NASCIMENTO | C19: Guajará-Mirim | D19: 45459 | E19: 45459 | F19: 34042.861 | G19: 1 | H19: 1 | J19: 0 | Q19: 57.711664 | R19: 3 | S19: 3 | T19: 199 | U19: 2 | W19: =_xlfn.XLOOKUP(A19,[1]CALCULO_VR!$D:$D,[1]CALCULO_VR!$J:$J) -> 80 | X19: =_xlfn.XLOOKUP(A19,[1]CALCULO_VR!$D:$D,[1]CALCULO_VR!$O:$O) -> -10.672623 | Y19: =_xlfn.XLOOKUP(A19,[1]CALCULO_VR!$D:$D,[1]CALCULO_VR!$P:$P) -> -64.805865
A20: 2585821 | B20: MARCELO ORO MON | C20: Nova Mamoré | D20: 45462 | E20: 45462 | F20: 34042.861 | G20: 1 | H20: 1 | J20: 0 | Q20: 27.488625 | R20: 1 | S20: 1 | T20: 130 | U20: 2 | W20: =_xlfn.XLOOKUP(A20,[1]CALCULO_VR!$D:$D,[1]CALCULO_VR!$J:$J) -> 80 | X20: =_xlfn.XLOOKUP(A20,[1]CALCULO_VR!$D:$D,[1]CALCULO_VR!$O:$O) -> -10.366032 | Y20: =_xlfn.XLOOKUP(A20,[1]CALCULO_VR!$D:$D,[1]CALCULO_VR!$P:$P) -> -65.082157
A21: 2583410 | B21: FRANCISCO ASSIS DE ALMEIDA | C21: Guajará-Mirim | D21: 45459 | E21: 45459 | F21: 34042.861 | G21: 1 | H21: 1 | J21: 0 | Q21: 57.249923 | R21: 3 | S21: 3 | T21: 199 | U21: 2 | W21: =_xlfn.XLOOKUP(A21,[1]CALCULO_VR!$D:$D,[1]CALCULO_VR!$J:$J) -> 80 | X21: =_xlfn.XLOOKUP(A21,[1]CALCULO_VR!$D:$D,[1]CALCULO_VR!$O:$O) -> -10.673652 | Y21: =_xlfn.XLOOKUP(A21,[1]CALCULO_VR!$D:$D,[1]CALCULO_VR!$P:$P) -> -64.809965
A22: 2583920 | B22: ESCOLA ENSINO FUNDAMENTAL VALDEMAR CABIXI | C22: Guajará-Mirim | D22: 45455 | E22: 45455 | F22: 34042.861 | G22: 1 | H22: 1 | J22: 0 | Q22: 129.99808 | R22: 6 | S22: 6 | T22: 118 | U22: 2 | W22: =_xlfn.XLOOKUP(A22,[1]CALCULO_VR!$D:$D,[1]CALCULO_VR!$J:$J) -> 80 | X22: =_xlfn.XLOOKUP(A22,[1]CALCULO_VR!$D:$D,[1]CALCULO_VR!$O:$O) -> -11.15186 | Y22: =_xlfn.XLOOKUP(A22,[1]CALCULO_VR!$D:$D,[1]CALCULO_VR!$P:$P) -> -64.19707
A23: 2583764 | B23: EVERLANI ORO WIN | C23: Guajará-Mirim | D23: 45456 | E23: 45456 | F23: 34042.861 | G23: 1 | H23: 1 | J23: 0 | Q23: 130.13093 | R23: 6 | S23: 6 | T23: 118 | U23: 2 | W23: =_xlfn.XLOOKUP(A23,[1]CALCULO_VR!$D:$D,[1]CALCULO_VR!$J:$J) -> 80 | X23: =_xlfn.XLOOKUP(A23,[1]CALCULO_VR!$D:$D,[1]CALCULO_VR!$O:$O) -> -11.150538 | Y23: =_xlfn.XLOOKUP(A23,[1]CALCULO_VR!$D:$D,[1]CALCULO_VR!$P:$P) -> -64.195328
A24: 2583766 | B24: WELINTON CABIXI MACURAP | C24: Guajará-Mirim | D24: 45456 | E24: 45456 | F24: 34042.861 | G24: 1 | H24: 1 | J24: 0 | Q24: 129.95073 | R24: 6 | S24: 6 | T24: 118 | U24: 2 | W24: =_xlfn.XLOOKUP(A24,[1]CALCULO_VR!$D:$D,[1]CALCULO_VR!$J:$J) -> 80 | X24: =_xlfn.XLOOKUP(A24,[1]CALCULO_VR!$D:$D,[1]CALCULO_VR!$O:$O) -> -11.152557 | Y24: =_xlfn.XLOOKUP(A24,[1]CALCULO_VR!$D:$D,[1]CALCULO_VR!$P:$P) -> -64.19777
A25: 2583767 | B25: FABRICIO ORO NAO CABIXI | C25: Guajará-Mirim | D25: 45457 | E25: 45457 | F25: 34042.861 | G25: 1 | H25: 1 | J25: 0 | Q25: 130.05216 | R25: 6 | S25: 6 | T25: 118 | U25: 2 | W25: =_xlfn.XLOOKUP(A25,[1]CALCULO_VR!$D:$D,[1]CALCULO_VR!$J:$J) -> 80 | X25: =_xlfn.XLOOKUP(A25,[1]CALCULO_VR!$D:$D,[1]CALCULO_VR!$O:$O) -> -11.15322 | Y25: =_xlfn.XLOOKUP(A25,[1]CALCULO_VR!$D:$D,[1]CALCULO_VR!$P:$P) -> -64.197018
A26: 2583768 | B26: TANIA ORO WIN CABIXI | C26: Guajará-Mirim | D26: 45457 | E26: 45457 | F26: 34042.861 | G26: 1 | H26: 1 | J26: 0 | Q26: 130.05496 | R26: 6 | S26: 6 | T26: 118 | U26: 2 | W26: =_xlfn.XLOOKUP(A26,[1]CALCULO_VR!$D:$D,[1]CALCULO_VR!$J:$J) -> 80 | X26: =_xlfn.XLOOKUP(A26,[1]CALCULO_VR!$D:$D,[1]CALCULO_VR!$O:$O) -> -11.154017 | Y26: =_xlfn.XLOOKUP(A26,[1]CALCULO_VR!$D:$D,[1]CALCULO_VR!$P:$P) -> -64.197268
A27: 2583769 | B27: ELIENETE ORO NAO CABIXI | C27: Guajará-Mirim | D27: 45457 | E27: 45457 | F27: 34042.861 | G27: 1 | H27: 1 | J27: 0 | Q27: 129.97582 | R27: 6 | S27: 6 | T27: 118 | U27: 2 | W27: =_xlfn.XLOOKUP(A27,[1]CALCULO_VR!$D:$D,[1]CALCULO_VR!$J:$J) -> 80 | X27: =_xlfn.XLOOKUP(A27,[1]CALCULO_VR!$D:$D,[1]CALCULO_VR!$O:$O) -> -11.148292 | Y27: =_xlfn.XLOOKUP(A27,[1]CALCULO_VR!$D:$D,[1]CALCULO_VR!$P:$P) -> -64.196057
A28: 2583770 | B28: ROMARIO ORO WIN | C28: Guajará-Mirim | D28: 45457 | E28: 45457 | F28: 34042.861 | G28: 1 | H28: 1 | J28: 0 | Q28: 130.04754 | R28: 6 | S28: 6 | T28: 118 | U28: 2 | W28: =_xlfn.XLOOKUP(A28,[1]CALCULO_VR!$D:$D,[1]CALCULO_VR!$J:$J) -> 80 | X28: =_xlfn.XLOOKUP(A28,[1]CALCULO_VR!$D:$D,[1]CALCULO_VR!$O:$O) -> -11.153937 | Y28: =_xlfn.XLOOKUP(A28,[1]CALCULO_VR!$D:$D,[1]CALCULO_VR!$P:$P) -> -64.197312
A29: 2585862 | B29: ROSILEIA ORO MON | C29: Nova Mamoré | D29: 45462 | E29: 45462 | F29: 34042.861 | G29: 1 | H29: 1 | J29: 0 | Q29: 27.487788 | R29: 1 | S29: 1 | T29: 130 | U29: 2 | W29: =_xlfn.XLOOKUP(A29,[1]CALCULO_VR!$D:$D,[1]CALCULO_VR!$J:$J) -> 80 | X29: =_xlfn.XLOOKUP(A29,[1]CALCULO_VR!$D:$D,[1]CALCULO_VR!$O:$O) -> -10.365348 | Y29: =_xlfn.XLOOKUP(A29,[1]CALCULO_VR!$D:$D,[1]CALCULO_VR!$P:$P) -> -65.082297
